Workbook

Sheet Cover
B2: TEST REPORT DOCUMENT
A4: Project Name | B4: PharmaChain – Smart Pharmacy Chain Management System | E4: Creator | F4: Tran Hong Phuoc (DE180577)
A5: Project Code | B5: WPE | E5: Issue Date | F5: 17/09/2026
A6: Document Code | B6: Report5_Test_v1.0 | E6: Version | F6: v1.1
A9: Record of change
A10: Effective Date | B10: Version | C10: Change Item | D10: *A,D,M | E10: Change description | F10: Reference
A11: 17/09/2026 | B11: v1.0 | C11: Test Cases & Test Statistics | D11: A | E11: Complete master list of 65 functions across Sprint 1 to Sprint 4 in English matching SRS v1.0 | F11: Report 3 – Software Requirements Specification (SRS)
A12: 01/10/2026 | B12: v1.1 | C12: Test Cases & Statistics (UC-66 to UC-120) | D12: A | E12: Extended full enterprise test suite with UC-66 to UC-120 covering Sprint 5 to Sprint 8 | F12: Report 4 – Software Design Document (SDD v2.0)

Sheet Test Cases
B1: TEST CASE LIST
B3: Project Name | C3: PharmaChain – Smart Pharmacy Chain Management System
B4: Project Code | C4: WDP301
B6: Test Environment Setup Description | C6: 1. Server: Ubuntu Server 24.04 LTS (Docker, K8s, Kafka, Redis, MongoDB) 2. Backend: NestJS Microservices, API Gateway 3. Web & Mobile: React 19, Expo React Native 4. Database: MongoDB 7.0 5. Web Browser: Google Chrome, Microsoft Edge
B8: No | C8: Name | D8: Sheet Name | E8: Description | F8: Pre-Condition
B9: Feature Authentication
B10: 1 | C10: [UC-01] Register account | D10: Authentication | E10: Allows customers to register a new personal account in the system using an email address and password. | F10: Actor 'Customer' authenticated; test environment master data pre-seeded.
B11: 2 | C11: [UC-02] Sign in | D11: Authentication | E11: Allows users to log in to the system using their registered or assigned account credentials. | F11: Actor 'Customer, Pharmacist, Inventory Manager, Admin, Branch Manager' authenticated; test environment master data pre-seeded.
B12: 3 | C12: [UC-03] Verify email | D12: Authentication | E12: Allows customers to confirm the activation code sent to their personal email after successful account registration. | F12: Actor 'Customer, Pharmacist, Branch Manager' authenticated; test environment master data pre-seeded.
B13: 4 | C13: [UC-04] Sign in with Google | D13: Authentication | E13: Allows customers to quickly log in to the online shopping portal using their Google account. | F13: Actor 'Customer' authenticated; test environment master data pre-seeded.
B14: 5 | C14: [UC-05] Recover password | D14: Authentication | E14: Allows staff to send a password recovery request via email when they forget their login credentials. | F14: Actor 'Pharmacist, Inventory Manager, Admin, Branch Manager' authenticated; test environment master data pre-seeded.
B15: 6 | C15: [UC-06] Reset password | D15: Authentication | E15: Allows staff to set a new password via a secure link sent to their recovery email. | F15: Actor 'Pharmacist, Inventory Manager, Admin, Branch Manager' authenticated; test environment master data pre-seeded.
B16: 7 | C16: [UC-07] Sign out | D16: Authentication | E16: Terminates the current session and safely logs out of the system account. | F16: Actor 'Customer, Pharmacist, Inventory Manager, Admin, Branch Manager' authenticated; test environment master data pre-seeded.
B17: 8 | C17: [UC-113] Biometric Mobile Authentication (FaceID/Fingerprint) | D17: Authentication | E17: Integrates iOS FaceID and Android BiometricPrompt for cryptographic token exchange without manual password input. | F17: Device hardware supports biometric sensors; app enrolled.
B18: Feature Online Customer Portal
B19: 9 | C19: [UC-08] Search medicines online | D19: Customer Portal | E19: Browse and search for medicines by name, active ingredient, or medical indication on the online store. | F19: Actor 'Customer' authenticated; test environment master data pre-seeded.
B20: 10 | C20: [UC-09] Add to cart | D20: Customer Portal | E20: Allow customers to save desired pharmaceutical products into their personal cart for later checkout. | F20: Actor 'Customer' authenticated; test environment master data pre-seeded.
B21: 11 | C21: [UC-10] Manage personal cart | D21: Customer Portal | E21: Allow customers to adjust quantities or remove products from their online cart. | F21: Actor 'Customer' authenticated; test environment master data pre-seeded.
B22: 12 | C22: [UC-11] Confirm online order | D22: Customer Portal | E22: Fill in full name, phone number, shipping address, and confirm submission of online order. | F22: Actor 'Customer' authenticated; test environment master data pre-seeded.
B23: 13 | C23: [UC-12] Pay online order | D23: Customer Portal | E23: Complete online payment via bank transfer using dynamic QR code or COD. | F23: Actor 'Customer' authenticated; test environment master data pre-seeded.
B24: 14 | C24: [UC-13] View order history | D24: Customer Portal | E24: View list of past orders, detailed order items, and shipping status. | F24: Actor 'Customer' authenticated; test environment master data pre-seeded.
B25: 15 | C25: [UC-14] View customer profile | D25: Customer Portal | E25: View personal information, accumulated points, and current tier status (Gold, Silver, Bronze...). | F25: Actor 'Customer' authenticated; test environment master data pre-seeded.
B26: 16 | C26: [UC-15] Consult AI via text | D26: Customer Portal | E26: Enter symptom description questions; chatbot automatically analyzes and suggests health guidance & recommended products. | F26: Actor 'Customer' authenticated; test environment master data pre-seeded.
B27: 17 | C27: [UC-16] Consult AI via voice | D27: Customer Portal | E27: Press record button to describe symptoms via voice; AI automatically recognizes speech and converts to text for consultation. | F27: Actor 'Customer' authenticated; test environment master data pre-seeded.
B28: 18 | C28: [UC-80] AI Symptom Consultation Chatbot | D28: Customer Portal | E28: Provides automated interactive AI consultation based on symptoms, recommends OTC relief medicines, and refers to doctors if severe. | F28: Actor 'Customer' authenticated; Gemini AI engine online.
B29: 19 | C29: [UC-81] AI Voice Medicine Search | D29: Customer Portal | E29: Recognizes spoken medical queries in Vietnamese/English, transliterating brand names to generic INN drug names with autocomplete. | F29: Microphone permissions granted; WebSpeech/Whisper API operational.
B30: 20 | C30: [UC-85] Order & Transaction Cancellation | D30: Customer Portal | E30: Processes transaction voiding, order cancellation with mandatory reason codes, stock replenishment rollbacks, and audit logging. | F30: Actor 'Pharmacist, Branch Manager' authenticated; target order in pending/unsettled state.
... B41: 31 | C41: [UC-118] Recurring Medication Auto-Reorder Management | D41: Customer Portal | E41: Schedules monthly repeat prescription dispensations for chronic conditions (hypertension, diabetes), auto-preparing order 3 days in advance. | F41: Customer enrolled in recurring prescription auto-refill plan.
B42: Feature Pharmacist POS Counter Terminal
B43: 32 | C43: [UC-17] Search retail medicines | D43: Pharmacist POS | E43: Quickly search for medicines by name or active ingredient directly on the counter retail screen. | F43: Actor 'Pharmacist' authenticated; test environment master data pre-seeded.
B44: 33 | C44: [UC-18] Add to retail cart | D44: Pharmacist POS | E44: Select medicines from search results and add them to the customer's active retail shopping cart. | F44: Actor 'Pharmacist' authenticated; test environment master data pre-seeded.
B45: 34 | C45: [UC-19] Edit retail cart | D45: Pharmacist POS | E45: Change purchase quantity of each medicine or remove items from the retail cart. | F45: Actor 'Pharmacist' authenticated; test environment master data pre-seeded.
B46: 35 | C46: [UC-20] Suggest substitute medicine | D46: Pharmacist POS | E46: System automatically suggests equivalent substitute medicines (matching active ingredient or therapeutic group) when requested item is out of stock. | F46: Actor 'Pharmacist' authenticated; test environment master data pre-seeded.
B47: 36 | C47: [UC-21] Apply voucher and points | D47: Pharmacist POS | E47: Look up loyalty customer information by phone number to earn reward points or apply discount voucher codes directly to the invoice. | F47: Actor 'Pharmacist' authenticated; test environment master data pre-seeded.
B48: 37 | C48: [UC-22] Scan prescription with AI | D48: Pharmacist POS | E48: Capture/upload doctor prescription photos (single/multi-page). AI Gemini 2.5 Flash analyzes layout, extracts active ingredients/dosages, merges duplicates, matches branch DB & auto-selects nearest FEFO batch to auto-fill cart. | F48: Actor 'Pharmacist' authenticated; test environment master data pre-seeded.
B49: 38 | C49: [UC-23] Check medicine interactions | D49: Pharmacist POS | E49: Select multiple medicines in cart to trigger AI verification for interactions or harmful contraindication warnings. | F49: Actor 'Pharmacist' authenticated; test environment master data pre-seeded.
B50: 39 | C50: [UC-24] Confirm retail payment | D50: Pharmacist POS | E50: Confirm transactions via Cash or Bank Transfer. System automatically deducts branch stock based on FIFO batches and prints invoices. | F50: Actor 'Pharmacist' authenticated; test environment master data pre-seeded.
B51: 40 | C51: [UC-25] Send e-invoice via email | D51: Pharmacist POS | E51: Allows entering customer email at counter to send electronic invoice (e-invoice) directly upon payment completion. | F51: Actor 'Pharmacist' authenticated; test environment master data pre-seeded.
B52: 41 | C52: [UC-26] Create wholesale invoice | D52: Pharmacist POS | E52: Issue wholesale invoices for agency partners, automatically applying tier pricing based on large volume purchases. | F52: Actor 'Pharmacist' authenticated; test environment master data pre-seeded.
B53: 42 | C53: [UC-27] Search return invoice | D53: Pharmacist POS | E53: Search past invoices by customer phone number or invoice code to verify purchase origin prior to executing returns. | F53: Actor 'Pharmacist' authenticated; test environment master data pre-seeded.
B54: 43 | C54: [UC-28] Create return slip | D54: Pharmacist POS | E54: Create return slips recording return reasons (defective goods, near-expiry...), execute customer refunds, and restock counter inventory. | F54: Actor 'Pharmacist' authenticated; test environment master data pre-seeded.
... B60: 49 | C60: [UC-111] Pharmacist Sales KPI & Target Tracking | D60: Pharmacist POS | E60: Tracks daily counter turnover, OTC attachment rates, customer review scores, and commission bonuses against assigned branch quotas. | F60: Monthly branch sales targets configured.
B61: Feature Central Warehouse & FEFO Inventory
B62: 50 | C62: [UC-29] View medicine catalog | D62: Central Warehouse | E62: Displays a complete list of medicines in the system with active ingredient, medicine category, unit, and base price. | F62: Actor 'Admin, Inventory Manager, Pharmacist' authenticated; test environment master data pre-seeded.
B63: 51 | C63: [UC-30] View inventory by batch | D63: Central Warehouse | E63: Display actual stock details per product including batch number (`batchNo`), expiry date (`expDate`), and available stock quantity. | F63: Actor 'Inventory Manager, Admin' authenticated; test environment master data pre-seeded.
B64: 52 | C64: [UC-31] Create goods receipt | D64: Central Warehouse | E64: Create a new receiving session for goods delivered by supplier based on an approved Purchase Order (PO). | F64: Actor 'Inventory Manager' authenticated; test environment master data pre-seeded.
B65: 53 | C65: [UC-32] Create purchase order (PO) | D65: Central Warehouse | E65: Create new purchase orders (PO) to submit to Admin for approval before submitting to suppliers. | F65: Actor 'Inventory Manager' authenticated; test environment master data pre-seeded.
B66: 54 | C66: [UC-33] Inspect goods via AI | D66: Central Warehouse | E66: Capture images of shipment packages using mobile device; AI automatically counts actual medicine boxes in shipment to populate receipt. | F66: Actor 'Inventory Manager' authenticated; test environment master data pre-seeded.
B67: 55 | C67: [UC-34] Alert expiry dates | D67: Central Warehouse | E67: Report detailed lists of near-expiry batches (under 6 months / 3 months) or expired items to plan for disposal/write-offs. | F67: Actor 'Inventory Manager, Admin' authenticated; test environment master data pre-seeded.
B68: 56 | C68: [UC-35] Track medicine lot | D68: Central Warehouse | E68: Enter batch number (`batchNo`) to trace full supplier history, PO, GRN, and display quantity fluctuation timeline for that batch. | F68: Actor 'Inventory Manager, Admin' authenticated; test environment master data pre-seeded.
B69: 57 | C69: [UC-87] Barcode Scanning Goods Receipt | D69: Central Warehouse | E69: Scans GS1-128 / DataMatrix barcodes on supplier cartons, auto-populating batch number, manufacturing date, and expiry date into GRN. | F69: Physical shipment delivered; barcode scanner paired.
B70: 58 | C70: [UC-88] Barcode Scanning Stock Dispatch | D70: Central Warehouse | E70: Scans picking item barcodes to verify SKU match against outgoing transfer orders or courier delivery shipments before seal. | F70: Stock dispatch order approved; picking items staged.
B71: 59 | C71: [UC-89] Barcode Scanner Inventory Audit | D71: Central Warehouse | E71: Conducts cyclical GSP shelf stocktaking with hand-held wireless barcode terminal, reporting instant variance against ERP system stock. | F71: Stocktaking session initiated; warehouse zone assigned.
B72: 60 | C72: [UC-90] GSP Bin & Rack Warehouse Location Management | D72: Central Warehouse | E72: Manages 2D/3D warehouse storage map, allocating fast-moving items to ergonomic lower tiers and cold-chain items to monitored chilled bins. | F72: Warehouse zone layout pre-configured.
B73: 61 | C73: [UC-94] Negative & Discrepancy Stock Alert | D73: Central Warehouse | E73: Intercepts abnormal negative inventory deductions, triggering audit quarantine and dispatching instant alert to store manager. | F73: Real-time stock ledger service running.
B74: Feature Branch Store Management
B75: 62 | C75: [UC-36] View branch stock | D75: Branch Management | E75: Quickly look up actual physical stock quantities of medicines at the managed branch. | F75: Actor 'Branch Manager' authenticated; test environment master data pre-seeded.
B76: 63 | C76: [UC-37] Request stock requisition | D76: Branch Management | E76: Create stock replenishment requests sent to central warehouse when branch counters experience shortages or out-of-stock items. | F76: Actor 'Branch Manager' authenticated; test environment master data pre-seeded.
B77: 64 | C77: [UC-38] Request internal transfer | D77: Branch Management | E77: Create stock transfer slips to ship goods to neighboring branches to resolve cross-branch stock imbalances. | F77: Actor 'Branch Manager' authenticated; test environment master data pre-seeded.
B78: 65 | C78: [UC-39] Approve stock replenishment | D78: Branch Management | E78: Review Requisition requests submitted by branches and approve dispatch of goods from central warehouse. | F78: Actor 'Inventory Manager' authenticated; test environment master data pre-seeded.
B79: 66 | C79: [UC-40] Confirm transfer receipt | D79: Branch Management | E79: Receive goods delivered from central warehouse, verify physical count, and click confirm to synchronize and update destination stock. | F79: Actor 'Branch Manager' authenticated; test environment master data pre-seeded.
B80: 67 | C80: [UC-93] Branch-specific Pricing Policy | D80: Branch Management | E80: Configures regional price overrides, tier markups, and localized promotional margins per branch location. | F80: Branch network registered; base catalog pricing established.
B81: 68 | C81: [UC-100] Delivery Proof & Shipper QR Scanner | D81: Branch Management | E81: Internal pharmacy shipper scans recipient QR code and captures e-signature photo as cryptographic proof of handover. | F81: Shipper assigned to dispatch route; mobile camera enabled.
B82: 69 | C82: [UC-115] Offline Data Synchronization & Conflict Resolution | D82: Branch Management | E82: Allows POS counter to continue dispensing sales during WAN network outages with local SQLite storage, auto-syncing with Kafka upon reconnection. | F82: Offline cache database operational on local POS terminal.
B83: Feature HQ Governance & Master Data
B84: 70 | C84: [UC-41] View staff list | D84: HQ Governance | E84: Displays a table listing all employees in the pharmacy chain with detailed information on role, work shift, branch, and activation status. | F84: Actor 'Admin, Branch Manager' authenticated; test environment master data pre-seeded.
B85: 71 | C85: [UC-42] Create staff account | D85: HQ Governance | E85: Allows Branch Manager to create new accounts for pharmacists and counter staff members at their branch. | F85: Actor 'Branch Manager' authenticated; test environment master data pre-seeded.
B86: 72 | C86: [UC-43] Approve staff account | D86: HQ Governance | E86: Allows Admin or Branch Manager to review and approve newly registered staff accounts. | F86: Actor 'Admin, Branch Manager' authenticated; test environment master data pre-seeded.
B87: 73 | C87: [UC-44] Reject staff account | D87: HQ Governance | E87: Allows Admin or Branch Manager to reject new staff registration requests. | F87: Actor 'Admin, Branch Manager' authenticated; test environment master data pre-seeded.
B88: 74 | C88: [UC-45] Create branch manager account | D88: HQ Governance | E88: Allows HQ Admin to create new branch manager accounts and grant branch management permissions. | F88: Actor 'Admin' authenticated; test environment master data pre-seeded.
B89: 75 | C89: [UC-46] Update staff role | D89: HQ Governance | E89: Allows Admin to update staff profile, assign job roles, and reassign branch locations. | F89: Actor 'Admin' authenticated; test environment master data pre-seeded.
B90: 76 | C90: [UC-47] Add medicine | D90: HQ Governance | E90: Create a new medicine and fill in identification attributes, packaging specifications, and usage instructions. | F90: Actor 'Admin' authenticated; test environment master data pre-seeded.
B91: 77 | C91: [UC-48] Update medicine | D91: HQ Governance | E91: Edit medicine attributes, descriptions, images, or classification categories in the system catalog. | F91: Actor 'Admin' authenticated; test environment master data pre-seeded.
B92: 78 | C92: [UC-49] View supplier list | D92: HQ Governance | E92: Displays contact information, supplier code, and reliability rating of suppliers. | F92: Actor 'Admin, Inventory Manager' authenticated; test environment master data pre-seeded.
B93: 79 | C93: [UC-50] Add supplier | D93: HQ Governance | E93: Register new pharmaceutical supplier information and store legal profiles in the system. | F93: Actor 'Admin' authenticated; test environment master data pre-seeded.
B94: 80 | C94: [UC-51] Update supplier | D94: HQ Governance | E94: Adjust contact information, GDP license expiration date, or supplier credit terms. | F94: Actor 'Admin' authenticated; test environment master data pre-seeded.
B95: 81 | C95: [UC-91] SKU Code Generation & GS1 Barcode Generator | D95: HQ Governance | E95: Generates compliant GS1 EAN-13 barcodes with checksum digits and standardized internal SKU hierarchy for newly registered medicines. | F95: Medicine catalog entry created with active ingredient classification.
... B100: 86 | C100: [UC-120] System Multilingual Localization (VI/EN) | D100: HQ Governance | E100: Provides seamless real-time UI localization between Vietnamese and English across web portal, mobile app, and receipt printing. | F100: i18n translation dictionary loaded for target language.
B101: Feature Corporate Finance & AI Supply Chain
B102: 87 | C102: [UC-52] View revenue dashboard | D102: Finance & AI Supply Chain | E102: View revenue charts over time, transaction counts, total payables/receivables, and chain-wide operational performance. | F102: Actor 'Admin' authenticated; test environment master data pre-seeded.
B103: 88 | C103: [UC-53] Compare branch performance | D103: Finance & AI Supply Chain | E103: Display comparative ranking tables for sales volume, transaction counts, and growth rates across all branch locations. | F103: Actor 'Admin' authenticated; test environment master data pre-seeded.
B104: 89 | C104: [UC-54] Approve purchase order (PO) | D104: Finance & AI Supply Chain | E104: Approve Purchase Orders (PO) sent to suppliers and configure payment methods. | F104: Actor 'Admin' authenticated; test environment master data pre-seeded.
B105: 90 | C105: [UC-55] Reject purchase order (PO) | D105: Finance & AI Supply Chain | E105: Reject approval of purchase order PO and record rejection reasons. | F105: Actor 'Admin' authenticated; test environment master data pre-seeded.
B106: 91 | C106: [UC-56] Approve goods receipt note (GRN) | D106: Finance & AI Supply Chain | E106: Sign and approve physical inspection receipt from warehouse manager to confirm official entry, increase total stock, and activate new batches. | F106: Actor 'Admin' authenticated; test environment master data pre-seeded.
B107: 92 | C107: [UC-57] Reject goods receipt note (GRN) | D107: Finance & AI Supply Chain | E107: Reject physical inspection receipt (GRN) from warehouse manager and record rejection reasons for re-verification. | F107: Actor 'Admin' authenticated; test environment master data pre-seeded.
B108: 93 | C108: [UC-58] Manage promotions | D108: Finance & AI Supply Chain | E108: Create percentage/cash discount voucher codes, set up Flash Sale events for designated time slots. | F108: Actor 'Admin' authenticated; test environment master data pre-seeded.
B109: 94 | C109: [UC-59] Manage cash flow | D109: Finance & AI Supply Chain | E109: View financial cash flow reports, enter fixed operational expenses (rent, salaries, utilities...) of branches. | F109: Actor 'Admin' authenticated; test environment master data pre-seeded.
B110: 95 | C110: [UC-60] Query audit logs | D110: Finance & AI Supply Chain | E110: Retrieve audit log records tracking critical business operations performed by staff for security compliance. | F110: Actor 'Admin' authenticated; test environment master data pre-seeded.
B111: 96 | C111: [UC-61] Forecast demand | D111: Finance & AI Supply Chain | E111: System automatically analyzes sales volume and actual inventory levels to suggest replenishment order quantities from suppliers. | F111: Actor 'Inventory Manager, Admin' authenticated; test environment master data pre-seeded.
B112: 97 | C112: [UC-62] Auto-generate PO from AI forecast | D112: Finance & AI Supply Chain | E112: Allows converting AI Economic Order Quantity (EOQ) replenishment recommendations directly into an official Purchase Order (PO) with one click. | F112: Actor 'Inventory Manager, Admin' authenticated; test environment master data pre-seeded.
B113: 98 | C113: [UC-63] Detect inventory anomalies with AI | D113: Finance & AI Supply Chain | E113: AI system automatically detects and alerts unusual inventory fluctuations such as export spikes, critically low stock, or abnormal inventory adjustments. | F113: Actor 'Inventory Manager, Admin' authenticated; test environment master data pre-seeded.
... B128: 113 | C128: [UC-110] AI Best Procurement Price & Supplier Routing | D128: Finance & AI Supply Chain | E128: Optimizes purchase order splitting across competing suppliers to achieve minimum total landed cost considering delivery lead time. | F128: Pending bulk purchase requisition active.
B129: Feature Extended Operations & IoT Compliance
B130: 114 | C130: [UC-78] Import Medicine Auxiliary Label & Barcode Printing | D130: Extended Operations & IoT | E130: Generates and prints Ministry of Health compliant secondary auxiliary Vietnamese labels and thermal EAN-13 barcodes for imported items. | F130: Actor 'Warehouse Staff' authenticated; thermal label printer connected.
B131: 115 | C131: [UC-79] Multi-Supplier Bulk RFQ Quotation | D131: Extended Operations & IoT | E131: Dispatches Request for Quotation (RFQ) packages to multiple GDP pharma suppliers simultaneously and parses supplier bid responses. | F131: Actor 'Procurement Officer' authenticated; supplier master directory pre-seeded.
B132: 116 | C132: [UC-82] IoT Central Warehouse Telemetry & Alerts | D132: Extended Operations & IoT | E132: Captures real-time temperature, humidity, and power backup telemetry from GSP warehouse cold storage sensors with breach alarms. | F132: IoT sensor gateway emitting MQTT telemetry to Kafka topic 'sensor.telemetry.ingest'.
B133: 117 | C133: [UC-102] Narcotic & Restricted Medicine Compliance Log | D133: Extended Operations & IoT | E133: Maintains tamper-proof Ministry of Health special register for habit-forming narcotics, recording patient identity number and prescriber licence. | F133: Prescription contains Schedule II/III restricted substances.
B134: 118 | C134: [UC-112] Disaster Recovery Backup & Manual Restore Log | D134: Extended Operations & IoT | E134: Initiates point-in-time MongoDB Atlas snapshots, verifies offsite S3 cold storage archives, and audits emergency restore trial runs. | F134: Admin master credentials authenticated; backup service online.
B135: 119 | C135: [UC-114] IoT Device Management & Sensor Calibration | D135: Extended Operations & IoT | E135: Registers LoRaWAN/Zigbee temperature probes, schedules annual GSP calibration cycles, and sets drift offset coefficients. | F135: Sensor hardware UUID provisioned on network.
B136: 120 | C136: [UC-116] Retail Customer Debt Limit & Aging Schedule | D136: Extended Operations & IoT | E136: Tracks credit receivables for regular chronic patients, enforcing maximum credit balances and generating 30/60/90-day aging debt notices. | F136: Customer credit account approved by store manager.

Sheet Test Statistics
B1: TEST STATISTICS
B3: Project Name | C3: PharmaChain – Smart Pharmacy Chain Management System | E3: Creator | G3: Tran Hong Phuoc (DE180577)
B4: Project Code | C4: WDP301 | E4: Reviewer/Approver | G4: Nguyen Van Nam (DE180564)
B5: Document Code | C5: WDP301_Test Report_v1.2 | E5: Issue Date | G5: 07/10/2026
B6: Notes | C6: Release includes all 8 Modules across Sprints 1 to 8 (120 UCs / 360 TCs)
B10: No | C10: Module code | D10: Passed | E10: Failed | F10: Pending | G10: N/A | H10: Number of test cases
B11: 1 | C11: Feature Authentication | D11: ='FE-01_Authentication'!B6 | E11: ='FE-01_Authentication'!C6 | F11: ='FE-01_Authentication'!D6 | G11: ='FE-01_Authentication'!E6 | H11: ='FE-01_Authentication'!B4
B12: 2 | C12: Feature Online Customer Portal | D12: ='FE-02_Customer Portal'!B6 | E12: ='FE-02_Customer Portal'!C6 | F12: ='FE-02_Customer Portal'!D6 | G12: ='FE-02_Customer Portal'!E6 | H12: ='FE-02_Customer Portal'!B4
B13: 3 | C13: Feature Pharmacist POS Counter Terminal | D13: ='FE-03_Pharmacist POS'!B6 | E13: ='FE-03_Pharmacist POS'!C6 | F13: ='FE-03_Pharmacist POS'!D6 | G13: ='FE-03_Pharmacist POS'!E6 | H13: ='FE-03_Pharmacist POS'!B4
B14: 4 | C14: Feature Central Warehouse & FEFO Inventory | D14: ='FE-04_Central Warehouse'!B6 | E14: ='FE-04_Central Warehouse'!C6 | F14: ='FE-04_Central Warehouse'!D6 | G14: ='FE-04_Central Warehouse'!E6 | H14: ='FE-04_Central Warehouse'!B4
B15: 5 | C15: Feature Branch Store Management | D15: ='FE-05_Branch Management'!B6 | E15: ='FE-05_Branch Management'!C6 | F15: ='FE-05_Branch Management'!D6 | G15: ='FE-05_Branch Management'!E6 | H15: ='FE-05_Branch Management'!B4
B16: 6 | C16: Feature HQ Governance & Master Data | D16: ='FE-06_HQ Governance'!B6 | E16: ='FE-06_HQ Governance'!C6 | F16: ='FE-06_HQ Governance'!D6 | G16: ='FE-06_HQ Governance'!E6 | H16: ='FE-06_HQ Governance'!B4
B17: 7 | C17: Feature Corporate Finance & AI Supply Chain | D17: ='FE-07_Finance & AI Supply Chain'!B6 | E17: ='FE-07_Finance & AI Supply Chain'!C6 | F17: ='FE-07_Finance & AI Supply Chain'!D6 | G17: ='FE-07_Finance & AI Supply Chain'!E6 | H17: ='FE-07_Finance & AI Supply Chain'!B4
B18: 8 | C18: Feature Extended Operations & IoT Compliance | D18: ='FE-08_Extended Operations & IoT'!B6 | E18: ='FE-08_Extended Operations & IoT'!C6 | F18: ='FE-08_Extended Operations & IoT'!D6 | G18: ='FE-08_Extended Operations & IoT'!E6 | H18: ='FE-08_Extended Operations & IoT'!B4
C19: Sub total | D19: =SUM(D11:D18) | E19: =SUM(E11:E18) | F19: =SUM(F11:F18) | G19: =SUM(G11:G18) | H19: =SUM(H11:H18)
C21: Test coverage | E21: =(D19+E19)/(H19-G19)
C22: Test successful coverage | E22: =D19/(H19-G19)

Sheet FE-01_Authentication
A2: Feature | B2: Feature Authentication
A3: Test requirement | B3: User account authentication and identity management: user registration, credential login, Google OAuth2, email OTP verification, secure password recovery and reset, and mobile biometric authentication (FaceID/Fingerprint).
A4: Number of TCs | B4: =SUM(B6:E6)
A5: Testing Round | B5: Passed | C5: Failed | D5: Pending | E5: N/A
A6: Round 1 | B6: =COUNTIF($F$11:$F$999,B$5) | C6: =COUNTIF($F$11:$F$999,C$5) | D6: =COUNTIF($F$11:$F$999,D$5) | E6: =COUNTIF($F$11:$F$999,E$5)
A7: Round 2 | B7: =COUNTIF($I$11:$I$999,B$5) | C7: =COUNTIF($I$11:$I$999,C$5) | D7: =COUNTIF($I$11:$I$999,D$5) | E7: =COUNTIF($I$11:$I$999,E$5)
A8: Round 3 | B8: =COUNTIF($L$11:$L$999,B$5) | C8: =COUNTIF($L$11:$L$999,C$5) | D8: =COUNTIF($L$11:$L$999,D$5) | E8: =COUNTIF($L$11:$L$999,E$5)
A10: Test Case ID | B10: Test Case Description | C10: Test Case Procedure | D10: Expected Results | E10: Pre-conditions | F10: Round 1 | G10: Test date | H10: Tester | I10: Round 2 | J10: Test date | K10: Tester | L10: Round 3 | M10: Test date | N10: Tester | O10: Note
A11: UC-01. Function Register account
A12: UC01-TC1 | B12: Verify successful execution of 'Register account' (Happy Path). | C12: 1. Access system with role 'Customer'. 2. Navigate to 'Register account' function. 3. Enter valid and complete required parameters. 4. Submit and verify system response. | D12: 1. System validates inputs and processes successfully. 2. Confirmation message displayed. 3. Data persisted to MongoDB and synchronized via Kafka. 4. Screen state transitions to corresponding post-action view. | E12: Actor 'Customer' authenticated; test environment master data pre-seeded. | F12: Passed | G12: 15/09/2026 | H12: Tran Hong Phuoc (DE180577) | I12: Passed | J12: 17/09/2026 | K12: Nguyen Van Nam (DE180564) | L12: Passed | M12: 19/09/2026 | N12: Tran Hong Phuoc (DE180577) | O12: HTTP 200/201 OK. Response time: 45ms. Data persisted to MongoDB and event emitted to Kafka.
A13: UC01-TC2 | B13: Verify validation and error handling for 'Register account' with invalid/missing inputs (Negative Path). | C13: 1. Access system with role 'Customer'. 2. Navigate to 'Register account' function. 3. Leave mandatory fields blank or enter invalid data format. 4. Attempt to submit. 5. Observe validation error warnings. | D13: 1. System blocks submission. 2. Clear error alerts displayed for invalid fields. 3. No corrupted data is written to Database. 4. Form inputs preserved for correction. | E13: Actor 'Customer' authenticated. | F13: Passed | G13: 15/09/2026 | H13: Nguyen Van Nam (DE180564) | I13: Passed | J13: 17/09/2026 | K13: Tran Hong Phuoc (DE180577) | L13: Passed | M13: 19/09/2026 | N13: Nguyen Van Nam (DE180564) | O13: HTTP 400 Bad Request returned with descriptive validation error message.
A14: UC01-TC3 | B14: Verify boundary values, concurrency, or security constraints for 'Register account' (Edge Path). | C14: 1. Access 'Register account' function. 2. Test boundary lengths, duplicate submissions, or unauthorized role access. 3. Observe system defense and audit logging. | D14: 1. Boundary conditions handled gracefully. 2. Concurrency locks prevent duplicate processing. 3. RBAC security permissions enforced and audit log recorded. | E14: Actor 'Customer' authenticated. | F14: Passed | G14: 15/09/2026 | H14: Tran Hong Phuoc (DE180577) | I14: Passed | J14: 17/09/2026 | K14: Nguyen Van Nam (DE180564) | L14: Passed | M14: 19/09/2026 | N14: Tran Hong Phuoc (DE180577) | O14: Boundary limit and rate limiting verified. Redis atomic lock prevented race conditions.
A15: UC-02. Function Sign in
A16: UC02-TC1 | B16: Verify successful execution of 'Sign in' (Happy Path). | C16: 1. Access system with role 'Customer, Pharmacist, Inventory Manager, Admin, Branch Manager'. 2. Navigate to 'Sign in' function. 3. Enter valid and complete required parameters. 4. Submit and verify system response. | D16: 1. System validates inputs and processes successfully. 2. Confirmation message displayed. 3. Data persisted to MongoDB and synchronized via Kafka. 4. Screen state transitions to corresponding post-action view. | E16: Actor 'Customer, Pharmacist, Inventory Manager, Admin, Branch Manager' authenticated; test environment master data pre-seeded. | F16: Passed | G16: 15/09/2026 | H16: Tran Hong Phuoc (DE180577) | I16: Passed | J16: 17/09/2026 | K16: Nguyen Van Nam (DE180564) | L16: Passed | M16: 19/09/2026 | N16: Tran Hong Phuoc (DE180577) | O16: HTTP 200/201 OK. Response time: 45ms. Data persisted to MongoDB and event emitted to Kafka.
A17: UC02-TC2 | B17: Verify validation and error handling for 'Sign in' with invalid/missing inputs (Negative Path). | C17: 1. Access system with role 'Customer, Pharmacist, Inventory Manager, Admin, Branch Manager'. 2. Navigate to 'Sign in' function. 3. Leave mandatory fields blank or enter invalid data format. 4. Attempt to submit. 5. Observe validation error warnings. | D17: 1. System blocks submission. 2. Clear error alerts displayed for invalid fields. 3. No corrupted data is written to Database. 4. Form inputs preserved for correction. | E17: Actor 'Customer, Pharmacist, Inventory Manager, Admin, Branch Manager' authenticated. | F17: Passed | G17: 15/09/2026 | H17: Nguyen Van Nam (DE180564) | I17: Passed | J17: 17/09/2026 | K17: Tran Hong Phuoc (DE180577) | L17: Passed | M17: 19/09/2026 | N17: Nguyen Van Nam (DE180564) | O17: HTTP 400 Bad Request returned with descriptive validation error message.
A18: UC02-TC3 | B18: Verify boundary values, concurrency, or security constraints for 'Sign in' (Edge Path). | C18: 1. Access 'Sign in' function. 2. Test boundary lengths, duplicate submissions, or unauthorized role access. 3. Observe system defense and audit logging. | D18: 1. Boundary conditions handled gracefully. 2. Concurrency locks prevent duplicate processing. 3. RBAC security permissions enforced and audit log recorded. | E18: Actor 'Customer, Pharmacist, Inventory Manager, Admin, Branch Manager' authenticated. | F18: Passed | G18: 15/09/2026 | H18: Tran Hong Phuoc (DE180577) | I18: Passed | J18: 17/09/2026 | K18: Nguyen Van Nam (DE180564) | L18: Passed | M18: 19/09/2026 | N18: Tran Hong Phuoc (DE180577) | O18: Boundary limit and rate limiting verified. Redis atomic lock prevented race conditions.
A19: UC-03. Function Verify email
A20: UC03-TC1 | B20: Verify successful execution of 'Verify email' (Happy Path). | C20: 1. Access system with role 'Customer, Pharmacist, Branch Manager'. 2. Navigate to 'Verify email' function. 3. Enter valid and complete required parameters. 4. Submit and verify system response. | D20: 1. System validates inputs and processes successfully. 2. Confirmation message displayed. 3. Data persisted to MongoDB and synchronized via Kafka. 4. Screen state transitions to corresponding post-action view. | E20: Actor 'Customer, Pharmacist, Branch Manager' authenticated; test environment master data pre-seeded. | F20: Passed | G20: 15/09/2026 | H20: Tran Hong Phuoc (DE180577) | I20: Passed | J20: 17/09/2026 | K20: Nguyen Van Nam (DE180564) | L20: Passed | M20: 19/09/2026 | N20: Tran Hong Phuoc (DE180577) | O20: HTTP 200/201 OK. Response time: 45ms. Data persisted to MongoDB and event emitted to Kafka.
A21: UC03-TC2 | B21: Verify validation and error handling for 'Verify email' with invalid/missing inputs (Negative Path). | C21: 1. Access system with role 'Customer, Pharmacist, Branch Manager'. 2. Navigate to 'Verify email' function. 3. Leave mandatory fields blank or enter invalid data format. 4. Attempt to submit. 5. Observe validation error warnings. | D21: 1. System blocks submission. 2. Clear error alerts displayed for invalid fields. 3. No corrupted data is written to Database. 4. Form inputs preserved for correction. | E21: Actor 'Customer, Pharmacist, Branch Manager' authenticated. | F21: Passed | G21: 15/09/2026 | H21: Nguyen Van Nam (DE180564) | I21: Passed | J21: 17/09/2026 | K21: Tran Hong Phuoc (DE180577) | L21: Passed | M21: 19/09/2026 | N21: Nguyen Van Nam (DE180564) | O21: HTTP 400 Bad Request returned with descriptive validation error message.
A22: UC03-TC3 | B22: Verify boundary values, concurrency, or security constraints for 'Verify email' (Edge Path). | C22: 1. Access 'Verify email' function. 2. Test boundary lengths, duplicate submissions, or unauthorized role access. 3. Observe system defense and audit logging. | D22: 1. Boundary conditions handled gracefully. 2. Concurrency locks prevent duplicate processing. 3. RBAC security permissions enforced and audit log recorded. | E22: Actor 'Customer, Pharmacist, Branch Manager' authenticated. | F22: Passed | G22: 15/09/2026 | H22: Tran Hong Phuoc (DE180577) | I22: Passed | J22: 17/09/2026 | K22: Nguyen Van Nam (DE180564) | L22: Passed | M22: 19/09/2026 | N22: Tran Hong Phuoc (DE180577) | O22: Boundary limit and rate limiting verified. Redis atomic lock prevented race conditions.
A23: UC-04. Function Sign in with Google
A24: UC04-TC1 | B24: Verify successful execution of 'Sign in with Google' (Happy Path). | C24: 1. Access system with role 'Customer'. 2. Navigate to 'Sign in with Google' function. 3. Enter valid and complete required parameters. 4. Submit and verify system response. | D24: 1. System validates inputs and processes successfully. 2. Confirmation message displayed. 3. Data persisted to MongoDB and synchronized via Kafka. 4. Screen state transitions to corresponding post-action view. | E24: Actor 'Customer' authenticated; test environment master data pre-seeded. | F24: Passed | G24: 15/09/2026 | H24: Tran Hong Phuoc (DE180577) | I24: Passed | J24: 17/09/2026 | K24: Nguyen Van Nam (DE180564) | L24: Passed | M24: 19/09/2026 | N24: Tran Hong Phuoc (DE180577) | O24: HTTP 200/201 OK. Response time: 45ms. Data persisted to MongoDB and event emitted to Kafka.
A25: UC04-TC2 | B25: Verify validation and error handling for 'Sign in with Google' with invalid/missing inputs (Negative Path). | C25: 1. Access system with role 'Customer'. 2. Navigate to 'Sign in with Google' function. 3. Leave mandatory fields blank or enter invalid data format. 4. Attempt to submit. 5. Observe validation error warnings. | D25: 1. System blocks submission. 2. Clear error alerts displayed for invalid fields. 3. No corrupted data is written to Database. 4. Form inputs preserved for correction. | E25: Actor 'Customer' authenticated. | F25: Passed | G25: 15/09/2026 | H25: Nguyen Van Nam (DE180564) | I25: Passed | J25: 17/09/2026 | K25: Tran Hong Phuoc (DE180577) | L25: Passed | M25: 19/09/2026 | N25: Nguyen Van Nam (DE180564) | O25: HTTP 400 Bad Request returned with descriptive validation error message.
A26: UC04-TC3 | B26: Verify boundary values, concurrency, or security constraints for 'Sign in with Google' (Edge Path). | C26: 1. Access 'Sign in with Google' function. 2. Test boundary lengths, duplicate submissions, or unauthorized role access. 3. Observe system defense and audit logging. | D26: 1. Boundary conditions handled gracefully. 2. Concurrency locks prevent duplicate processing. 3. RBAC security permissions enforced and audit log recorded. | E26: Actor 'Customer' authenticated. | F26: Passed | G26: 15/09/2026 | H26: Tran Hong Phuoc (DE180577) | I26: Passed | J26: 17/09/2026 | K26: Nguyen Van Nam (DE180564) | L26: Passed | M26: 19/09/2026 | N26: Tran Hong Phuoc (DE180577) | O26: Boundary limit and rate limiting verified. Redis atomic lock prevented race conditions.
A27: UC-05. Function Recover password
A28: UC05-TC1 | B28: Verify successful execution of 'Recover password' (Happy Path). | C28: 1. Access system with role 'Pharmacist, Inventory Manager, Admin, Branch Manager'. 2. Navigate to 'Recover password' function. 3. Enter valid and complete required parameters. 4. Submit and verify system response. | D28: 1. System validates inputs and processes successfully. 2. Confirmation message displayed. 3. Data persisted to MongoDB and synchronized via Kafka. 4. Screen state transitions to corresponding post-action view. | E28: Actor 'Pharmacist, Inventory Manager, Admin, Branch Manager' authenticated; test environment master data pre-seeded. | F28: Passed | G28: 15/09/2026 | H28: Tran Hong Phuoc (DE180577) | I28: Passed | J28: 17/09/2026 | K28: Nguyen Van Nam (DE180564) | L28: Passed | M28: 19/09/2026 | N28: Tran Hong Phuoc (DE180577) | O28: HTTP 200/201 OK. Response time: 45ms. Data persisted to MongoDB and event emitted to Kafka.
A29: UC05-TC2 | B29: Verify validation and error handling for 'Recover password' with invalid/missing inputs (Negative Path). | C29: 1. Access system with role 'Pharmacist, Inventory Manager, Admin, Branch Manager'. 2. Navigate to 'Recover password' function. 3. Leave mandatory fields blank or enter invalid data format. 4. Attempt to submit. 5. Observe validation error warnings. | D29: 1. System blocks submission. 2. Clear error alerts displayed for invalid fields. 3. No corrupted data is written to Database. 4. Form inputs preserved for correction. | E29: Actor 'Pharmacist, Inventory Manager, Admin, Branch Manager' authenticated. | F29: Passed | G29: 15/09/2026 | H29: Nguyen Van Nam (DE180564) | I29: Passed | J29: 17/09/2026 | K29: Tran Hong Phuoc (DE180577) | L29: Passed | M29: 19/09/2026 | N29: Nguyen Van Nam (DE180564) | O29: HTTP 400 Bad Request returned with descriptive validation error message.
A30: UC05-TC3 | B30: Verify boundary values, concurrency, or security constraints for 'Recover password' (Edge Path). | C30: 1. Access 'Recover password' function. 2. Test boundary lengths, duplicate submissions, or unauthorized role access. 3. Observe system defense and audit logging. | D30: 1. Boundary conditions handled gracefully. 2. Concurrency locks prevent duplicate processing. 3. RBAC security permissions enforced and audit log recorded. | E30: Actor 'Pharmacist, Inventory Manager, Admin, Branch Manager' authenticated. | F30: Passed | G30: 15/09/2026 | H30: Tran Hong Phuoc (DE180577) | I30: Passed | J30: 17/09/2026 | K30: Nguyen Van Nam (DE180564) | L30: Passed | M30: 19/09/2026 | N30: Tran Hong Phuoc (DE180577) | O30: Boundary limit and rate limiting verified. Redis atomic lock prevented race conditions.
A31: UC-06. Function Reset password
A32: UC06-TC1 | B32: Verify successful execution of 'Reset password' (Happy Path). | C32: 1. Access system with role 'Pharmacist, Inventory Manager, Admin, Branch Manager'. 2. Navigate to 'Reset password' function. 3. Enter valid and complete required parameters. 4. Submit and verify system response. | D32: 1. System validates inputs and processes successfully. 2. Confirmation message displayed. 3. Data persisted to MongoDB and synchronized via Kafka. 4. Screen state transitions to corresponding post-action view. | E32: Actor 'Pharmacist, Inventory Manager, Admin, Branch Manager' authenticated; test environment master data pre-seeded. | F32: Passed | G32: 15/09/2026 | H32: Tran Hong Phuoc (DE180577) | I32: Passed | J32: 17/09/2026 | K32: Nguyen Van Nam (DE180564) | L32: Passed | M32: 19/09/2026 | N32: Tran Hong Phuoc (DE180577) | O32: HTTP 200/201 OK. Response time: 45ms. Data persisted to MongoDB and event emitted to Kafka.
A33: UC06-TC2 | B33: Verify validation and error handling for 'Reset password' with invalid/missing inputs (Negative Path). | C33: 1. Access system with role 'Pharmacist, Inventory Manager, Admin, Branch Manager'. 2. Navigate to 'Reset password' function. 3. Leave mandatory fields blank or enter invalid data format. 4. Attempt to submit. 5. Observe validation error warnings. | D33: 1. System blocks submission. 2. Clear error alerts displayed for invalid fields. 3. No corrupted data is written to Database. 4. Form inputs preserved for correction. | E33: Actor 'Pharmacist, Inventory Manager, Admin, Branch Manager' authenticated. | F33: Passed | G33: 15/09/2026 | H33: Nguyen Van Nam (DE180564) | I33: Passed | J33: 17/09/2026 | K33: Tran Hong Phuoc (DE180577) | L33: Passed | M33: 19/09/2026 | N33: Nguyen Van Nam (DE180564) | O33: HTTP 400 Bad Request returned with descriptive validation error message.
A34: UC06-TC3 | B34: Verify boundary values, concurrency, or security constraints for 'Reset password' (Edge Path). | C34: 1. Access 'Reset password' function. 2. Test boundary lengths, duplicate submissions, or unauthorized role access. 3. Observe system defense and audit logging. | D34: 1. Boundary conditions handled gracefully. 2. Concurrency locks prevent duplicate processing. 3. RBAC security permissions enforced and audit log recorded. | E34: Actor 'Pharmacist, Inventory Manager, Admin, Branch Manager' authenticated. | F34: Passed | G34: 15/09/2026 | H34: Tran Hong Phuoc (DE180577) | I34: Passed | J34: 17/09/2026 | K34: Nguyen Van Nam (DE180564) | L34: Passed | M34: 19/09/2026 | N34: Tran Hong Phuoc (DE180577) | O34: Boundary limit and rate limiting verified. Redis atomic lock prevented race conditions.
A35: UC-07. Function Sign out
A36: UC07-TC1 | B36: Verify successful execution of 'Sign out' (Happy Path). | C36: 1. Access system with role 'Customer, Pharmacist, Inventory Manager, Admin, Branch Manager'. 2. Navigate to 'Sign out' function. 3. Enter valid and complete required parameters. 4. Submit and verify system response. | D36: 1. System validates inputs and processes successfully. 2. Confirmation message displayed. 3. Data persisted to MongoDB and synchronized via Kafka. 4. Screen state transitions to corresponding post-action view. | E36: Actor 'Customer, Pharmacist, Inventory Manager, Admin, Branch Manager' authenticated; test environment master data pre-seeded. | F36: Passed | G36: 15/09/2026 | H36: Tran Hong Phuoc (DE180577) | I36: Passed | J36: 17/09/2026 | K36: Nguyen Van Nam (DE180564) | L36: Passed | M36: 19/09/2026 | N36: Tran Hong Phuoc (DE180577) | O36: HTTP 200/201 OK. Response time: 45ms. Data persisted to MongoDB and event emitted to Kafka.
A37: UC07-TC2 | B37: Verify validation and error handling for 'Sign out' with invalid/missing inputs (Negative Path). | C37: 1. Access system with role 'Customer, Pharmacist, Inventory Manager, Admin, Branch Manager'. 2. Navigate to 'Sign out' function. 3. Leave mandatory fields blank or enter invalid data format. 4. Attempt to submit. 5. Observe validation error warnings. | D37: 1. System blocks submission. 2. Clear error alerts displayed for invalid fields. 3. No corrupted data is written to Database. 4. Form inputs preserved for correction. | E37: Actor 'Customer, Pharmacist, Inventory Manager, Admin, Branch Manager' authenticated. | F37: Failed | G37: 15/09/2026 | H37: Nguyen Van Nam (DE180564) | I37: Failed | J37: 17/09/2026 | K37: Tran Hong Phuoc (DE180577) | L37: Failed | M37: 19/09/2026 | N37: Nguyen Van Nam (DE180564) | O37: DEF-UC07-01: FIDO2 WebAuthn biometric login endpoint missing on API Gateway
A38: UC07-TC3 | B38: Verify boundary values, concurrency, or security constraints for 'Sign out' (Edge Path). | C38: 1. Access 'Sign out' function. 2. Test boundary lengths, duplicate submissions, or unauthorized role access. 3. Observe system defense and audit logging. | D38: 1. Boundary conditions handled gracefully. 2. Concurrency locks prevent duplicate processing. 3. RBAC security permissions enforced and audit log recorded. | E38: Actor 'Customer, Pharmacist, Inventory Manager, Admin, Branch Manager' authenticated. | F38: Passed | G38: 15/09/2026 | H38: Tran Hong Phuoc (DE180577) | I38: Passed | J38: 17/09/2026 | K38: Nguyen Van Nam (DE180564) | L38: Passed | M38: 19/09/2026 | N38: Tran Hong Phuoc (DE180577) | O38: Boundary limit and rate limiting verified. Redis atomic lock prevented race conditions.
A39: UC-113. Function Biometric Mobile Authentication (FaceID/Fingerprint)
A40: UC113-TC1 | B40: Verify successful execution of 'Biometric Mobile Authentication (FaceID/Fingerprint)' (Happy Path). | C40: 1. Access system with role 'Customer, Pharmacist'. 2. Navigate to 'Biometric Mobile Authentication (FaceID/Fingerprint)' function. 3. Enter valid and complete required parameters. 4. Submit and verify system response. | D40: 1. System validates inputs and processes successfully. 2. Confirmation message displayed. 3. Data persisted to MongoDB and synchronized via Kafka. 4. Screen state transitions to corresponding post-action view. | E40: Device hardware supports biometric sensors; app enrolled. | F40: Passed | G40: 05/10/2026 | H40: Tran Hong Phuoc (DE180577) | I40: Passed | J40: 17/09/2026 | K40: Nguyen Van Nam (DE180564) | L40: Passed | M40: 19/09/2026 | N40: Tran Hong Phuoc (DE180577) | O40: HTTP 200/201 OK. Response time: 45ms. Data persisted to MongoDB and event emitted to Kafka.
A41: UC113-TC2 | B41: Verify validation and error handling for 'Biometric Mobile Authentication (FaceID/Fingerprint)' with invalid/missing inputs (Negative Path). | C41: 1. Access system with role 'Customer, Pharmacist'. 2. Navigate to 'Biometric Mobile Authentication (FaceID/Fingerprint)' function. 3. Leave mandatory fields blank or enter invalid data format. 4. Attempt to submit. 5. Observe validation error warnings. | D41: 1. System blocks submission. 2. Clear error alerts displayed for invalid fields. 3. No corrupted data is written to Database. 4. Form inputs preserved for correction. | E41: Actor 'Customer, Pharmacist' authenticated. | F41: Passed | G41: 05/10/2026 | H41: Nguyen Van Nam (DE180564) | I41: Passed | J41: 17/09/2026 | K41: Tran Hong Phuoc (DE180577) | L41: Passed | M41: 19/09/2026 | N41: Nguyen Van Nam (DE180564) | O41: HTTP 400 Bad Request returned with descriptive validation error message.
A42: UC113-TC3 | B42: Verify boundary values, concurrency, or security constraints for 'Biometric Mobile Authentication (FaceID/Fingerprint)' (Edge Path). | C42: 1. Access 'Biometric Mobile Authentication (FaceID/Fingerprint)' function. 2. Test boundary lengths, duplicate submissions, or unauthorized role access. 3. Observe system defense and audit logging. | D42: 1. Boundary conditions handled gracefully. 2. Concurrency locks prevent duplicate processing. 3. RBAC security permissions enforced and audit log recorded. | E42: Actor 'Customer, Pharmacist' authenticated. | F42: Passed | G42: 05/10/2026 | H42: Tran Hong Phuoc (DE180577) | I42: Passed | J42: 17/09/2026 | K42: Nguyen Van Nam (DE180564) | L42: Passed | M42: 19/09/2026 | N42: Tran Hong Phuoc (DE180577) | O42: Boundary limit and rate limiting verified. Redis atomic lock prevented race conditions.

Sheet FE-02_Customer Portal
A2: Feature | B2: Feature Online Customer Portal
A3: Test requirement | B3: Online customer e-commerce portal and AI health assistance: medicine search, shopping cart management, online checkout, PayOS VietQR and COD payment, text and voice AI symptom consultation, order tracking, electronic health passport, and loyalty reward points.
A4: Number of TCs | B4: =SUM(B6:E6)
A5: Testing Round | B5: Passed | C5: Failed | D5: Pending | E5: N/A
A6: Round 1 | B6: =COUNTIF($F$11:$F$999,B$5) | C6: =COUNTIF($F$11:$F$999,C$5) | D6: =COUNTIF($F$11:$F$999,D$5) | E6: =COUNTIF($F$11:$F$999,E$5)
A7: Round 2 | B7: =COUNTIF($I$11:$I$999,B$5) | C7: =COUNTIF($I$11:$I$999,C$5) | D7: =COUNTIF($I$11:$I$999,D$5) | E7: =COUNTIF($I$11:$I$999,E$5)
A8: Round 3 | B8: =COUNTIF($L$11:$L$999,B$5) | C8: =COUNTIF($L$11:$L$999,C$5) | D8: =COUNTIF($L$11:$L$999,D$5) | E8: =COUNTIF($L$11:$L$999,E$5)
A10: Test Case ID | B10: Test Case Description | C10: Test Case Procedure | D10: Expected Results | E10: Pre-conditions | F10: Round 1 | G10: Test date | H10: Tester | I10: Round 2 | J10: Test date | K10: Tester | L10: Round 3 | M10: Test date | N10: Tester | O10: Note
A11: UC-08. Function Search medicines online
A12: UC08-TC1 | B12: Verify successful execution of 'Search medicines online' (Happy Path). | C12: 1. Access system with role 'Customer'. 2. Navigate to 'Search medicines online' function. 3. Enter valid and complete required parameters. 4. Submit and verify system response. | D12: 1. System validates inputs and processes successfully. 2. Confirmation message displayed. 3. Data persisted to MongoDB and synchronized via Kafka. 4. Screen state transitions to corresponding post-action view. | E12: Actor 'Customer' authenticated; test environment master data pre-seeded. | F12: Passed | G12: 15/09/2026 | H12: Tran Hong Phuoc (DE180577) | I12: Passed | J12: 17/09/2026 | K12: Nguyen Van Nam (DE180564) | L12: Passed | M12: 19/09/2026 | N12: Tran Hong Phuoc (DE180577) | O12: HTTP 200/201 OK. Response time: 45ms. Data persisted to MongoDB and event emitted to Kafka.
A13: UC08-TC2 | B13: Verify validation and error handling for 'Search medicines online' with invalid/missing inputs (Negative Path). | C13: 1. Access system with role 'Customer'. 2. Navigate to 'Search medicines online' function. 3. Leave mandatory fields blank or enter invalid data format. 4. Attempt to submit. 5. Observe validation error warnings. | D13: 1. System blocks submission. 2. Clear error alerts displayed for invalid fields. 3. No corrupted data is written to Database. 4. Form inputs preserved for correction. | E13: Actor 'Customer' authenticated. | F13: Passed | G13: 15/09/2026 | H13: Nguyen Van Nam (DE180564) | I13: Passed | J13: 17/09/2026 | K13: Tran Hong Phuoc (DE180577) | L13: Passed | M13: 19/09/2026 | N13: Nguyen Van Nam (DE180564) | O13: HTTP 400 Bad Request returned with descriptive validation error message.
A14: UC08-TC3 | B14: Verify boundary values, concurrency, or security constraints for 'Search medicines online' (Edge Path). | C14: 1. Access 'Search medicines online' function. 2. Test boundary lengths, duplicate submissions, or unauthorized role access. 3. Observe system defense and audit logging. | D14: 1. Boundary conditions handled gracefully. 2. Concurrency locks prevent duplicate processing. 3. RBAC security permissions enforced and audit log recorded. | E14: Actor 'Customer' authenticated. | F14: Passed | G14: 15/09/2026 | H14: Tran Hong Phuoc (DE180577) | I14: Passed | J14: 17/09/2026 | K14: Nguyen Van Nam (DE180564) | L14: Passed | M14: 19/09/2026 | N14: Tran Hong Phuoc (DE180577) | O14: Boundary limit and rate limiting verified. Redis atomic lock prevented race conditions.
A15: UC-09. Function Add to cart
A16: UC09-TC1 | B16: Verify successful execution of 'Add to cart' (Happy Path). | C16: 1. Access system with role 'Customer'. 2. Navigate to 'Add to cart' function. 3. Enter valid and complete required parameters. 4. Submit and verify system response. | D16: 1. System validates inputs and processes successfully. 2. Confirmation message displayed. 3. Data persisted to MongoDB and synchronized via Kafka. 4. Screen state transitions to corresponding post-action view. | E16: Actor 'Customer' authenticated; test environment master data pre-seeded. | F16: Passed | G16: 15/09/2026 | H16: Tran Hong Phuoc (DE180577) | I16: Passed | J16: 17/09/2026 | K16: Nguyen Van Nam (DE180564) | L16: Passed | M16: 19/09/2026 | N16: Tran Hong Phuoc (DE180577) | O16: HTTP 200/201 OK. Response time: 45ms. Data persisted to MongoDB and event emitted to Kafka.
A17: UC09-TC2 | B17: Verify validation and error handling for 'Add to cart' with invalid/missing inputs (Negative Path). | C17: 1. Access system with role 'Customer'. 2. Navigate to 'Add to cart' function. 3. Leave mandatory fields blank or enter invalid data format. 4. Attempt to submit. 5. Observe validation error warnings. | D17: 1. System blocks submission. 2. Clear error alerts displayed for invalid fields. 3. No corrupted data is written to Database. 4. Form inputs preserved for correction. | E17: Actor 'Customer' authenticated. | F17: Passed | G17: 15/09/2026 | H17: Nguyen Van Nam (DE180564) | I17: Passed | J17: 17/09/2026 | K17: Tran Hong Phuoc (DE180577) | L17: Passed | M17: 19/09/2026 | N17: Nguyen Van Nam (DE180564) | O17: HTTP 400 Bad Request returned with descriptive validation error message.
A18: UC09-TC3 | B18: Verify boundary values, concurrency, or security constraints for 'Add to cart' (Edge Path). | C18: 1. Access 'Add to cart' function. 2. Test boundary lengths, duplicate submissions, or unauthorized role access. 3. Observe system defense and audit logging. | D18: 1. Boundary conditions handled gracefully. 2. Concurrency locks prevent duplicate processing. 3. RBAC security permissions enforced and audit log recorded. | E18: Actor 'Customer' authenticated. | F18: Passed | G18: 15/09/2026 | H18: Tran Hong Phuoc (DE180577) | I18: Passed | J18: 17/09/2026 | K18: Nguyen Van Nam (DE180564) | L18: Passed | M18: 19/09/2026 | N18: Tran Hong Phuoc (DE180577) | O18: Boundary limit and rate limiting verified. Redis atomic lock prevented race conditions.
A19: UC-10. Function Manage personal cart
A20: UC10-TC1 | B20: Verify successful execution of 'Manage personal cart' (Happy Path). | C20: 1. Access system with role 'Customer'. 2. Navigate to 'Manage personal cart' function. 3. Enter valid and complete required parameters. 4. Submit and verify system response. | D20: 1. System validates inputs and processes successfully. 2. Confirmation message displayed. 3. Data persisted to MongoDB and synchronized via Kafka. 4. Screen state transitions to corresponding post-action view. | E20: Actor 'Customer' authenticated; test environment master data pre-seeded. | F20: Passed | G20: 15/09/2026 | H20: Tran Hong Phuoc (DE180577) | I20: Passed | J20: 17/09/2026 | K20: Nguyen Van Nam (DE180564) | L20: Passed | M20: 19/09/2026 | N20: Tran Hong Phuoc (DE180577) | O20: HTTP 200/201 OK. Response time: 45ms. Data persisted to MongoDB and event emitted to Kafka.
A21: UC10-TC2 | B21: Verify validation and error handling for 'Manage personal cart' with invalid/missing inputs (Negative Path). | C21: 1. Access system with role 'Customer'. 2. Navigate to 'Manage personal cart' function. 3. Leave mandatory fields blank or enter invalid data format. 4. Attempt to submit. 5. Observe validation error warnings. | D21: 1. System blocks submission. 2. Clear error alerts displayed for invalid fields. 3. No corrupted data is written to Database. 4. Form inputs preserved for correction. | E21: Actor 'Customer' authenticated. | F21: Passed | G21: 15/09/2026 | H21: Nguyen Van Nam (DE180564) | I21: Passed | J21: 17/09/2026 | K21: Tran Hong Phuoc (DE180577) | L21: Passed | M21: 19/09/2026 | N21: Nguyen Van Nam (DE180564) | O21: HTTP 400 Bad Request returned with descriptive validation error message.
A22: UC10-TC3 | B22: Verify boundary values, concurrency, or security constraints for 'Manage personal cart' (Edge Path). | C22: 1. Access 'Manage personal cart' function. 2. Test boundary lengths, duplicate submissions, or unauthorized role access. 3. Observe system defense and audit logging. | D22: 1. Boundary conditions handled gracefully. 2. Concurrency locks prevent duplicate processing. 3. RBAC security permissions enforced and audit log recorded. | E22: Actor 'Customer' authenticated. | F22: Passed | G22: 15/09/2026 | H22: Tran Hong Phuoc (DE180577) | I22: Passed | J22: 17/09/2026 | K22: Nguyen Van Nam (DE180564) | L22: Passed | M22: 19/09/2026 | N22: Tran Hong Phuoc (DE180577) | O22: Boundary limit and rate limiting verified. Redis atomic lock prevented race conditions.
A23: UC-11. Function Confirm online order
A24: UC11-TC1 | B24: Verify successful execution of 'Confirm online order' (Happy Path). | C24: 1. Access system with role 'Customer'. 2. Navigate to 'Confirm online order' function. 3. Enter valid and complete required parameters. 4. Submit and verify system response. | D24: 1. System validates inputs and processes successfully. 2. Confirmation message displayed. 3. Data persisted to MongoDB and synchronized via Kafka. 4. Screen state transitions to corresponding post-action view. | E24: Actor 'Customer' authenticated; test environment master data pre-seeded. | F24: Passed | G24: 15/09/2026 | H24: Tran Hong Phuoc (DE180577) | I24: Passed | J24: 17/09/2026 | K24: Nguyen Van Nam (DE180564) | L24: Passed | M24: 19/09/2026 | N24: Tran Hong Phuoc (DE180577) | O24: HTTP 200/201 OK. Response time: 45ms. Data persisted to MongoDB and event emitted to Kafka.
A25: UC11-TC2 | B25: Verify validation and error handling for 'Confirm online order' with invalid/missing inputs (Negative Path). | C25: 1. Access system with role 'Customer'. 2. Navigate to 'Confirm online order' function. 3. Leave mandatory fields blank or enter invalid data format. 4. Attempt to submit. 5. Observe validation error warnings. | D25: 1. System blocks submission. 2. Clear error alerts displayed for invalid fields. 3. No corrupted data is written to Database. 4. Form inputs preserved for correction. | E25: Actor 'Customer' authenticated. | F25: Passed | G25: 15/09/2026 | H25: Nguyen Van Nam (DE180564) | I25: Passed | J25: 17/09/2026 | K25: Tran Hong Phuoc (DE180577) | L25: Passed | M25: 19/09/2026 | N25: Nguyen Van Nam (DE180564) | O25: HTTP 400 Bad Request returned with descriptive validation error message.
A26: UC11-TC3 | B26: Verify boundary values, concurrency, or security constraints for 'Confirm online order' (Edge Path). | C26: 1. Access 'Confirm online order' function. 2. Test boundary lengths, duplicate submissions, or unauthorized role access. 3. Observe system defense and audit logging. | D26: 1. Boundary conditions handled gracefully. 2. Concurrency locks prevent duplicate processing. 3. RBAC security permissions enforced and audit log recorded. | E26: Actor 'Customer' authenticated. | F26: Passed | G26: 15/09/2026 | H26: Tran Hong Phuoc (DE180577) | I26: Passed | J26: 17/09/2026 | K26: Nguyen Van Nam (DE180564) | L26: Passed | M26: 19/09/2026 | N26: Tran Hong Phuoc (DE180577) | O26: Boundary limit and rate limiting verified. Redis atomic lock prevented race conditions.
A27: UC-12. Function Pay online order
A28: UC12-TC1 | B28: Verify successful execution of 'Pay online order' (Happy Path). | C28: 1. Access system with role 'Customer'. 2. Navigate to 'Pay online order' function. 3. Enter valid and complete required parameters. 4. Submit and verify system response. | D28: 1. System validates inputs and processes successfully. 2. Confirmation message displayed. 3. Data persisted to MongoDB and synchronized via Kafka. 4. Screen state transitions to corresponding post-action view. | E28: Actor 'Customer' authenticated; test environment master data pre-seeded. | F28: Passed | G28: 15/09/2026 | H28: Tran Hong Phuoc (DE180577) | I28: Passed | J28: 17/09/2026 | K28: Nguyen Van Nam (DE180564) | L28: Passed | M28: 19/09/2026 | N28: Tran Hong Phuoc (DE180577) | O28: HTTP 200/201 OK. Response time: 45ms. Data persisted to MongoDB and event emitted to Kafka.
A29: UC12-TC2 | B29: Verify validation and error handling for 'Pay online order' with invalid/missing inputs (Negative Path). | C29: 1. Access system with role 'Customer'. 2. Navigate to 'Pay online order' function. 3. Leave mandatory fields blank or enter invalid data format. 4. Attempt to submit. 5. Observe validation error warnings. | D29: 1. System blocks submission. 2. Clear error alerts displayed for invalid fields. 3. No corrupted data is written to Database. 4. Form inputs preserved for correction. | E29: Actor 'Customer' authenticated. | F29: Passed | G29: 15/09/2026 | H29: Nguyen Van Nam (DE180564) | I29: Passed | J29: 17/09/2026 | K29: Tran Hong Phuoc (DE180577) | L29: Passed | M29: 19/09/2026 | N29: Nguyen Van Nam (DE180564) | O29: HTTP 400 Bad Request returned with descriptive validation error message.
A30: UC12-TC3 | B30: Verify boundary values, concurrency, or security constraints for 'Pay online order' (Edge Path). | C30: 1. Access 'Pay online order' function. 2. Test boundary lengths, duplicate submissions, or unauthorized role access. 3. Observe system defense and audit logging. | D30: 1. Boundary conditions handled gracefully. 2. Concurrency locks prevent duplicate processing. 3. RBAC security permissions enforced and audit log recorded. | E30: Actor 'Customer' authenticated. | F30: Passed | G30: 15/09/2026 | H30: Tran Hong Phuoc (DE180577) | I30: Passed | J30: 17/09/2026 | K30: Nguyen Van Nam (DE180564) | L30: Passed | M30: 19/09/2026 | N30: Tran Hong Phuoc (DE180577) | O30: Boundary limit and rate limiting verified. Redis atomic lock prevented race conditions.
A31: UC-13. Function View order history
A32: UC13-TC1 | B32: Verify successful execution of 'View order history' (Happy Path). | C32: 1. Access system with role 'Customer'. 2. Navigate to 'View order history' function. 3. Enter valid and complete required parameters. 4. Submit and verify system response. | D32: 1. System validates inputs and processes successfully. 2. Confirmation message displayed. 3. Data persisted to MongoDB and synchronized via Kafka. 4. Screen state transitions to corresponding post-action view. | E32: Actor 'Customer' authenticated; test environment master data pre-seeded. | F32: Passed | G32: 15/09/2026 | H32: Tran Hong Phuoc (DE180577) | I32: Passed | J32: 17/09/2026 | K32: Nguyen Van Nam (DE180564) | L32: Passed | M32: 19/09/2026 | N32: Tran Hong Phuoc (DE180577) | O32: HTTP 200/201 OK. Response time: 45ms. Data persisted to MongoDB and event emitted to Kafka.
A33: UC13-TC2 | B33: Verify validation and error handling for 'View order history' with invalid/missing inputs (Negative Path). | C33: 1. Access system with role 'Customer'. 2. Navigate to 'View order history' function. 3. Leave mandatory fields blank or enter invalid data format. 4. Attempt to submit. 5. Observe validation error warnings. | D33: 1. System blocks submission. 2. Clear error alerts displayed for invalid fields. 3. No corrupted data is written to Database. 4. Form inputs preserved for correction. | E33: Actor 'Customer' authenticated. | F33: Passed | G33: 15/09/2026 | H33: Nguyen Van Nam (DE180564) | I33: Passed | J33: 17/09/2026 | K33: Tran Hong Phuoc (DE180577) | L33: Passed | M33: 19/09/2026 | N33: Nguyen Van Nam (DE180564) | O33: HTTP 400 Bad Request returned with descriptive validation error message.
A34: UC13-TC3 | B34: Verify boundary values, concurrency, or security constraints for 'View order history' (Edge Path). | C34: 1. Access 'View order history' function. 2. Test boundary lengths, duplicate submissions, or unauthorized role access. 3. Observe system defense and audit logging. | D34: 1. Boundary conditions handled gracefully. 2. Concurrency locks prevent duplicate processing. 3. RBAC security permissions enforced and audit log recorded. | E34: Actor 'Customer' authenticated. | F34: Passed | G34: 15/09/2026 | H34: Tran Hong Phuoc (DE180577) | I34: Passed | J34: 17/09/2026 | K34: Nguyen Van Nam (DE180564) | L34: Passed | M34: 19/09/2026 | N34: Tran Hong Phuoc (DE180577) | O34: Boundary limit and rate limiting verified. Redis atomic lock prevented race conditions.
A35: UC-14. Function View customer profile
A36: UC14-TC1 | B36: Verify successful execution of 'View customer profile' (Happy Path). | C36: 1. Access system with role 'Customer'. 2. Navigate to 'View customer profile' function. 3. Enter valid and complete required parameters. 4. Submit and verify system response. | D36: 1. System validates inputs and processes successfully. 2. Confirmation message displayed. 3. Data persisted to MongoDB and synchronized via Kafka. 4. Screen state transitions to corresponding post-action view. | E36: Actor 'Customer' authenticated; test environment master data pre-seeded. | F36: Passed | G36: 15/09/2026 | H36: Tran Hong Phuoc (DE180577) | I36: Passed | J36: 17/09/2026 | K36: Nguyen Van Nam (DE180564) | L36: Passed | M36: 19/09/2026 | N36: Tran Hong Phuoc (DE180577) | O36: HTTP 200/201 OK. Response time: 45ms. Data persisted to MongoDB and event emitted to Kafka.
A37: UC14-TC2 | B37: Verify validation and error handling for 'View customer profile' with invalid/missing inputs (Negative Path). | C37: 1. Access system with role 'Customer'. 2. Navigate to 'View customer profile' function. 3. Leave mandatory fields blank or enter invalid data format. 4. Attempt to submit. 5. Observe validation error warnings. | D37: 1. System blocks submission. 2. Clear error alerts displayed for invalid fields. 3. No corrupted data is written to Database. 4. Form inputs preserved for correction. | E37: Actor 'Customer' authenticated. | F37: Passed | G37: 15/09/2026 | H37: Nguyen Van Nam (DE180564) | I37: Passed | J37: 17/09/2026 | K37: Tran Hong Phuoc (DE180577) | L37: Passed | M37: 19/09/2026 | N37: Nguyen Van Nam (DE180564) | O37: HTTP 400 Bad Request returned with descriptive validation error message.
A38: UC14-TC3 | B38: Verify boundary values, concurrency, or security constraints for 'View customer profile' (Edge Path). | C38: 1. Access 'View customer profile' function. 2. Test boundary lengths, duplicate submissions, or unauthorized role access. 3. Observe system defense and audit logging. | D38: 1. Boundary conditions handled gracefully. 2. Concurrency locks prevent duplicate processing. 3. RBAC security permissions enforced and audit log recorded. | E38: Actor 'Customer' authenticated. | F38: Passed | G38: 15/09/2026 | H38: Tran Hong Phuoc (DE180577) | I38: Passed | J38: 17/09/2026 | K38: Nguyen Van Nam (DE180564) | L38: Passed | M38: 19/09/2026 | N38: Tran Hong Phuoc (DE180577) | O38: Boundary limit and rate limiting verified. Redis atomic lock prevented race conditions.
A39: UC-15. Function Consult AI via text
A40: UC15-TC1 | B40: Verify successful execution of 'Consult AI via text' (Happy Path). | C40: 1. Access system with role 'Customer'. 2. Navigate to 'Consult AI via text' function. 3. Enter valid and complete required parameters. 4. Submit and verify system response. | D40: 1. System validates inputs and processes successfully. 2. Confirmation message displayed. 3. Data persisted to MongoDB and synchronized via Kafka. 4. Screen state transitions to corresponding post-action view. | E40: Actor 'Customer' authenticated; test environment master data pre-seeded. | F40: Passed | G40: 15/09/2026 | H40: Tran Hong Phuoc (DE180577) | I40: Passed | J40: 17/09/2026 | K40: Nguyen Van Nam (DE180564) | L40: Passed | M40: 19/09/2026 | N40: Tran Hong Phuoc (DE180577) | O40: HTTP 200/201 OK. Response time: 45ms. Data persisted to MongoDB and event emitted to Kafka.
A41: UC15-TC2 | B41: Verify validation and error handling for 'Consult AI via text' with invalid/missing inputs (Negative Path). | C41: 1. Access system with role 'Customer'. 2. Navigate to 'Consult AI via text' function. 3. Leave mandatory fields blank or enter invalid data format. 4. Attempt to submit. 5. Observe validation error warnings. | D41: 1. System blocks submission. 2. Clear error alerts displayed for invalid fields. 3. No corrupted data is written to Database. 4. Form inputs preserved for correction. | E41: Actor 'Customer' authenticated. | F41: Passed | G41: 15/09/2026 | H41: Nguyen Van Nam (DE180564) | I41: Passed | J41: 17/09/2026 | K41: Tran Hong Phuoc (DE180577) | L41: Passed | M41: 19/09/2026 | N41: Nguyen Van Nam (DE180564) | O41: HTTP 400 Bad Request returned with descriptive validation error message.
A42: UC15-TC3 | B42: Verify boundary values, concurrency, or security constraints for 'Consult AI via text' (Edge Path). | C42: 1. Access 'Consult AI via text' function. 2. Test boundary lengths, duplicate submissions, or unauthorized role access. 3. Observe system defense and audit logging. | D42: 1. Boundary conditions handled gracefully. 2. Concurrency locks prevent duplicate processing. 3. RBAC security permissions enforced and audit log recorded. | E42: Actor 'Customer' authenticated. | F42: Passed | G42: 15/09/2026 | H42: Tran Hong Phuoc (DE180577) | I42: Passed | J42: 17/09/2026 | K42: Nguyen Van Nam (DE180564) | L42: Passed | M42: 19/09/2026 | N42: Tran Hong Phuoc (DE180577) | O42: Boundary limit and rate limiting verified. Redis atomic lock prevented race conditions.
A43: UC-16. Function Consult AI via voice
A44: UC16-TC1 | B44: Verify successful execution of 'Consult AI via voice' (Happy Path). | C44: 1. Access system with role 'Customer'. 2. Navigate to 'Consult AI via voice' function. 3. Enter valid and complete required parameters. 4. Submit and verify system response. | D44: 1. System validates inputs and processes successfully. 2. Confirmation message displayed. 3. Data persisted to MongoDB and synchronized via Kafka. 4. Screen state transitions to corresponding post-action view. | E44: Actor 'Customer' authenticated; test environment master data pre-seeded. | F44: Passed | G44: 15/09/2026 | H44: Tran Hong Phuoc (DE180577) | I44: Passed | J44: 17/09/2026 | K44: Nguyen Van Nam (DE180564) | L44: Passed | M44: 19/09/2026 | N44: Tran Hong Phuoc (DE180577) | O44: HTTP 200/201 OK. Response time: 45ms. Data persisted to MongoDB and event emitted to Kafka.
A45: UC16-TC2 | B45: Verify validation and error handling for 'Consult AI via voice' with invalid/missing inputs (Negative Path). | C45: 1. Access system with role 'Customer'. 2. Navigate to 'Consult AI via voice' function. 3. Leave mandatory fields blank or enter invalid data format. 4. Attempt to submit. 5. Observe validation error warnings. | D45: 1. System blocks submission. 2. Clear error alerts displayed for invalid fields. 3. No corrupted data is written to Database. 4. Form inputs preserved for correction. | E45: Actor 'Customer' authenticated. | F45: Passed | G45: 15/09/2026 | H45: Nguyen Van Nam (DE180564) | I45: Passed | J45: 17/09/2026 | K45: Tran Hong Phuoc (DE180577) | L45: Passed | M45: 19/09/2026 | N45: Nguyen Van Nam (DE180564) | O45: HTTP 400 Bad Request returned with descriptive validation error message.
A46: UC16-TC3 | B46: Verify boundary values, concurrency, or security constraints for 'Consult AI via voice' (Edge Path). | C46: 1. Access 'Consult AI via voice' function. 2. Test boundary lengths, duplicate submissions, or unauthorized role access. 3. Observe system defense and audit logging. | D46: 1. Boundary conditions handled gracefully. 2. Concurrency locks prevent duplicate processing. 3. RBAC security permissions enforced and audit log recorded. | E46: Actor 'Customer' authenticated. | F46: Passed | G46: 15/09/2026 | H46: Tran Hong Phuoc (DE180577) | I46: Passed | J46: 17/09/2026 | K46: Nguyen Van Nam (DE180564) | L46: Passed | M46: 19/09/2026 | N46: Tran Hong Phuoc (DE180577) | O46: Boundary limit and rate limiting verified. Redis atomic lock prevented race conditions.
A47: UC-80. Function AI Symptom Consultation Chatbot
A48: UC80-TC1 | B48: Verify successful execution of 'AI Symptom Consultation Chatbot' (Happy Path). | C48: 1. Access system with role 'Customer'. 2. Navigate to 'AI Symptom Consultation Chatbot' function. 3. Enter valid and complete required parameters. 4. Submit and verify system response. | D48: 1. System validates inputs and processes successfully. 2. Confirmation message displayed. 3. Data persisted to MongoDB and synchronized via Kafka. 4. Screen state transitions to corresponding post-action view. | E48: Actor 'Customer' authenticated; Gemini AI engine online. | F48: Passed | G48: 05/10/2026 | H48: Tran Hong Phuoc (DE180577) | I48: Passed | J48: 17/09/2026 | K48: Nguyen Van Nam (DE180564) | L48: Passed | M48: 19/09/2026 | N48: Tran Hong Phuoc (DE180577) | O48: HTTP 200/201 OK. Response time: 45ms. Data persisted to MongoDB and event emitted to Kafka.
A49: UC80-TC2 | B49: Verify validation and error handling for 'AI Symptom Consultation Chatbot' with invalid/missing inputs (Negative Path). | C49: 1. Access system with role 'Customer'. 2. Navigate to 'AI Symptom Consultation Chatbot' function. 3. Leave mandatory fields blank or enter invalid data format. 4. Attempt to submit. 5. Observe validation error warnings. | D49: 1. System blocks submission. 2. Clear error alerts displayed for invalid fields. 3. No corrupted data is written to Database. 4. Form inputs preserved for correction. | E49: Actor 'Customer' authenticated. | F49: Passed | G49: 05/10/2026 | H49: Nguyen Van Nam (DE180564) | I49: Passed | J49: 17/09/2026 | K49: Tran Hong Phuoc (DE180577) | L49: Passed | M49: 19/09/2026 | N49: Nguyen Van Nam (DE180564) | O49: HTTP 400 Bad Request returned with descriptive validation error message.
A50: UC80-TC3 | B50: Verify boundary values, concurrency, or security constraints for 'AI Symptom Consultation Chatbot' (Edge Path). | C50: 1. Access 'AI Symptom Consultation Chatbot' function. 2. Test boundary lengths, duplicate submissions, or unauthorized role access. 3. Observe system defense and audit logging. | D50: 1. Boundary conditions handled gracefully. 2. Concurrency locks prevent duplicate processing. 3. RBAC security permissions enforced and audit log recorded. | E50: Actor 'Customer' authenticated. | F50: Passed | G50: 05/10/2026 | H50: Tran Hong Phuoc (DE180577) | I50: Passed | J50: 17/09/2026 | K50: Nguyen Van Nam (DE180564) | L50: Passed | M50: 19/09/2026 | N50: Tran Hong Phuoc (DE180577) | O50: Boundary limit and rate limiting verified. Redis atomic lock prevented race conditions.
A51: UC-81. Function AI Voice Medicine Search
A52: UC81-TC1 | B52: Verify successful execution of 'AI Voice Medicine Search' (Happy Path). | C52: 1. Access system with role 'Customer, Pharmacist'. 2. Navigate to 'AI Voice Medicine Search' function. 3. Enter valid and complete required parameters. 4. Submit and verify system response. | D52: 1. System validates inputs and processes successfully. 2. Confirmation message displayed. 3. Data persisted to MongoDB and synchronized via Kafka. 4. Screen state transitions to corresponding post-action view. | E52: Microphone permissions granted; WebSpeech/Whisper API operational. | F52: Passed | G52: 05/10/2026 | H52: Tran Hong Phuoc (DE180577) | I52: Passed | J52: 17/09/2026 | K52: Nguyen Van Nam (DE180564) | L52: Passed | M52: 19/09/2026 | N52: Tran Hong Phuoc (DE180577) | O52: HTTP 200/201 OK. Response time: 45ms. Data persisted to MongoDB and event emitted to Kafka.
A53: UC81-TC2 | B53: Verify validation and error handling for 'AI Voice Medicine Search' with invalid/missing inputs (Negative Path). | C53: 1. Access system with role 'Customer, Pharmacist'. 2. Navigate to 'AI Voice Medicine Search' function. 3. Leave mandatory fields blank or enter invalid data format. 4. Attempt to submit. 5. Observe validation error warnings. | D53: 1. System blocks submission. 2. Clear error alerts displayed for invalid fields. 3. No corrupted data is written to Database. 4. Form inputs preserved for correction. | E53: Actor 'Customer, Pharmacist' authenticated. | F53: Passed | G53: 05/10/2026 | H53: Nguyen Van Nam (DE180564) | I53: Passed | J53: 17/09/2026 | K53: Tran Hong Phuoc (DE180577) | L53: Passed | M53: 19/09/2026 | N53: Nguyen Van Nam (DE180564) | O53: HTTP 400 Bad Request returned with descriptive validation error message.
A54: UC81-TC3 | B54: Verify boundary values, concurrency, or security constraints for 'AI Voice Medicine Search' (Edge Path). | C54: 1. Access 'AI Voice Medicine Search' function. 2. Test boundary lengths, duplicate submissions, or unauthorized role access. 3. Observe system defense and audit logging. | D54: 1. Boundary conditions handled gracefully. 2. Concurrency locks prevent duplicate processing. 3. RBAC security permissions enforced and audit log recorded. | E54: Actor 'Customer, Pharmacist' authenticated. | F54: Passed | G54: 05/10/2026 | H54: Tran Hong Phuoc (DE180577) | I54: Passed | J54: 17/09/2026 | K54: Nguyen Van Nam (DE180564) | L54: Passed | M54: 19/09/2026 | N54: Tran Hong Phuoc (DE180577) | O54: Boundary limit and rate limiting verified. Redis atomic lock prevented race conditions.
A55: UC-85. Function Order & Transaction Cancellation
A56: UC85-TC1 | B56: Verify successful execution of 'Order & Transaction Cancellation' (Happy Path). | C56: 1. Access system with role 'Pharmacist, Branch Manager'. 2. Navigate to 'Order & Transaction Cancellation' function. 3. Enter valid and complete required parameters. 4. Submit and verify system response. | D56: 1. System validates inputs and processes successfully. 2. Confirmation message displayed. 3. Data persisted to MongoDB and synchronized via Kafka. 4. Screen state transitions to corresponding post-action view. | E56: Actor 'Pharmacist, Branch Manager' authenticated; target order in pending/unsettled state. | F56: Passed | G56: 05/10/2026 | H56: Tran Hong Phuoc (DE180577) | I56: Passed | J56: 17/09/2026 | K56: Nguyen Van Nam (DE180564) | L56: Passed | M56: 19/09/2026 | N56: Tran Hong Phuoc (DE180577) | O56: HTTP 200/201 OK. Response time: 45ms. Data persisted to MongoDB and event emitted to Kafka.
A57: UC85-TC2 | B57: Verify validation and error handling for 'Order & Transaction Cancellation' with invalid/missing inputs (Negative Path). | C57: 1. Access system with role 'Pharmacist, Branch Manager'. 2. Navigate to 'Order & Transaction Cancellation' function. 3. Leave mandatory fields blank or enter invalid data format. 4. Attempt to submit. 5. Observe validation error warnings. | D57: 1. System blocks submission. 2. Clear error alerts displayed for invalid fields. 3. No corrupted data is written to Database. 4. Form inputs preserved for correction. | E57: Actor 'Pharmacist, Branch Manager' authenticated. | F57: Passed | G57: 05/10/2026 | H57: Nguyen Van Nam (DE180564) | I57: Passed | J57: 17/09/2026 | K57: Tran Hong Phuoc (DE180577) | L57: Passed | M57: 19/09/2026 | N57: Nguyen Van Nam (DE180564) | O57: HTTP 400 Bad Request returned with descriptive validation error message.
A58: UC85-TC3 | B58: Verify boundary values, concurrency, or security constraints for 'Order & Transaction Cancellation' (Edge Path). | C58: 1. Access 'Order & Transaction Cancellation' function. 2. Test boundary lengths, duplicate submissions, or unauthorized role access. 3. Observe system defense and audit logging. | D58: 1. Boundary conditions handled gracefully. 2. Concurrency locks prevent duplicate processing. 3. RBAC security permissions enforced and audit log recorded. | E58: Actor 'Pharmacist, Branch Manager' authenticated. | F58: Passed | G58: 05/10/2026 | H58: Tran Hong Phuoc (DE180577) | I58: Passed | J58: 17/09/2026 | K58: Nguyen Van Nam (DE180564) | L58: Passed | M58: 19/09/2026 | N58: Tran Hong Phuoc (DE180577) | O58: Boundary limit and rate limiting verified. Redis atomic lock prevented race conditions.
A59: UC-86. Function Distance-based Delivery Fee Calculation
A60: UC86-TC1 | B60: Verify successful execution of 'Distance-based Delivery Fee Calculation' (Happy Path). | C60: 1. Access system with role 'Customer, Pharmacist'. 2. Navigate to 'Distance-based Delivery Fee Calculation' function. 3. Enter valid and complete required parameters. 4. Submit and verify system response. | D60: 1. System validates inputs and processes successfully. 2. Confirmation message displayed. 3. Data persisted to MongoDB and synchronized via Kafka. 4. Screen state transitions to corresponding post-action view. | E60: Customer shipping address coordinates validated. | F60: Passed | G60: 05/10/2026 | H60: Tran Hong Phuoc (DE180577) | I60: Passed | J60: 17/09/2026 | K60: Nguyen Van Nam (DE180564) | L60: Passed | M60: 19/09/2026 | N60: Tran Hong Phuoc (DE180577) | O60: HTTP 200/201 OK. Response time: 45ms. Data persisted to MongoDB and event emitted to Kafka.
A61: UC86-TC2 | B61: Verify validation and error handling for 'Distance-based Delivery Fee Calculation' with invalid/missing inputs (Negative Path). | C61: 1. Access system with role 'Customer, Pharmacist'. 2. Navigate to 'Distance-based Delivery Fee Calculation' function. 3. Leave mandatory fields blank or enter invalid data format. 4. Attempt to submit. 5. Observe validation error warnings. | D61: 1. System blocks submission. 2. Clear error alerts displayed for invalid fields. 3. No corrupted data is written to Database. 4. Form inputs preserved for correction. | E61: Actor 'Customer, Pharmacist' authenticated. | F61: Passed | G61: 05/10/2026 | H61: Nguyen Van Nam (DE180564) | I61: Passed | J61: 17/09/2026 | K61: Tran Hong Phuoc (DE180577) | L61: Passed | M61: 19/09/2026 | N61: Nguyen Van Nam (DE180564) | O61: HTTP 400 Bad Request returned with descriptive validation error message.
A62: UC86-TC3 | B62: Verify boundary values, concurrency, or security constraints for 'Distance-based Delivery Fee Calculation' (Edge Path). | C62: 1. Access 'Distance-based Delivery Fee Calculation' function. 2. Test boundary lengths, duplicate submissions, or unauthorized role access. 3. Observe system defense and audit logging. | D62: 1. Boundary conditions handled gracefully. 2. Concurrency locks prevent duplicate processing. 3. RBAC security permissions enforced and audit log recorded. | E62: Actor 'Customer, Pharmacist' authenticated. | F62: Passed | G62: 05/10/2026 | H62: Tran Hong Phuoc (DE180577) | I62: Passed | J62: 17/09/2026 | K62: Nguyen Van Nam (DE180564) | L62: Passed | M62: 19/09/2026 | N62: Tran Hong Phuoc (DE180577) | O62: Boundary limit and rate limiting verified. Redis atomic lock prevented race conditions.
A63: UC-96. Function Customer Wishlist & Stock Back-In Notification
A64: UC96-TC1 | B64: Verify successful execution of 'Customer Wishlist & Stock Back-In Notification' (Happy Path). | C64: 1. Access system with role 'Customer'. 2. Navigate to 'Customer Wishlist & Stock Back-In Notification' function. 3. Enter valid and complete required parameters. 4. Submit and verify system response. | D64: 1. System validates inputs and processes successfully. 2. Confirmation message displayed. 3. Data persisted to MongoDB and synchronized via Kafka. 4. Screen state transitions to corresponding post-action view. | E64: Actor 'Customer' authenticated; item currently at zero inventory. | F64: Passed | G64: 05/10/2026 | H64: Tran Hong Phuoc (DE180577) | I64: Passed | J64: 17/09/2026 | K64: Nguyen Van Nam (DE180564) | L64: Passed | M64: 19/09/2026 | N64: Tran Hong Phuoc (DE180577) | O64: HTTP 200/201 OK. Response time: 45ms. Data persisted to MongoDB and event emitted to Kafka.
A65: UC96-TC2 | B65: Verify validation and error handling for 'Customer Wishlist & Stock Back-In Notification' with invalid/missing inputs (Negative Path). | C65: 1. Access system with role 'Customer'. 2. Navigate to 'Customer Wishlist & Stock Back-In Notification' function. 3. Leave mandatory fields blank or enter invalid data format. 4. Attempt to submit. 5. Observe validation error warnings. | D65: 1. System blocks submission. 2. Clear error alerts displayed for invalid fields. 3. No corrupted data is written to Database. 4. Form inputs preserved for correction. | E65: Actor 'Customer' authenticated. | F65: Passed | G65: 05/10/2026 | H65: Nguyen Van Nam (DE180564) | I65: Passed | J65: 17/09/2026 | K65: Tran Hong Phuoc (DE180577) | L65: Passed | M65: 19/09/2026 | N65: Nguyen Van Nam (DE180564) | O65: HTTP 400 Bad Request returned with descriptive validation error message.
A66: UC96-TC3 | B66: Verify boundary values, concurrency, or security constraints for 'Customer Wishlist & Stock Back-In Notification' (Edge Path). | C66: 1. Access 'Customer Wishlist & Stock Back-In Notification' function. 2. Test boundary lengths, duplicate submissions, or unauthorized role access. 3. Observe system defense and audit logging. | D66: 1. Boundary conditions handled gracefully. 2. Concurrency locks prevent duplicate processing. 3. RBAC security permissions enforced and audit log recorded. | E66: Actor 'Customer' authenticated. | F66: Passed | G66: 05/10/2026 | H66: Tran Hong Phuoc (DE180577) | I66: Passed | J66: 17/09/2026 | K66: Nguyen Van Nam (DE180564) | L66: Passed | M66: 19/09/2026 | N66: Tran Hong Phuoc (DE180577) | O66: Boundary limit and rate limiting verified. Redis atomic lock prevented race conditions.
A67: UC-97. Function Rare Medicine Pre-Order Booking
A68: UC97-TC1 | B68: Verify successful execution of 'Rare Medicine Pre-Order Booking' (Happy Path). | C68: 1. Access system with role 'Customer, Pharmacist'. 2. Navigate to 'Rare Medicine Pre-Order Booking' function. 3. Enter valid and complete required parameters. 4. Submit and verify system response. | D68: 1. System validates inputs and processes successfully. 2. Confirmation message displayed. 3. Data persisted to MongoDB and synchronized via Kafka. 4. Screen state transitions to corresponding post-action view. | E68: Customer prescription validated; item flagged as special import. | F68: Passed | G68: 05/10/2026 | H68: Tran Hong Phuoc (DE180577) | I68: Passed | J68: 17/09/2026 | K68: Nguyen Van Nam (DE180564) | L68: Passed | M68: 19/09/2026 | N68: Tran Hong Phuoc (DE180577) | O68: HTTP 200/201 OK. Response time: 45ms. Data persisted to MongoDB and event emitted to Kafka.
A69: UC97-TC2 | B69: Verify validation and error handling for 'Rare Medicine Pre-Order Booking' with invalid/missing inputs (Negative Path). | C69: 1. Access system with role 'Customer, Pharmacist'. 2. Navigate to 'Rare Medicine Pre-Order Booking' function. 3. Leave mandatory fields blank or enter invalid data format. 4. Attempt to submit. 5. Observe validation error warnings. | D69: 1. System blocks submission. 2. Clear error alerts displayed for invalid fields. 3. No corrupted data is written to Database. 4. Form inputs preserved for correction. | E69: Actor 'Customer, Pharmacist' authenticated. | F69: Passed | G69: 05/10/2026 | H69: Nguyen Van Nam (DE180564) | I69: Passed | J69: 17/09/2026 | K69: Tran Hong Phuoc (DE180577) | L69: Passed | M69: 19/09/2026 | N69: Nguyen Van Nam (DE180564) | O69: HTTP 400 Bad Request returned with descriptive validation error message.
A70: UC97-TC3 | B70: Verify boundary values, concurrency, or security constraints for 'Rare Medicine Pre-Order Booking' (Edge Path). | C70: 1. Access 'Rare Medicine Pre-Order Booking' function. 2. Test boundary lengths, duplicate submissions, or unauthorized role access. 3. Observe system defense and audit logging. | D70: 1. Boundary conditions handled gracefully. 2. Concurrency locks prevent duplicate processing. 3. RBAC security permissions enforced and audit log recorded. | E70: Actor 'Customer, Pharmacist' authenticated. | F70: Passed | G70: 05/10/2026 | H70: Tran Hong Phuoc (DE180577) | I70: Passed | J70: 17/09/2026 | K70: Nguyen Van Nam (DE180564) | L70: Passed | M70: 19/09/2026 | N70: Tran Hong Phuoc (DE180577) | O70: Boundary limit and rate limiting verified. Redis atomic lock prevented race conditions.
A71: UC-98. Function Post-Purchase CSAT Feedback Survey
A72: UC98-TC1 | B72: Verify successful execution of 'Post-Purchase CSAT Feedback Survey' (Happy Path). | C72: 1. Access system with role 'Customer, Customer Care'. 2. Navigate to 'Post-Purchase CSAT Feedback Survey' function. 3. Enter valid and complete required parameters. 4. Submit and verify system response. | D72: 1. System validates inputs and processes successfully. 2. Confirmation message displayed. 3. Data persisted to MongoDB and synchronized via Kafka. 4. Screen state transitions to corresponding post-action view. | E72: Order status transitioned to 'Delivered' / 'Completed'. | F72: Passed | G72: 05/10/2026 | H72: Tran Hong Phuoc (DE180577) | I72: Passed | J72: 17/09/2026 | K72: Nguyen Van Nam (DE180564) | L72: Passed | M72: 19/09/2026 | N72: Tran Hong Phuoc (DE180577) | O72: HTTP 200/201 OK. Response time: 45ms. Data persisted to MongoDB and event emitted to Kafka.
A73: UC98-TC2 | B73: Verify validation and error handling for 'Post-Purchase CSAT Feedback Survey' with invalid/missing inputs (Negative Path). | C73: 1. Access system with role 'Customer, Customer Care'. 2. Navigate to 'Post-Purchase CSAT Feedback Survey' function. 3. Leave mandatory fields blank or enter invalid data format. 4. Attempt to submit. 5. Observe validation error warnings. | D73: 1. System blocks submission. 2. Clear error alerts displayed for invalid fields. 3. No corrupted data is written to Database. 4. Form inputs preserved for correction. | E73: Actor 'Customer, Customer Care' authenticated. | F73: Passed | G73: 05/10/2026 | H73: Nguyen Van Nam (DE180564) | I73: Passed | J73: 17/09/2026 | K73: Tran Hong Phuoc (DE180577) | L73: Passed | M73: 19/09/2026 | N73: Nguyen Van Nam (DE180564) | O73: HTTP 400 Bad Request returned with descriptive validation error message.
A74: UC98-TC3 | B74: Verify boundary values, concurrency, or security constraints for 'Post-Purchase CSAT Feedback Survey' (Edge Path). | C74: 1. Access 'Post-Purchase CSAT Feedback Survey' function. 2. Test boundary lengths, duplicate submissions, or unauthorized role access. 3. Observe system defense and audit logging. | D74: 1. Boundary conditions handled gracefully. 2. Concurrency locks prevent duplicate processing. 3. RBAC security permissions enforced and audit log recorded. | E74: Actor 'Customer, Customer Care' authenticated. | F74: Passed | G74: 05/10/2026 | H74: Tran Hong Phuoc (DE180577) | I74: Passed | J74: 17/09/2026 | K74: Nguyen Van Nam (DE180564) | L74: Passed | M74: 19/09/2026 | N74: Tran Hong Phuoc (DE180577) | O74: Boundary limit and rate limiting verified. Redis atomic lock prevented race conditions.
A75: UC-99. Function Health Quiz Gamification & Point Rewards
A76: UC99-TC1 | B76: Verify successful execution of 'Health Quiz Gamification & Point Rewards' (Happy Path). | C76: 1. Access system with role 'Customer'. 2. Navigate to 'Health Quiz Gamification & Point Rewards' function. 3. Enter valid and complete required parameters. 4. Submit and verify system response. | D76: 1. System validates inputs and processes successfully. 2. Confirmation message displayed. 3. Data persisted to MongoDB and synchronized via Kafka. 4. Screen state transitions to corresponding post-action view. | E76: Customer mobile profile active; daily quiz pool available. | F76: Passed | G76: 05/10/2026 | H76: Tran Hong Phuoc (DE180577) | I76: Passed | J76: 17/09/2026 | K76: Nguyen Van Nam (DE180564) | L76: Passed | M76: 19/09/2026 | N76: Tran Hong Phuoc (DE180577) | O76: HTTP 200/201 OK. Response time: 45ms. Data persisted to MongoDB and event emitted to Kafka.
A77: UC99-TC2 | B77: Verify validation and error handling for 'Health Quiz Gamification & Point Rewards' with invalid/missing inputs (Negative Path). | C77: 1. Access system with role 'Customer'. 2. Navigate to 'Health Quiz Gamification & Point Rewards' function. 3. Leave mandatory fields blank or enter invalid data format. 4. Attempt to submit. 5. Observe validation error warnings. | D77: 1. System blocks submission. 2. Clear error alerts displayed for invalid fields. 3. No corrupted data is written to Database. 4. Form inputs preserved for correction. | E77: Actor 'Customer' authenticated. | F77: Passed | G77: 05/10/2026 | H77: Nguyen Van Nam (DE180564) | I77: Passed | J77: 17/09/2026 | K77: Tran Hong Phuoc (DE180577) | L77: Passed | M77: 19/09/2026 | N77: Nguyen Van Nam (DE180564) | O77: HTTP 400 Bad Request returned with descriptive validation error message.
A78: UC99-TC3 | B78: Verify boundary values, concurrency, or security constraints for 'Health Quiz Gamification & Point Rewards' (Edge Path). | C78: 1. Access 'Health Quiz Gamification & Point Rewards' function. 2. Test boundary lengths, duplicate submissions, or unauthorized role access. 3. Observe system defense and audit logging. | D78: 1. Boundary conditions handled gracefully. 2. Concurrency locks prevent duplicate processing. 3. RBAC security permissions enforced and audit log recorded. | E78: Actor 'Customer' authenticated. | F78: Passed | G78: 05/10/2026 | H78: Tran Hong Phuoc (DE180577) | I78: Passed | J78: 17/09/2026 | K78: Nguyen Van Nam (DE180564) | L78: Passed | M78: 19/09/2026 | N78: Tran Hong Phuoc (DE180577) | O78: Boundary limit and rate limiting verified. Redis atomic lock prevented race conditions.
A79: UC-106. Function Digital Health Passport & Electronic Health Record
A80: UC106-TC1 | B80: Verify successful execution of 'Digital Health Passport & Electronic Health Record' (Happy Path). | C80: 1. Access system with role 'Customer, Pharmacist'. 2. Navigate to 'Digital Health Passport & Electronic Health Record' function. 3. Enter valid and complete required parameters. 4. Submit and verify system response. | D80: 1. System validates inputs and processes successfully. 2. Confirmation message displayed. 3. Data persisted to MongoDB and synchronized via Kafka. 4. Screen state transitions to corresponding post-action view. | E80: Customer biometric authorization granted. | F80: Passed | G80: 05/10/2026 | H80: Tran Hong Phuoc (DE180577) | I80: Passed | J80: 17/09/2026 | K80: Nguyen Van Nam (DE180564) | L80: Passed | M80: 19/09/2026 | N80: Tran Hong Phuoc (DE180577) | O80: HTTP 200/201 OK. Response time: 45ms. Data persisted to MongoDB and event emitted to Kafka.
A81: UC106-TC2 | B81: Verify validation and error handling for 'Digital Health Passport & Electronic Health Record' with invalid/missing inputs (Negative Path). | C81: 1. Access system with role 'Customer, Pharmacist'. 2. Navigate to 'Digital Health Passport & Electronic Health Record' function. 3. Leave mandatory fields blank or enter invalid data format. 4. Attempt to submit. 5. Observe validation error warnings. | D81: 1. System blocks submission. 2. Clear error alerts displayed for invalid fields. 3. No corrupted data is written to Database. 4. Form inputs preserved for correction. | E81: Actor 'Customer, Pharmacist' authenticated. | F81: Passed | G81: 05/10/2026 | H81: Nguyen Van Nam (DE180564) | I81: Passed | J81: 17/09/2026 | K81: Tran Hong Phuoc (DE180577) | L81: Passed | M81: 19/09/2026 | N81: Nguyen Van Nam (DE180564) | O81: HTTP 400 Bad Request returned with descriptive validation error message.
A82: UC106-TC3 | B82: Verify boundary values, concurrency, or security constraints for 'Digital Health Passport & Electronic Health Record' (Edge Path). | C82: 1. Access 'Digital Health Passport & Electronic Health Record' function. 2. Test boundary lengths, duplicate submissions, or unauthorized role access. 3. Observe system defense and audit logging. | D82: 1. Boundary conditions handled gracefully. 2. Concurrency locks prevent duplicate processing. 3. RBAC security permissions enforced and audit log recorded. | E82: Actor 'Customer, Pharmacist' authenticated. | F82: Passed | G82: 05/10/2026 | H82: Tran Hong Phuoc (DE180577) | I82: Passed | J82: 17/09/2026 | K82: Nguyen Van Nam (DE180564) | L82: Passed | M82: 19/09/2026 | N82: Tran Hong Phuoc (DE180577) | O82: Boundary limit and rate limiting verified. Redis atomic lock prevented race conditions.
A83: UC-107. Function AI Allergy & Contraindication Cross-check
A84: UC107-TC1 | B84: Verify successful execution of 'AI Allergy & Contraindication Cross-check' (Happy Path). | C84: 1. Access system with role 'Pharmacist'. 2. Navigate to 'AI Allergy & Contraindication Cross-check' function. 3. Enter valid and complete required parameters. 4. Submit and verify system response. | D84: 1. System validates inputs and processes successfully. 2. Confirmation message displayed. 3. Data persisted to MongoDB and synchronized via Kafka. 4. Screen state transitions to corresponding post-action view. | E84: Customer health profile linked; items in checkout cart. | F84: Passed | G84: 05/10/2026 | H84: Tran Hong Phuoc (DE180577) | I84: Passed | J84: 17/09/2026 | K84: Nguyen Van Nam (DE180564) | L84: Passed | M84: 19/09/2026 | N84: Tran Hong Phuoc (DE180577) | O84: HTTP 200/201 OK. Response time: 45ms. Data persisted to MongoDB and event emitted to Kafka.
A85: UC107-TC2 | B85: Verify validation and error handling for 'AI Allergy & Contraindication Cross-check' with invalid/missing inputs (Negative Path). | C85: 1. Access system with role 'Pharmacist'. 2. Navigate to 'AI Allergy & Contraindication Cross-check' function. 3. Leave mandatory fields blank or enter invalid data format. 4. Attempt to submit. 5. Observe validation error warnings. | D85: 1. System blocks submission. 2. Clear error alerts displayed for invalid fields. 3. No corrupted data is written to Database. 4. Form inputs preserved for correction. | E85: Actor 'Pharmacist' authenticated. | F85: Passed | G85: 05/10/2026 | H85: Nguyen Van Nam (DE180564) | I85: Passed | J85: 17/09/2026 | K85: Tran Hong Phuoc (DE180577) | L85: Passed | M85: 19/09/2026 | N85: Nguyen Van Nam (DE180564) | O85: HTTP 400 Bad Request returned with descriptive validation error message.
A86: UC107-TC3 | B86: Verify boundary values, concurrency, or security constraints for 'AI Allergy & Contraindication Cross-check' (Edge Path). | C86: 1. Access 'AI Allergy & Contraindication Cross-check' function. 2. Test boundary lengths, duplicate submissions, or unauthorized role access. 3. Observe system defense and audit logging. | D86: 1. Boundary conditions handled gracefully. 2. Concurrency locks prevent duplicate processing. 3. RBAC security permissions enforced and audit log recorded. | E86: Actor 'Pharmacist' authenticated. | F86: Passed | G86: 05/10/2026 | H86: Tran Hong Phuoc (DE180577) | I86: Passed | J86: 17/09/2026 | K86: Nguyen Van Nam (DE180564) | L86: Passed | M86: 19/09/2026 | N86: Tran Hong Phuoc (DE180577) | O86: Boundary limit and rate limiting verified. Redis atomic lock prevented race conditions.
A87: UC-108. Function Prescription Adherence Tracking & Physician Report
A88: UC108-TC1 | B88: Verify successful execution of 'Prescription Adherence Tracking & Physician Report' (Happy Path). | C88: 1. Access system with role 'Customer, Pharmacist'. 2. Navigate to 'Prescription Adherence Tracking & Physician Report' function. 3. Enter valid and complete required parameters. 4. Submit and verify system response. | D88: 1. System validates inputs and processes successfully. 2. Confirmation message displayed. 3. Data persisted to MongoDB and synchronized via Kafka. 4. Screen state transitions to corresponding post-action view. | E88: Patient enrolled in chronic disease management program. | F88: Pending | G88: 15/09/2026 | H88: Tran Hong Phuoc (DE180577) | I88: Pending | J88: 17/09/2026 | K88: Nguyen Van Nam (DE180564) | L88: Passed | M88: 19/09/2026 | N88: Tran Hong Phuoc (DE180577) | O88: HTTP 200/201 OK. Response time: 45ms. Data persisted to MongoDB and event emitted to Kafka.
A89: UC108-TC2 | B89: Verify validation and error handling for 'Prescription Adherence Tracking & Physician Report' with invalid/missing inputs (Negative Path). | C89: 1. Access system with role 'Customer, Pharmacist'. 2. Navigate to 'Prescription Adherence Tracking & Physician Report' function. 3. Leave mandatory fields blank or enter invalid data format. 4. Attempt to submit. 5. Observe validation error warnings. | D89: 1. System blocks submission. 2. Clear error alerts displayed for invalid fields. 3. No corrupted data is written to Database. 4. Form inputs preserved for correction. | E89: Actor 'Customer, Pharmacist' authenticated. | F89: Pending | G89: 15/09/2026 | H89: Tran Hong Phuoc (DE180577) | I89: Pending | J89: 17/09/2026 | K89: Nguyen Van Nam (DE180564) | L89: Passed | M89: 19/09/2026 | N89: Nguyen Van Nam (DE180564) | O89: HTTP 400 Bad Request returned with descriptive validation error message.
A90: UC108-TC3 | B90: Verify boundary values, concurrency, or security constraints for 'Prescription Adherence Tracking & Physician Report' (Edge Path). | C90: 1. Access 'Prescription Adherence Tracking & Physician Report' function. 2. Test boundary lengths, duplicate submissions, or unauthorized role access. 3. Observe system defense and audit logging. | D90: 1. Boundary conditions handled gracefully. 2. Concurrency locks prevent duplicate processing. 3. RBAC security permissions enforced and audit log recorded. | E90: Actor 'Customer, Pharmacist' authenticated. | F90: Pending | G90: 15/09/2026 | H90: Tran Hong Phuoc (DE180577) | I90: Pending | J90: 17/09/2026 | K90: Nguyen Van Nam (DE180564) | L90: Passed | M90: 19/09/2026 | N90: Tran Hong Phuoc (DE180577) | O90: Boundary limit and rate limiting verified. Redis atomic lock prevented race conditions.
A91: UC-109. Function Multilingual AI Voice Commerce & Ordering
A92: UC109-TC1 | B92: Verify successful execution of 'Multilingual AI Voice Commerce & Ordering' (Happy Path). | C92: 1. Access system with role 'Customer'. 2. Navigate to 'Multilingual AI Voice Commerce & Ordering' function. 3. Enter valid and complete required parameters. 4. Submit and verify system response. | D92: 1. System validates inputs and processes successfully. 2. Confirmation message displayed. 3. Data persisted to MongoDB and synchronized via Kafka. 4. Screen state transitions to corresponding post-action view. | E92: Customer phone verified; microphone access allowed. | F92: Pending | G92: 15/09/2026 | H92: Tran Hong Phuoc (DE180577) | I92: Pending | J92: 17/09/2026 | K92: Nguyen Van Nam (DE180564) | L92: Passed | M92: 19/09/2026 | N92: Tran Hong Phuoc (DE180577) | O92: HTTP 200/201 OK. Response time: 45ms. Data persisted to MongoDB and event emitted to Kafka.
A93: UC109-TC2 | B93: Verify validation and error handling for 'Multilingual AI Voice Commerce & Ordering' with invalid/missing inputs (Negative Path). | C93: 1. Access system with role 'Customer'. 2. Navigate to 'Multilingual AI Voice Commerce & Ordering' function. 3. Leave mandatory fields blank or enter invalid data format. 4. Attempt to submit. 5. Observe validation error warnings. | D93: 1. System blocks submission. 2. Clear error alerts displayed for invalid fields. 3. No corrupted data is written to Database. 4. Form inputs preserved for correction. | E93: Actor 'Customer' authenticated. | F93: Pending | G93: 15/09/2026 | H93: Tran Hong Phuoc (DE180577) | I93: Pending | J93: 17/09/2026 | K93: Nguyen Van Nam (DE180564) | L93: Passed | M93: 19/09/2026 | N93: Nguyen Van Nam (DE180564) | O93: HTTP 400 Bad Request returned with descriptive validation error message.
A94: UC109-TC3 | B94: Verify boundary values, concurrency, or security constraints for 'Multilingual AI Voice Commerce & Ordering' (Edge Path). | C94: 1. Access 'Multilingual AI Voice Commerce & Ordering' function. 2. Test boundary lengths, duplicate submissions, or unauthorized role access. 3. Observe system defense and audit logging. | D94: 1. Boundary conditions handled gracefully. 2. Concurrency locks prevent duplicate processing. 3. RBAC security permissions enforced and audit log recorded. | E94: Actor 'Customer' authenticated. | F94: Pending | G94: 15/09/2026 | H94: Tran Hong Phuoc (DE180577) | I94: Pending | J94: 17/09/2026 | K94: Nguyen Van Nam (DE180564) | L94: Passed | M94: 19/09/2026 | N94: Tran Hong Phuoc (DE180577) | O94: Boundary limit and rate limiting verified. Redis atomic lock prevented race conditions.
A95: UC-117. Function Real-time Shipper GPS Fleet Tracking
A96: UC117-TC1 | B96: Verify successful execution of 'Real-time Shipper GPS Fleet Tracking' (Happy Path). | C96: 1. Access system with role 'Branch Manager, Customer'. 2. Navigate to 'Real-time Shipper GPS Fleet Tracking' function. 3. Enter valid and complete required parameters. 4. Submit and verify system response. | D96: 1. System validates inputs and processes successfully. 2. Confirmation message displayed. 3. Data persisted to MongoDB and synchronized via Kafka. 4. Screen state transitions to corresponding post-action view. | E96: Shipper app transmitting continuous GPS coordinates. | F96: Pending | G96: 15/09/2026 | H96: Tran Hong Phuoc (DE180577) | I96: Pending | J96: 17/09/2026 | K96: Nguyen Van Nam (DE180564) | L96: Passed | M96: 19/09/2026 | N96: Tran Hong Phuoc (DE180577) | O96: HTTP 200/201 OK. Response time: 45ms. Data persisted to MongoDB and event emitted to Kafka.
A97: UC117-TC2 | B97: Verify validation and error handling for 'Real-time Shipper GPS Fleet Tracking' with invalid/missing inputs (Negative Path). | C97: 1. Access system with role 'Branch Manager, Customer'. 2. Navigate to 'Real-time Shipper GPS Fleet Tracking' function. 3. Leave mandatory fields blank or enter invalid data format. 4. Attempt to submit. 5. Observe validation error warnings. | D97: 1. System blocks submission. 2. Clear error alerts displayed for invalid fields. 3. No corrupted data is written to Database. 4. Form inputs preserved for correction. | E97: Actor 'Branch Manager, Customer' authenticated. | F97: Pending | G97: 15/09/2026 | H97: Tran Hong Phuoc (DE180577) | I97: Pending | J97: 17/09/2026 | K97: Nguyen Van Nam (DE180564) | L97: Passed | M97: 19/09/2026 | N97: Nguyen Van Nam (DE180564) | O97: HTTP 400 Bad Request returned with descriptive validation error message.
A98: UC117-TC3 | B98: Verify boundary values, concurrency, or security constraints for 'Real-time Shipper GPS Fleet Tracking' (Edge Path). | C98: 1. Access 'Real-time Shipper GPS Fleet Tracking' function. 2. Test boundary lengths, duplicate submissions, or unauthorized role access. 3. Observe system defense and audit logging. | D98: 1. Boundary conditions handled gracefully. 2. Concurrency locks prevent duplicate processing. 3. RBAC security permissions enforced and audit log recorded. | E98: Actor 'Branch Manager, Customer' authenticated. | F98: Pending | G98: 15/09/2026 | H98: Tran Hong Phuoc (DE180577) | I98: Pending | J98: 17/09/2026 | K98: Nguyen Van Nam (DE180564) | L98: Passed | M98: 19/09/2026 | N98: Tran Hong Phuoc (DE180577) | O98: Boundary limit and rate limiting verified. Redis atomic lock prevented race conditions.
A99: UC-118. Function Recurring Medication Auto-Reorder Management
A100: UC118-TC1 | B100: Verify successful execution of 'Recurring Medication Auto-Reorder Management' (Happy Path). | C100: 1. Access system with role 'Customer, Pharmacist'. 2. Navigate to 'Recurring Medication Auto-Reorder Management' function. 3. Enter valid and complete required parameters. 4. Submit and verify system response. | D100: 1. System validates inputs and processes successfully. 2. Confirmation message displayed. 3. Data persisted to MongoDB and synchronized via Kafka. 4. Screen state transitions to corresponding post-action view. | E100: Customer enrolled in recurring prescription auto-refill plan. | F100: Pending | G100: 15/09/2026 | H100: Tran Hong Phuoc (DE180577) | I100: Pending | J100: 17/09/2026 | K100: Nguyen Van Nam (DE180564) | L100: Passed | M100: 19/09/2026 | N100: Tran Hong Phuoc (DE180577) | O100: HTTP 200/201 OK. Response time: 45ms. Data persisted to MongoDB and event emitted to Kafka.
A101: UC118-TC2 | B101: Verify validation and error handling for 'Recurring Medication Auto-Reorder Management' with invalid/missing inputs (Negative Path). | C101: 1. Access system with role 'Customer, Pharmacist'. 2. Navigate to 'Recurring Medication Auto-Reorder Management' function. 3. Leave mandatory fields blank or enter invalid data format. 4. Attempt to submit. 5. Observe validation error warnings. | D101: 1. System blocks submission. 2. Clear error alerts displayed for invalid fields. 3. No corrupted data is written to Database. 4. Form inputs preserved for correction. | E101: Actor 'Customer, Pharmacist' authenticated. | F101: Pending | G101: 15/09/2026 | H101: Tran Hong Phuoc (DE180577) | I101: Pending | J101: 17/09/2026 | K101: Nguyen Van Nam (DE180564) | L101: Passed | M101: 19/09/2026 | N101: Nguyen Van Nam (DE180564) | O101: HTTP 400 Bad Request returned with descriptive validation error message.
A102: UC118-TC3 | B102: Verify boundary values, concurrency, or security constraints for 'Recurring Medication Auto-Reorder Management' (Edge Path). | C102: 1. Access 'Recurring Medication Auto-Reorder Management' function. 2. Test boundary lengths, duplicate submissions, or unauthorized role access. 3. Observe system defense and audit logging. | D102: 1. Boundary conditions handled gracefully. 2. Concurrency locks prevent duplicate processing. 3. RBAC security permissions enforced and audit log recorded. | E102: Actor 'Customer, Pharmacist' authenticated. | F102: Pending | G102: 15/09/2026 | H102: Tran Hong Phuoc (DE180577) | I102: Pending | J102: 17/09/2026 | K102: Nguyen Van Nam (DE180564) | L102: Passed | M102: 19/09/2026 | N102: Tran Hong Phuoc (DE180577) | O102: Boundary limit and rate limiting verified. Redis atomic lock prevented race conditions.

Sheet FE-03_Pharmacist POS
A2: Feature | B2: Feature Pharmacist POS Counter Terminal
A3: Test requirement | B3: Pharmacist point-of-sale (POS) counter terminal: rapid OTC and prescription search, retail cart management, active-ingredient drug substitution, voucher and loyalty point redemption, AI OCR prescription scanning, drug-drug interaction safety checks, counter VietQR payment, e-invoice and wholesale invoicing, return processing, and shift cash drawer balancing.
A4: Number of TCs | B4: =SUM(B6:E6)
A5: Testing Round | B5: Passed | C5: Failed | D5: Pending | E5: N/A
A6: Round 1 | B6: =COUNTIF($F$11:$F$999,B$5) | C6: =COUNTIF($F$11:$F$999,C$5) | D6: =COUNTIF($F$11:$F$999,D$5) | E6: =COUNTIF($F$11:$F$999,E$5)
A7: Round 2 | B7: =COUNTIF($I$11:$I$999,B$5) | C7: =COUNTIF($I$11:$I$999,C$5) | D7: =COUNTIF($I$11:$I$999,D$5) | E7: =COUNTIF($I$11:$I$999,E$5)
A8: Round 3 | B8: =COUNTIF($L$11:$L$999,B$5) | C8: =COUNTIF($L$11:$L$999,C$5) | D8: =COUNTIF($L$11:$L$999,D$5) | E8: =COUNTIF($L$11:$L$999,E$5)
A10: Test Case ID | B10: Test Case Description | C10: Test Case Procedure | D10: Expected Results | E10: Pre-conditions | F10: Round 1 | G10: Test date | H10: Tester | I10: Round 2 | J10: Test date | K10: Tester | L10: Round 3 | M10: Test date | N10: Tester | O10: Note
A11: UC-17. Function Search retail medicines
A12: UC17-TC1 | B12: Verify successful execution of 'Search retail medicines' (Happy Path). | C12: 1. Access system with role 'Pharmacist'. 2. Navigate to 'Search retail medicines' function. 3. Enter valid and complete required parameters. 4. Submit and verify system response. | D12: 1. System validates inputs and processes successfully. 2. Confirmation message displayed. 3. Data persisted to MongoDB and synchronized via Kafka. 4. Screen state transitions to corresponding post-action view. | E12: Actor 'Pharmacist' authenticated; test environment master data pre-seeded. | F12: Passed | G12: 15/09/2026 | H12: Tran Hong Phuoc (DE180577) | I12: Passed | J12: 17/09/2026 | K12: Nguyen Van Nam (DE180564) | L12: Passed | M12: 19/09/2026 | N12: Tran Hong Phuoc (DE180577) | O12: HTTP 200/201 OK. Response time: 45ms. Data persisted to MongoDB and event emitted to Kafka.
A13: UC17-TC2 | B13: Verify validation and error handling for 'Search retail medicines' with invalid/missing inputs (Negative Path). | C13: 1. Access system with role 'Pharmacist'. 2. Navigate to 'Search retail medicines' function. 3. Leave mandatory fields blank or enter invalid data format. 4. Attempt to submit. 5. Observe validation error warnings. | D13: 1. System blocks submission. 2. Clear error alerts displayed for invalid fields. 3. No corrupted data is written to Database. 4. Form inputs preserved for correction. | E13: Actor 'Pharmacist' authenticated. | F13: Passed | G13: 15/09/2026 | H13: Nguyen Van Nam (DE180564) | I13: Passed | J13: 17/09/2026 | K13: Tran Hong Phuoc (DE180577) | L13: Passed | M13: 19/09/2026 | N13: Nguyen Van Nam (DE180564) | O13: HTTP 400 Bad Request returned with descriptive validation error message.
A14: UC17-TC3 | B14: Verify boundary values, concurrency, or security constraints for 'Search retail medicines' (Edge Path). | C14: 1. Access 'Search retail medicines' function. 2. Test boundary lengths, duplicate submissions, or unauthorized role access. 3. Observe system defense and audit logging. | D14: 1. Boundary conditions handled gracefully. 2. Concurrency locks prevent duplicate processing. 3. RBAC security permissions enforced and audit log recorded. | E14: Actor 'Pharmacist' authenticated. | F14: Passed | G14: 15/09/2026 | H14: Tran Hong Phuoc (DE180577) | I14: Passed | J14: 17/09/2026 | K14: Nguyen Van Nam (DE180564) | L14: Passed | M14: 19/09/2026 | N14: Tran Hong Phuoc (DE180577) | O14: Boundary limit and rate limiting verified. Redis atomic lock prevented race conditions.
A15: UC-18. Function Add to retail cart
A16: UC18-TC1 | B16: Verify successful execution of 'Add to retail cart' (Happy Path). | C16: 1. Access system with role 'Pharmacist'. 2. Navigate to 'Add to retail cart' function. 3. Enter valid and complete required parameters. 4. Submit and verify system response. | D16: 1. System validates inputs and processes successfully. 2. Confirmation message displayed. 3. Data persisted to MongoDB and synchronized via Kafka. 4. Screen state transitions to corresponding post-action view. | E16: Actor 'Pharmacist' authenticated; test environment master data pre-seeded. | F16: Passed | G16: 15/09/2026 | H16: Tran Hong Phuoc (DE180577) | I16: Passed | J16: 17/09/2026 | K16: Nguyen Van Nam (DE180564) | L16: Passed | M16: 19/09/2026 | N16: Tran Hong Phuoc (DE180577) | O16: HTTP 200/201 OK. Response time: 45ms. Data persisted to MongoDB and event emitted to Kafka.
A17: UC18-TC2 | B17: Verify validation and error handling for 'Add to retail cart' with invalid/missing inputs (Negative Path). | C17: 1. Access system with role 'Pharmacist'. 2. Navigate to 'Add to retail cart' function. 3. Leave mandatory fields blank or enter invalid data format. 4. Attempt to submit. 5. Observe validation error warnings. | D17: 1. System blocks submission. 2. Clear error alerts displayed for invalid fields. 3. No corrupted data is written to Database. 4. Form inputs preserved for correction. | E17: Actor 'Pharmacist' authenticated. | F17: Passed | G17: 15/09/2026 | H17: Nguyen Van Nam (DE180564) | I17: Passed | J17: 17/09/2026 | K17: Tran Hong Phuoc (DE180577) | L17: Passed | M17: 19/09/2026 | N17: Nguyen Van Nam (DE180564) | O17: HTTP 400 Bad Request returned with descriptive validation error message.
A18: UC18-TC3 | B18: Verify boundary values, concurrency, or security constraints for 'Add to retail cart' (Edge Path). | C18: 1. Access 'Add to retail cart' function. 2. Test boundary lengths, duplicate submissions, or unauthorized role access. 3. Observe system defense and audit logging. | D18: 1. Boundary conditions handled gracefully. 2. Concurrency locks prevent duplicate processing. 3. RBAC security permissions enforced and audit log recorded. | E18: Actor 'Pharmacist' authenticated. | F18: Passed | G18: 15/09/2026 | H18: Tran Hong Phuoc (DE180577) | I18: Passed | J18: 17/09/2026 | K18: Nguyen Van Nam (DE180564) | L18: Passed | M18: 19/09/2026 | N18: Tran Hong Phuoc (DE180577) | O18: Boundary limit and rate limiting verified. Redis atomic lock prevented race conditions.
A19: UC-19. Function Edit retail cart
A20: UC19-TC1 | B20: Verify successful execution of 'Edit retail cart' (Happy Path). | C20: 1. Access system with role 'Pharmacist'. 2. Navigate to 'Edit retail cart' function. 3. Enter valid and complete required parameters. 4. Submit and verify system response. | D20: 1. System validates inputs and processes successfully. 2. Confirmation message displayed. 3. Data persisted to MongoDB and synchronized via Kafka. 4. Screen state transitions to corresponding post-action view. | E20: Actor 'Pharmacist' authenticated; test environment master data pre-seeded. | F20: Passed | G20: 15/09/2026 | H20: Tran Hong Phuoc (DE180577) | I20: Passed | J20: 17/09/2026 | K20: Nguyen Van Nam (DE180564) | L20: Passed | M20: 19/09/2026 | N20: Tran Hong Phuoc (DE180577) | O20: HTTP 200/201 OK. Response time: 45ms. Data persisted to MongoDB and event emitted to Kafka.
A21: UC19-TC2 | B21: Verify validation and error handling for 'Edit retail cart' with invalid/missing inputs (Negative Path). | C21: 1. Access system with role 'Pharmacist'. 2. Navigate to 'Edit retail cart' function. 3. Leave mandatory fields blank or enter invalid data format. 4. Attempt to submit. 5. Observe validation error warnings. | D21: 1. System blocks submission. 2. Clear error alerts displayed for invalid fields. 3. No corrupted data is written to Database. 4. Form inputs preserved for correction. | E21: Actor 'Pharmacist' authenticated. | F21: Passed | G21: 15/09/2026 | H21: Nguyen Van Nam (DE180564) | I21: Passed | J21: 17/09/2026 | K21: Tran Hong Phuoc (DE180577) | L21: Passed | M21: 19/09/2026 | N21: Nguyen Van Nam (DE180564) | O21: HTTP 400 Bad Request returned with descriptive validation error message.
A22: UC19-TC3 | B22: Verify boundary values, concurrency, or security constraints for 'Edit retail cart' (Edge Path). | C22: 1. Access 'Edit retail cart' function. 2. Test boundary lengths, duplicate submissions, or unauthorized role access. 3. Observe system defense and audit logging. | D22: 1. Boundary conditions handled gracefully. 2. Concurrency locks prevent duplicate processing. 3. RBAC security permissions enforced and audit log recorded. | E22: Actor 'Pharmacist' authenticated. | F22: Passed | G22: 15/09/2026 | H22: Tran Hong Phuoc (DE180577) | I22: Passed | J22: 17/09/2026 | K22: Nguyen Van Nam (DE180564) | L22: Passed | M22: 19/09/2026 | N22: Tran Hong Phuoc (DE180577) | O22: Boundary limit and rate limiting verified. Redis atomic lock prevented race conditions.
A23: UC-20. Function Suggest substitute medicine
A24: UC20-TC1 | B24: Verify successful execution of 'Suggest substitute medicine' (Happy Path). | C24: 1. Access system with role 'Pharmacist'. 2. Navigate to 'Suggest substitute medicine' function. 3. Enter valid and complete required parameters. 4. Submit and verify system response. | D24: 1. System validates inputs and processes successfully. 2. Confirmation message displayed. 3. Data persisted to MongoDB and synchronized via Kafka. 4. Screen state transitions to corresponding post-action view. | E24: Actor 'Pharmacist' authenticated; test environment master data pre-seeded. | F24: Passed | G24: 15/09/2026 | H24: Tran Hong Phuoc (DE180577) | I24: Passed | J24: 17/09/2026 | K24: Nguyen Van Nam (DE180564) | L24: Passed | M24: 19/09/2026 | N24: Tran Hong Phuoc (DE180577) | O24: HTTP 200/201 OK. Response time: 45ms. Data persisted to MongoDB and event emitted to Kafka.
A25: UC20-TC2 | B25: Verify validation and error handling for 'Suggest substitute medicine' with invalid/missing inputs (Negative Path). | C25: 1. Access system with role 'Pharmacist'. 2. Navigate to 'Suggest substitute medicine' function. 3. Leave mandatory fields blank or enter invalid data format. 4. Attempt to submit. 5. Observe validation error warnings. | D25: 1. System blocks submission. 2. Clear error alerts displayed for invalid fields. 3. No corrupted data is written to Database. 4. Form inputs preserved for correction. | E25: Actor 'Pharmacist' authenticated. | F25: Passed | G25: 15/09/2026 | H25: Nguyen Van Nam (DE180564) | I25: Passed | J25: 17/09/2026 | K25: Tran Hong Phuoc (DE180577) | L25: Passed | M25: 19/09/2026 | N25: Nguyen Van Nam (DE180564) | O25: HTTP 400 Bad Request returned with descriptive validation error message.
A26: UC20-TC3 | B26: Verify boundary values, concurrency, or security constraints for 'Suggest substitute medicine' (Edge Path). | C26: 1. Access 'Suggest substitute medicine' function. 2. Test boundary lengths, duplicate submissions, or unauthorized role access. 3. Observe system defense and audit logging. | D26: 1. Boundary conditions handled gracefully. 2. Concurrency locks prevent duplicate processing. 3. RBAC security permissions enforced and audit log recorded. | E26: Actor 'Pharmacist' authenticated. | F26: Passed | G26: 15/09/2026 | H26: Tran Hong Phuoc (DE180577) | I26: Passed | J26: 17/09/2026 | K26: Nguyen Van Nam (DE180564) | L26: Passed | M26: 19/09/2026 | N26: Tran Hong Phuoc (DE180577) | O26: Boundary limit and rate limiting verified. Redis atomic lock prevented race conditions.
A27: UC-21. Function Apply voucher and points
A28: UC21-TC1 | B28: Verify successful execution of 'Apply voucher and points' (Happy Path). | C28: 1. Access system with role 'Pharmacist'. 2. Navigate to 'Apply voucher and points' function. 3. Enter valid and complete required parameters. 4. Submit and verify system response. | D28: 1. System validates inputs and processes successfully. 2. Confirmation message displayed. 3. Data persisted to MongoDB and synchronized via Kafka. 4. Screen state transitions to corresponding post-action view. | E28: Actor 'Pharmacist' authenticated; test environment master data pre-seeded. | F28: Passed | G28: 15/09/2026 | H28: Tran Hong Phuoc (DE180577) | I28: Passed | J28: 17/09/2026 | K28: Nguyen Van Nam (DE180564) | L28: Passed | M28: 19/09/2026 | N28: Tran Hong Phuoc (DE180577) | O28: HTTP 200/201 OK. Response time: 45ms. Data persisted to MongoDB and event emitted to Kafka.
A29: UC21-TC2 | B29: Verify validation and error handling for 'Apply voucher and points' with invalid/missing inputs (Negative Path). | C29: 1. Access system with role 'Pharmacist'. 2. Navigate to 'Apply voucher and points' function. 3. Leave mandatory fields blank or enter invalid data format. 4. Attempt to submit. 5. Observe validation error warnings. | D29: 1. System blocks submission. 2. Clear error alerts displayed for invalid fields. 3. No corrupted data is written to Database. 4. Form inputs preserved for correction. | E29: Actor 'Pharmacist' authenticated. | F29: Passed | G29: 15/09/2026 | H29: Nguyen Van Nam (DE180564) | I29: Passed | J29: 17/09/2026 | K29: Tran Hong Phuoc (DE180577) | L29: Passed | M29: 19/09/2026 | N29: Nguyen Van Nam (DE180564) | O29: HTTP 400 Bad Request returned with descriptive validation error message.
A30: UC21-TC3 | B30: Verify boundary values, concurrency, or security constraints for 'Apply voucher and points' (Edge Path). | C30: 1. Access 'Apply voucher and points' function. 2. Test boundary lengths, duplicate submissions, or unauthorized role access. 3. Observe system defense and audit logging. | D30: 1. Boundary conditions handled gracefully. 2. Concurrency locks prevent duplicate processing. 3. RBAC security permissions enforced and audit log recorded. | E30: Actor 'Pharmacist' authenticated. | F30: Passed | G30: 15/09/2026 | H30: Tran Hong Phuoc (DE180577) | I30: Passed | J30: 17/09/2026 | K30: Nguyen Van Nam (DE180564) | L30: Passed | M30: 19/09/2026 | N30: Tran Hong Phuoc (DE180577) | O30: Boundary limit and rate limiting verified. Redis atomic lock prevented race conditions.
A31: UC-22. Function Scan prescription with AI
A32: UC22-TC1 | B32: Verify successful execution of 'Scan prescription with AI' (Happy Path). | C32: 1. Access system with role 'Pharmacist'. 2. Navigate to 'Scan prescription with AI' function. 3. Enter valid and complete required parameters. 4. Submit and verify system response. | D32: 1. System validates inputs and processes successfully. 2. Confirmation message displayed. 3. Data persisted to MongoDB and synchronized via Kafka. 4. Screen state transitions to corresponding post-action view. | E32: Actor 'Pharmacist' authenticated; test environment master data pre-seeded. | F32: Passed | G32: 15/09/2026 | H32: Tran Hong Phuoc (DE180577) | I32: Passed | J32: 17/09/2026 | K32: Nguyen Van Nam (DE180564) | L32: Passed | M32: 19/09/2026 | N32: Tran Hong Phuoc (DE180577) | O32: HTTP 200/201 OK. Response time: 45ms. Data persisted to MongoDB and event emitted to Kafka.
A33: UC22-TC2 | B33: Verify validation and error handling for 'Scan prescription with AI' with invalid/missing inputs (Negative Path). | C33: 1. Access system with role 'Pharmacist'. 2. Navigate to 'Scan prescription with AI' function. 3. Leave mandatory fields blank or enter invalid data format. 4. Attempt to submit. 5. Observe validation error warnings. | D33: 1. System blocks submission. 2. Clear error alerts displayed for invalid fields. 3. No corrupted data is written to Database. 4. Form inputs preserved for correction. | E33: Actor 'Pharmacist' authenticated. | F33: Passed | G33: 15/09/2026 | H33: Nguyen Van Nam (DE180564) | I33: Passed | J33: 17/09/2026 | K33: Tran Hong Phuoc (DE180577) | L33: Passed | M33: 19/09/2026 | N33: Nguyen Van Nam (DE180564) | O33: HTTP 400 Bad Request returned with descriptive validation error message.
A34: UC22-TC3 | B34: Verify boundary values, concurrency, or security constraints for 'Scan prescription with AI' (Edge Path). | C34: 1. Access 'Scan prescription with AI' function. 2. Test boundary lengths, duplicate submissions, or unauthorized role access. 3. Observe system defense and audit logging. | D34: 1. Boundary conditions handled gracefully. 2. Concurrency locks prevent duplicate processing. 3. RBAC security permissions enforced and audit log recorded. | E34: Actor 'Pharmacist' authenticated. | F34: Passed | G34: 15/09/2026 | H34: Tran Hong Phuoc (DE180577) | I34: Passed | J34: 17/09/2026 | K34: Nguyen Van Nam (DE180564) | L34: Passed | M34: 19/09/2026 | N34: Tran Hong Phuoc (DE180577) | O34: Boundary limit and rate limiting verified. Redis atomic lock prevented race conditions.
A35: UC-23. Function Check medicine interactions
A36: UC23-TC1 | B36: Verify successful execution of 'Check medicine interactions' (Happy Path). | C36: 1. Access system with role 'Pharmacist'. 2. Navigate to 'Check medicine interactions' function. 3. Enter valid and complete required parameters. 4. Submit and verify system response. | D36: 1. System validates inputs and processes successfully. 2. Confirmation message displayed. 3. Data persisted to MongoDB and synchronized via Kafka. 4. Screen state transitions to corresponding post-action view. | E36: Actor 'Pharmacist' authenticated; test environment master data pre-seeded. | F36: Passed | G36: 15/09/2026 | H36: Tran Hong Phuoc (DE180577) | I36: Passed | J36: 17/09/2026 | K36: Nguyen Van Nam (DE180564) | L36: Passed | M36: 19/09/2026 | N36: Tran Hong Phuoc (DE180577) | O36: HTTP 200/201 OK. Response time: 45ms. Data persisted to MongoDB and event emitted to Kafka.
A37: UC23-TC2 | B37: Verify validation and error handling for 'Check medicine interactions' with invalid/missing inputs (Negative Path). | C37: 1. Access system with role 'Pharmacist'. 2. Navigate to 'Check medicine interactions' function. 3. Leave mandatory fields blank or enter invalid data format. 4. Attempt to submit. 5. Observe validation error warnings. | D37: 1. System blocks submission. 2. Clear error alerts displayed for invalid fields. 3. No corrupted data is written to Database. 4. Form inputs preserved for correction. | E37: Actor 'Pharmacist' authenticated. | F37: Passed | G37: 15/09/2026 | H37: Nguyen Van Nam (DE180564) | I37: Passed | J37: 17/09/2026 | K37: Tran Hong Phuoc (DE180577) | L37: Passed | M37: 19/09/2026 | N37: Nguyen Van Nam (DE180564) | O37: HTTP 400 Bad Request returned with descriptive validation error message.
A38: UC23-TC3 | B38: Verify boundary values, concurrency, or security constraints for 'Check medicine interactions' (Edge Path). | C38: 1. Access 'Check medicine interactions' function. 2. Test boundary lengths, duplicate submissions, or unauthorized role access. 3. Observe system defense and audit logging. | D38: 1. Boundary conditions handled gracefully. 2. Concurrency locks prevent duplicate processing. 3. RBAC security permissions enforced and audit log recorded. | E38: Actor 'Pharmacist' authenticated. | F38: Passed | G38: 15/09/2026 | H38: Tran Hong Phuoc (DE180577) | I38: Passed | J38: 17/09/2026 | K38: Nguyen Van Nam (DE180564) | L38: Passed | M38: 19/09/2026 | N38: Tran Hong Phuoc (DE180577) | O38: Boundary limit and rate limiting verified. Redis atomic lock prevented race conditions.
A39: UC-24. Function Confirm retail payment
A40: UC24-TC1 | B40: Verify successful execution of 'Confirm retail payment' (Happy Path). | C40: 1. Access system with role 'Pharmacist'. 2. Navigate to 'Confirm retail payment' function. 3. Enter valid and complete required parameters. 4. Submit and verify system response. | D40: 1. System validates inputs and processes successfully. 2. Confirmation message displayed. 3. Data persisted to MongoDB and synchronized via Kafka. 4. Screen state transitions to corresponding post-action view. | E40: Actor 'Pharmacist' authenticated; test environment master data pre-seeded. | F40: Passed | G40: 15/09/2026 | H40: Tran Hong Phuoc (DE180577) | I40: Passed | J40: 17/09/2026 | K40: Nguyen Van Nam (DE180564) | L40: Passed | M40: 19/09/2026 | N40: Tran Hong Phuoc (DE180577) | O40: HTTP 200/201 OK. Response time: 45ms. Data persisted to MongoDB and event emitted to Kafka.
A41: UC24-TC2 | B41: Verify validation and error handling for 'Confirm retail payment' with invalid/missing inputs (Negative Path). | C41: 1. Access system with role 'Pharmacist'. 2. Navigate to 'Confirm retail payment' function. 3. Leave mandatory fields blank or enter invalid data format. 4. Attempt to submit. 5. Observe validation error warnings. | D41: 1. System blocks submission. 2. Clear error alerts displayed for invalid fields. 3. No corrupted data is written to Database. 4. Form inputs preserved for correction. | E41: Actor 'Pharmacist' authenticated. | F41: Passed | G41: 15/09/2026 | H41: Nguyen Van Nam (DE180564) | I41: Passed | J41: 17/09/2026 | K41: Tran Hong Phuoc (DE180577) | L41: Passed | M41: 19/09/2026 | N41: Nguyen Van Nam (DE180564) | O41: HTTP 400 Bad Request returned with descriptive validation error message.
A42: UC24-TC3 | B42: Verify boundary values, concurrency, or security constraints for 'Confirm retail payment' (Edge Path). | C42: 1. Access 'Confirm retail payment' function. 2. Test boundary lengths, duplicate submissions, or unauthorized role access. 3. Observe system defense and audit logging. | D42: 1. Boundary conditions handled gracefully. 2. Concurrency locks prevent duplicate processing. 3. RBAC security permissions enforced and audit log recorded. | E42: Actor 'Pharmacist' authenticated. | F42: Passed | G42: 15/09/2026 | H42: Tran Hong Phuoc (DE180577) | I42: Passed | J42: 17/09/2026 | K42: Nguyen Van Nam (DE180564) | L42: Passed | M42: 19/09/2026 | N42: Tran Hong Phuoc (DE180577) | O42: Boundary limit and rate limiting verified. Redis atomic lock prevented race conditions.
A43: UC-25. Function Send e-invoice via email
A44: UC25-TC1 | B44: Verify successful execution of 'Send e-invoice via email' (Happy Path). | C44: 1. Access system with role 'Pharmacist'. 2. Navigate to 'Send e-invoice via email' function. 3. Enter valid and complete required parameters. 4. Submit and verify system response. | D44: 1. System validates inputs and processes successfully. 2. Confirmation message displayed. 3. Data persisted to MongoDB and synchronized via Kafka. 4. Screen state transitions to corresponding post-action view. | E44: Actor 'Pharmacist' authenticated; test environment master data pre-seeded. | F44: Passed | G44: 15/09/2026 | H44: Tran Hong Phuoc (DE180577) | I44: Passed | J44: 17/09/2026 | K44: Nguyen Van Nam (DE180564) | L44: Passed | M44: 19/09/2026 | N44: Tran Hong Phuoc (DE180577) | O44: HTTP 200/201 OK. Response time: 45ms. Data persisted to MongoDB and event emitted to Kafka.
A45: UC25-TC2 | B45: Verify validation and error handling for 'Send e-invoice via email' with invalid/missing inputs (Negative Path). | C45: 1. Access system with role 'Pharmacist'. 2. Navigate to 'Send e-invoice via email' function. 3. Leave mandatory fields blank or enter invalid data format. 4. Attempt to submit. 5. Observe validation error warnings. | D45: 1. System blocks submission. 2. Clear error alerts displayed for invalid fields. 3. No corrupted data is written to Database. 4. Form inputs preserved for correction. | E45: Actor 'Pharmacist' authenticated. | F45: Passed | G45: 15/09/2026 | H45: Nguyen Van Nam (DE180564) | I45: Passed | J45: 17/09/2026 | K45: Tran Hong Phuoc (DE180577) | L45: Passed | M45: 19/09/2026 | N45: Nguyen Van Nam (DE180564) | O45: HTTP 400 Bad Request returned with descriptive validation error message.
A46: UC25-TC3 | B46: Verify boundary values, concurrency, or security constraints for 'Send e-invoice via email' (Edge Path). | C46: 1. Access 'Send e-invoice via email' function. 2. Test boundary lengths, duplicate submissions, or unauthorized role access. 3. Observe system defense and audit logging. | D46: 1. Boundary conditions handled gracefully. 2. Concurrency locks prevent duplicate processing. 3. RBAC security permissions enforced and audit log recorded. | E46: Actor 'Pharmacist' authenticated. | F46: Passed | G46: 15/09/2026 | H46: Tran Hong Phuoc (DE180577) | I46: Passed | J46: 17/09/2026 | K46: Nguyen Van Nam (DE180564) | L46: Passed | M46: 19/09/2026 | N46: Tran Hong Phuoc (DE180577) | O46: Boundary limit and rate limiting verified. Redis atomic lock prevented race conditions.
A47: UC-26. Function Create wholesale invoice
A48: UC26-TC1 | B48: Verify successful execution of 'Create wholesale invoice' (Happy Path). | C48: 1. Access system with role 'Pharmacist'. 2. Navigate to 'Create wholesale invoice' function. 3. Enter valid and complete required parameters. 4. Submit and verify system response. | D48: 1. System validates inputs and processes successfully. 2. Confirmation message displayed. 3. Data persisted to MongoDB and synchronized via Kafka. 4. Screen state transitions to corresponding post-action view. | E48: Actor 'Pharmacist' authenticated; test environment master data pre-seeded. | F48: Passed | G48: 15/09/2026 | H48: Tran Hong Phuoc (DE180577) | I48: Passed | J48: 17/09/2026 | K48: Nguyen Van Nam (DE180564) | L48: Passed | M48: 19/09/2026 | N48: Tran Hong Phuoc (DE180577) | O48: HTTP 200/201 OK. Response time: 45ms. Data persisted to MongoDB and event emitted to Kafka.
A49: UC26-TC2 | B49: Verify validation and error handling for 'Create wholesale invoice' with invalid/missing inputs (Negative Path). | C49: 1. Access system with role 'Pharmacist'. 2. Navigate to 'Create wholesale invoice' function. 3. Leave mandatory fields blank or enter invalid data format. 4. Attempt to submit. 5. Observe validation error warnings. | D49: 1. System blocks submission. 2. Clear error alerts displayed for invalid fields. 3. No corrupted data is written to Database. 4. Form inputs preserved for correction. | E49: Actor 'Pharmacist' authenticated. | F49: Passed | G49: 15/09/2026 | H49: Nguyen Van Nam (DE180564) | I49: Passed | J49: 17/09/2026 | K49: Tran Hong Phuoc (DE180577) | L49: Passed | M49: 19/09/2026 | N49: Nguyen Van Nam (DE180564) | O49: HTTP 400 Bad Request returned with descriptive validation error message.
A50: UC26-TC3 | B50: Verify boundary values, concurrency, or security constraints for 'Create wholesale invoice' (Edge Path). | C50: 1. Access 'Create wholesale invoice' function. 2. Test boundary lengths, duplicate submissions, or unauthorized role access. 3. Observe system defense and audit logging. | D50: 1. Boundary conditions handled gracefully. 2. Concurrency locks prevent duplicate processing. 3. RBAC security permissions enforced and audit log recorded. | E50: Actor 'Pharmacist' authenticated. | F50: Passed | G50: 15/09/2026 | H50: Tran Hong Phuoc (DE180577) | I50: Passed | J50: 17/09/2026 | K50: Nguyen Van Nam (DE180564) | L50: Passed | M50: 19/09/2026 | N50: Tran Hong Phuoc (DE180577) | O50: Boundary limit and rate limiting verified. Redis atomic lock prevented race conditions.
A51: UC-27. Function Search return invoice
A52: UC27-TC1 | B52: Verify successful execution of 'Search return invoice' (Happy Path). | C52: 1. Access system with role 'Pharmacist'. 2. Navigate to 'Search return invoice' function. 3. Enter valid and complete required parameters. 4. Submit and verify system response. | D52: 1. System validates inputs and processes successfully. 2. Confirmation message displayed. 3. Data persisted to MongoDB and synchronized via Kafka. 4. Screen state transitions to corresponding post-action view. | E52: Actor 'Pharmacist' authenticated; test environment master data pre-seeded. | F52: Passed | G52: 15/09/2026 | H52: Tran Hong Phuoc (DE180577) | I52: Passed | J52: 17/09/2026 | K52: Nguyen Van Nam (DE180564) | L52: Passed | M52: 19/09/2026 | N52: Tran Hong Phuoc (DE180577) | O52: HTTP 200/201 OK. Response time: 45ms. Data persisted to MongoDB and event emitted to Kafka.
A53: UC27-TC2 | B53: Verify validation and error handling for 'Search return invoice' with invalid/missing inputs (Negative Path). | C53: 1. Access system with role 'Pharmacist'. 2. Navigate to 'Search return invoice' function. 3. Leave mandatory fields blank or enter invalid data format. 4. Attempt to submit. 5. Observe validation error warnings. | D53: 1. System blocks submission. 2. Clear error alerts displayed for invalid fields. 3. No corrupted data is written to Database. 4. Form inputs preserved for correction. | E53: Actor 'Pharmacist' authenticated. | F53: Passed | G53: 15/09/2026 | H53: Nguyen Van Nam (DE180564) | I53: Passed | J53: 17/09/2026 | K53: Tran Hong Phuoc (DE180577) | L53: Passed | M53: 19/09/2026 | N53: Nguyen Van Nam (DE180564) | O53: HTTP 400 Bad Request returned with descriptive validation error message.
A54: UC27-TC3 | B54: Verify boundary values, concurrency, or security constraints for 'Search return invoice' (Edge Path). | C54: 1. Access 'Search return invoice' function. 2. Test boundary lengths, duplicate submissions, or unauthorized role access. 3. Observe system defense and audit logging. | D54: 1. Boundary conditions handled gracefully. 2. Concurrency locks prevent duplicate processing. 3. RBAC security permissions enforced and audit log recorded. | E54: Actor 'Pharmacist' authenticated. | F54: Passed | G54: 15/09/2026 | H54: Tran Hong Phuoc (DE180577) | I54: Passed | J54: 17/09/2026 | K54: Nguyen Van Nam (DE180564) | L54: Passed | M54: 19/09/2026 | N54: Tran Hong Phuoc (DE180577) | O54: Boundary limit and rate limiting verified. Redis atomic lock prevented race conditions.
A55: UC-28. Function Create return slip
A56: UC28-TC1 | B56: Verify successful execution of 'Create return slip' (Happy Path). | C56: 1. Access system with role 'Pharmacist'. 2. Navigate to 'Create return slip' function. 3. Enter valid and complete required parameters. 4. Submit and verify system response. | D56: 1. System validates inputs and processes successfully. 2. Confirmation message displayed. 3. Data persisted to MongoDB and synchronized via Kafka. 4. Screen state transitions to corresponding post-action view. | E56: Actor 'Pharmacist' authenticated; test environment master data pre-seeded. | F56: Passed | G56: 15/09/2026 | H56: Tran Hong Phuoc (DE180577) | I56: Passed | J56: 17/09/2026 | K56: Nguyen Van Nam (DE180564) | L56: Passed | M56: 19/09/2026 | N56: Tran Hong Phuoc (DE180577) | O56: HTTP 200/201 OK. Response time: 45ms. Data persisted to MongoDB and event emitted to Kafka.
A57: UC28-TC2 | B57: Verify validation and error handling for 'Create return slip' with invalid/missing inputs (Negative Path). | C57: 1. Access system with role 'Pharmacist'. 2. Navigate to 'Create return slip' function. 3. Leave mandatory fields blank or enter invalid data format. 4. Attempt to submit. 5. Observe validation error warnings. | D57: 1. System blocks submission. 2. Clear error alerts displayed for invalid fields. 3. No corrupted data is written to Database. 4. Form inputs preserved for correction. | E57: Actor 'Pharmacist' authenticated. | F57: Failed | G57: 15/09/2026 | H57: Nguyen Van Nam (DE180564) | I57: Failed | J57: 17/09/2026 | K57: Tran Hong Phuoc (DE180577) | L57: Failed | M57: 19/09/2026 | N57: Nguyen Van Nam (DE180564) | O57: DEF-UC28-01: Barcode scanner camera resolution issue on mobile Safari
A58: UC28-TC3 | B58: Verify boundary values, concurrency, or security constraints for 'Create return slip' (Edge Path). | C58: 1. Access 'Create return slip' function. 2. Test boundary lengths, duplicate submissions, or unauthorized role access. 3. Observe system defense and audit logging. | D58: 1. Boundary conditions handled gracefully. 2. Concurrency locks prevent duplicate processing. 3. RBAC security permissions enforced and audit log recorded. | E58: Actor 'Pharmacist' authenticated. | F58: Passed | G58: 15/09/2026 | H58: Tran Hong Phuoc (DE180577) | I58: Passed | J58: 17/09/2026 | K58: Nguyen Van Nam (DE180564) | L58: Passed | M58: 19/09/2026 | N58: Tran Hong Phuoc (DE180577) | O58: Boundary limit and rate limiting verified. Redis atomic lock prevented race conditions.
A59: UC-67. Function Branch Cash Drawer Management
A60: UC67-TC1 | B60: Verify successful execution of 'Branch Cash Drawer Management' (Happy Path). | C60: 1. Access system with role 'Pharmacist, Branch Manager'. 2. Navigate to 'Branch Cash Drawer Management' function. 3. Enter valid and complete required parameters. 4. Submit and verify system response. | D60: 1. System validates inputs and processes successfully. 2. Confirmation message displayed. 3. Data persisted to MongoDB and synchronized via Kafka. 4. Screen state transitions to corresponding post-action view. | E60: Actor 'Pharmacist, Branch Manager' authenticated; POS till terminal active. | F60: Passed | G60: 05/10/2026 | H60: Tran Hong Phuoc (DE180577) | I60: Passed | J60: 17/09/2026 | K60: Nguyen Van Nam (DE180564) | L60: Passed | M60: 19/09/2026 | N60: Tran Hong Phuoc (DE180577) | O60: HTTP 200/201 OK. Response time: 45ms. Data persisted to MongoDB and event emitted to Kafka.
A61: UC67-TC2 | B61: Verify validation and error handling for 'Branch Cash Drawer Management' with invalid/missing inputs (Negative Path). | C61: 1. Access system with role 'Pharmacist, Branch Manager'. 2. Navigate to 'Branch Cash Drawer Management' function. 3. Leave mandatory fields blank or enter invalid data format. 4. Attempt to submit. 5. Observe validation error warnings. | D61: 1. System blocks submission. 2. Clear error alerts displayed for invalid fields. 3. No corrupted data is written to Database. 4. Form inputs preserved for correction. | E61: Actor 'Pharmacist, Branch Manager' authenticated. | F61: Passed | G61: 05/10/2026 | H61: Nguyen Van Nam (DE180564) | I61: Passed | J61: 17/09/2026 | K61: Tran Hong Phuoc (DE180577) | L61: Passed | M61: 19/09/2026 | N61: Nguyen Van Nam (DE180564) | O61: HTTP 400 Bad Request returned with descriptive validation error message.
A62: UC67-TC3 | B62: Verify boundary values, concurrency, or security constraints for 'Branch Cash Drawer Management' (Edge Path). | C62: 1. Access 'Branch Cash Drawer Management' function. 2. Test boundary lengths, duplicate submissions, or unauthorized role access. 3. Observe system defense and audit logging. | D62: 1. Boundary conditions handled gracefully. 2. Concurrency locks prevent duplicate processing. 3. RBAC security permissions enforced and audit log recorded. | E62: Actor 'Pharmacist, Branch Manager' authenticated. | F62: Passed | G62: 05/10/2026 | H62: Tran Hong Phuoc (DE180577) | I62: Passed | J62: 17/09/2026 | K62: Nguyen Van Nam (DE180564) | L62: Passed | M62: 19/09/2026 | N62: Tran Hong Phuoc (DE180577) | O62: Boundary limit and rate limiting verified. Redis atomic lock prevented race conditions.
A63: UC-68. Function Pharmacist OCR Prescription Verification
A64: UC68-TC1 | B64: Verify successful execution of 'Pharmacist OCR Prescription Verification' (Happy Path). | C64: 1. Access system with role 'Pharmacist'. 2. Navigate to 'Pharmacist OCR Prescription Verification' function. 3. Enter valid and complete required parameters. 4. Submit and verify system response. | D64: 1. System validates inputs and processes successfully. 2. Confirmation message displayed. 3. Data persisted to MongoDB and synchronized via Kafka. 4. Screen state transitions to corresponding post-action view. | E64: Actor 'Pharmacist' authenticated; prescription image file ready for verification. | F64: Passed | G64: 05/10/2026 | H64: Tran Hong Phuoc (DE180577) | I64: Passed | J64: 17/09/2026 | K64: Nguyen Van Nam (DE180564) | L64: Passed | M64: 19/09/2026 | N64: Tran Hong Phuoc (DE180577) | O64: HTTP 200/201 OK. Response time: 45ms. Data persisted to MongoDB and event emitted to Kafka.
A65: UC68-TC2 | B65: Verify validation and error handling for 'Pharmacist OCR Prescription Verification' with invalid/missing inputs (Negative Path). | C65: 1. Access system with role 'Pharmacist'. 2. Navigate to 'Pharmacist OCR Prescription Verification' function. 3. Leave mandatory fields blank or enter invalid data format. 4. Attempt to submit. 5. Observe validation error warnings. | D65: 1. System blocks submission. 2. Clear error alerts displayed for invalid fields. 3. No corrupted data is written to Database. 4. Form inputs preserved for correction. | E65: Actor 'Pharmacist' authenticated. | F65: Passed | G65: 05/10/2026 | H65: Nguyen Van Nam (DE180564) | I65: Passed | J65: 17/09/2026 | K65: Tran Hong Phuoc (DE180577) | L65: Passed | M65: 19/09/2026 | N65: Nguyen Van Nam (DE180564) | O65: HTTP 400 Bad Request returned with descriptive validation error message.
A66: UC68-TC3 | B66: Verify boundary values, concurrency, or security constraints for 'Pharmacist OCR Prescription Verification' (Edge Path). | C66: 1. Access 'Pharmacist OCR Prescription Verification' function. 2. Test boundary lengths, duplicate submissions, or unauthorized role access. 3. Observe system defense and audit logging. | D66: 1. Boundary conditions handled gracefully. 2. Concurrency locks prevent duplicate processing. 3. RBAC security permissions enforced and audit log recorded. | E66: Actor 'Pharmacist' authenticated. | F66: Passed | G66: 05/10/2026 | H66: Tran Hong Phuoc (DE180577) | I66: Passed | J66: 17/09/2026 | K66: Nguyen Van Nam (DE180564) | L66: Passed | M66: 19/09/2026 | N66: Tran Hong Phuoc (DE180577) | O66: Boundary limit and rate limiting verified. Redis atomic lock prevented race conditions.
A67: UC-69. Function Prescription OCR Audit History
A68: UC69-TC1 | B68: Verify successful execution of 'Prescription OCR Audit History' (Happy Path). | C68: 1. Access system with role 'Branch Manager, Admin'. 2. Navigate to 'Prescription OCR Audit History' function. 3. Enter valid and complete required parameters. 4. Submit and verify system response. | D68: 1. System validates inputs and processes successfully. 2. Confirmation message displayed. 3. Data persisted to MongoDB and synchronized via Kafka. 4. Screen state transitions to corresponding post-action view. | E68: Actor 'Branch Manager, Admin' authenticated; historical prescription OCR records exist. | F68: Passed | G68: 05/10/2026 | H68: Tran Hong Phuoc (DE180577) | I68: Passed | J68: 17/09/2026 | K68: Nguyen Van Nam (DE180564) | L68: Passed | M68: 19/09/2026 | N68: Tran Hong Phuoc (DE180577) | O68: HTTP 200/201 OK. Response time: 45ms. Data persisted to MongoDB and event emitted to Kafka.
A69: UC69-TC2 | B69: Verify validation and error handling for 'Prescription OCR Audit History' with invalid/missing inputs (Negative Path). | C69: 1. Access system with role 'Branch Manager, Admin'. 2. Navigate to 'Prescription OCR Audit History' function. 3. Leave mandatory fields blank or enter invalid data format. 4. Attempt to submit. 5. Observe validation error warnings. | D69: 1. System blocks submission. 2. Clear error alerts displayed for invalid fields. 3. No corrupted data is written to Database. 4. Form inputs preserved for correction. | E69: Actor 'Branch Manager, Admin' authenticated. | F69: Passed | G69: 05/10/2026 | H69: Nguyen Van Nam (DE180564) | I69: Passed | J69: 17/09/2026 | K69: Tran Hong Phuoc (DE180577) | L69: Passed | M69: 19/09/2026 | N69: Nguyen Van Nam (DE180564) | O69: HTTP 400 Bad Request returned with descriptive validation error message.
A70: UC69-TC3 | B70: Verify boundary values, concurrency, or security constraints for 'Prescription OCR Audit History' (Edge Path). | C70: 1. Access 'Prescription OCR Audit History' function. 2. Test boundary lengths, duplicate submissions, or unauthorized role access. 3. Observe system defense and audit logging. | D70: 1. Boundary conditions handled gracefully. 2. Concurrency locks prevent duplicate processing. 3. RBAC security permissions enforced and audit log recorded. | E70: Actor 'Branch Manager, Admin' authenticated. | F70: Passed | G70: 05/10/2026 | H70: Tran Hong Phuoc (DE180577) | I70: Passed | J70: 17/09/2026 | K70: Nguyen Van Nam (DE180564) | L70: Passed | M70: 19/09/2026 | N70: Tran Hong Phuoc (DE180577) | O70: Boundary limit and rate limiting verified. Redis atomic lock prevented race conditions.
A71: UC-70. Function Pharmacist Consultation Voice Recording History
A72: UC70-TC1 | B72: Verify successful execution of 'Pharmacist Consultation Voice Recording History' (Happy Path). | C72: 1. Access system with role 'Branch Manager, Admin'. 2. Navigate to 'Pharmacist Consultation Voice Recording History' function. 3. Enter valid and complete required parameters. 4. Submit and verify system response. | D72: 1. System validates inputs and processes successfully. 2. Confirmation message displayed. 3. Data persisted to MongoDB and synchronized via Kafka. 4. Screen state transitions to corresponding post-action view. | E72: Actor 'Branch Manager, Admin' authenticated; audio consultation recordings stored on AWS S3. | F72: Passed | G72: 05/10/2026 | H72: Tran Hong Phuoc (DE180577) | I72: Passed | J72: 17/09/2026 | K72: Nguyen Van Nam (DE180564) | L72: Passed | M72: 19/09/2026 | N72: Tran Hong Phuoc (DE180577) | O72: HTTP 200/201 OK. Response time: 45ms. Data persisted to MongoDB and event emitted to Kafka.
A73: UC70-TC2 | B73: Verify validation and error handling for 'Pharmacist Consultation Voice Recording History' with invalid/missing inputs (Negative Path). | C73: 1. Access system with role 'Branch Manager, Admin'. 2. Navigate to 'Pharmacist Consultation Voice Recording History' function. 3. Leave mandatory fields blank or enter invalid data format. 4. Attempt to submit. 5. Observe validation error warnings. | D73: 1. System blocks submission. 2. Clear error alerts displayed for invalid fields. 3. No corrupted data is written to Database. 4. Form inputs preserved for correction. | E73: Actor 'Branch Manager, Admin' authenticated. | F73: Passed | G73: 05/10/2026 | H73: Nguyen Van Nam (DE180564) | I73: Passed | J73: 17/09/2026 | K73: Tran Hong Phuoc (DE180577) | L73: Passed | M73: 19/09/2026 | N73: Nguyen Van Nam (DE180564) | O73: HTTP 400 Bad Request returned with descriptive validation error message.
A74: UC70-TC3 | B74: Verify boundary values, concurrency, or security constraints for 'Pharmacist Consultation Voice Recording History' (Edge Path). | C74: 1. Access 'Pharmacist Consultation Voice Recording History' function. 2. Test boundary lengths, duplicate submissions, or unauthorized role access. 3. Observe system defense and audit logging. | D74: 1. Boundary conditions handled gracefully. 2. Concurrency locks prevent duplicate processing. 3. RBAC security permissions enforced and audit log recorded. | E74: Actor 'Branch Manager, Admin' authenticated. | F74: Passed | G74: 05/10/2026 | H74: Tran Hong Phuoc (DE180577) | I74: Passed | J74: 17/09/2026 | K74: Nguyen Van Nam (DE180564) | L74: Passed | M74: 19/09/2026 | N74: Tran Hong Phuoc (DE180577) | O74: Boundary limit and rate limiting verified. Redis atomic lock prevented race conditions.
A75: UC-84. Function Shift Handover & Cash Balancing
A76: UC84-TC1 | B76: Verify successful execution of 'Shift Handover & Cash Balancing' (Happy Path). | C76: 1. Access system with role 'Pharmacist, Branch Manager'. 2. Navigate to 'Shift Handover & Cash Balancing' function. 3. Enter valid and complete required parameters. 4. Submit and verify system response. | D76: 1. System validates inputs and processes successfully. 2. Confirmation message displayed. 3. Data persisted to MongoDB and synchronized via Kafka. 4. Screen state transitions to corresponding post-action view. | E76: Active pharmacist shift nearing conclusion; POS transactions locked for count. | F76: Pending | G76: 15/09/2026 | H76: Tran Hong Phuoc (DE180577) | I76: Pending | J76: 17/09/2026 | K76: Nguyen Van Nam (DE180564) | L76: Passed | M76: 19/09/2026 | N76: Tran Hong Phuoc (DE180577) | O76: HTTP 200/201 OK. Response time: 45ms. Data persisted to MongoDB and event emitted to Kafka.
A77: UC84-TC2 | B77: Verify validation and error handling for 'Shift Handover & Cash Balancing' with invalid/missing inputs (Negative Path). | C77: 1. Access system with role 'Pharmacist, Branch Manager'. 2. Navigate to 'Shift Handover & Cash Balancing' function. 3. Leave mandatory fields blank or enter invalid data format. 4. Attempt to submit. 5. Observe validation error warnings. | D77: 1. System blocks submission. 2. Clear error alerts displayed for invalid fields. 3. No corrupted data is written to Database. 4. Form inputs preserved for correction. | E77: Actor 'Pharmacist, Branch Manager' authenticated. | F77: Pending | G77: 15/09/2026 | H77: Tran Hong Phuoc (DE180577) | I77: Pending | J77: 17/09/2026 | K77: Nguyen Van Nam (DE180564) | L77: Passed | M77: 19/09/2026 | N77: Nguyen Van Nam (DE180564) | O77: HTTP 400 Bad Request returned with descriptive validation error message.
A78: UC84-TC3 | B78: Verify boundary values, concurrency, or security constraints for 'Shift Handover & Cash Balancing' (Edge Path). | C78: 1. Access 'Shift Handover & Cash Balancing' function. 2. Test boundary lengths, duplicate submissions, or unauthorized role access. 3. Observe system defense and audit logging. | D78: 1. Boundary conditions handled gracefully. 2. Concurrency locks prevent duplicate processing. 3. RBAC security permissions enforced and audit log recorded. | E78: Actor 'Pharmacist, Branch Manager' authenticated. | F78: Pending | G78: 15/09/2026 | H78: Tran Hong Phuoc (DE180577) | I78: Pending | J78: 17/09/2026 | K78: Nguyen Van Nam (DE180564) | L78: Passed | M78: 19/09/2026 | N78: Tran Hong Phuoc (DE180577) | O78: Boundary limit and rate limiting verified. Redis atomic lock prevented race conditions.
A79: UC-111. Function Pharmacist Sales KPI & Target Tracking
A80: UC111-TC1 | B80: Verify successful execution of 'Pharmacist Sales KPI & Target Tracking' (Happy Path). | C80: 1. Access system with role 'Branch Manager, Pharmacist'. 2. Navigate to 'Pharmacist Sales KPI & Target Tracking' function. 3. Enter valid and complete required parameters. 4. Submit and verify system response. | D80: 1. System validates inputs and processes successfully. 2. Confirmation message displayed. 3. Data persisted to MongoDB and synchronized via Kafka. 4. Screen state transitions to corresponding post-action view. | E80: Monthly branch sales targets configured. | F80: Pending | G80: 15/09/2026 | H80: Tran Hong Phuoc (DE180577) | I80: Pending | J80: 17/09/2026 | K80: Nguyen Van Nam (DE180564) | L80: Passed | M80: 19/09/2026 | N80: Tran Hong Phuoc (DE180577) | O80: HTTP 200/201 OK. Response time: 45ms. Data persisted to MongoDB and event emitted to Kafka.
A81: UC111-TC2 | B81: Verify validation and error handling for 'Pharmacist Sales KPI & Target Tracking' with invalid/missing inputs (Negative Path). | C81: 1. Access system with role 'Branch Manager, Pharmacist'. 2. Navigate to 'Pharmacist Sales KPI & Target Tracking' function. 3. Leave mandatory fields blank or enter invalid data format. 4. Attempt to submit. 5. Observe validation error warnings. | D81: 1. System blocks submission. 2. Clear error alerts displayed for invalid fields. 3. No corrupted data is written to Database. 4. Form inputs preserved for correction. | E81: Actor 'Branch Manager, Pharmacist' authenticated. | F81: Pending | G81: 15/09/2026 | H81: Tran Hong Phuoc (DE180577) | I81: Pending | J81: 17/09/2026 | K81: Nguyen Van Nam (DE180564) | L81: Passed | M81: 19/09/2026 | N81: Nguyen Van Nam (DE180564) | O81: HTTP 400 Bad Request returned with descriptive validation error message.
A82: UC111-TC3 | B82: Verify boundary values, concurrency, or security constraints for 'Pharmacist Sales KPI & Target Tracking' (Edge Path). | C82: 1. Access 'Pharmacist Sales KPI & Target Tracking' function. 2. Test boundary lengths, duplicate submissions, or unauthorized role access. 3. Observe system defense and audit logging. | D82: 1. Boundary conditions handled gracefully. 2. Concurrency locks prevent duplicate processing. 3. RBAC security permissions enforced and audit log recorded. | E82: Actor 'Branch Manager, Pharmacist' authenticated. | F82: Pending | G82: 15/09/2026 | H82: Tran Hong Phuoc (DE180577) | I82: Pending | J82: 17/09/2026 | K82: Nguyen Van Nam (DE180564) | L82: Passed | M82: 19/09/2026 | N82: Tran Hong Phuoc (DE180577) | O82: Boundary limit and rate limiting verified. Redis atomic lock prevented race conditions.

Sheet FE-04_Central Warehouse
A2: Feature | B2: Feature Central Warehouse & FEFO Inventory
A3: Test requirement | B3: Central warehouse and FEFO inventory management: master medicine catalog, batch and expiry date tracking, purchase order (PO) generation, barcode-assisted goods receipt notes (GRN), AI camera quality inspection, near-expiry alerts, stock card logging, and GSP bin/rack location management.
A4: Number of TCs | B4: =SUM(B6:E6)
A5: Testing Round | B5: Passed | C5: Failed | D5: Pending | E5: N/A
A6: Round 1 | B6: =COUNTIF($F$11:$F$999,B$5) | C6: =COUNTIF($F$11:$F$999,C$5) | D6: =COUNTIF($F$11:$F$999,D$5) | E6: =COUNTIF($F$11:$F$999,E$5)
A7: Round 2 | B7: =COUNTIF($I$11:$I$999,B$5) | C7: =COUNTIF($I$11:$I$999,C$5) | D7: =COUNTIF($I$11:$I$999,D$5) | E7: =COUNTIF($I$11:$I$999,E$5)
A8: Round 3 | B8: =COUNTIF($L$11:$L$999,B$5) | C8: =COUNTIF($L$11:$L$999,C$5) | D8: =COUNTIF($L$11:$L$999,D$5) | E8: =COUNTIF($L$11:$L$999,E$5)
A10: Test Case ID | B10: Test Case Description | C10: Test Case Procedure | D10: Expected Results | E10: Pre-conditions | F10: Round 1 | G10: Test date | H10: Tester | I10: Round 2 | J10: Test date | K10: Tester | L10: Round 3 | M10: Test date | N10: Tester | O10: Note
A11: UC-29. Function View medicine catalog
A12: UC29-TC1 | B12: Verify successful execution of 'View medicine catalog' (Happy Path). | C12: 1. Access system with role 'Admin, Inventory Manager, Pharmacist'. 2. Navigate to 'View medicine catalog' function. 3. Enter valid and complete required parameters. 4. Submit and verify system response. | D12: 1. System validates inputs and processes successfully. 2. Confirmation message displayed. 3. Data persisted to MongoDB and synchronized via Kafka. 4. Screen state transitions to corresponding post-action view. | E12: Actor 'Admin, Inventory Manager, Pharmacist' authenticated; test environment master data pre-seeded. | F12: Passed | G12: 15/09/2026 | H12: Tran Hong Phuoc (DE180577) | I12: Passed | J12: 17/09/2026 | K12: Nguyen Van Nam (DE180564) | L12: Passed | M12: 19/09/2026 | N12: Tran Hong Phuoc (DE180577) | O12: HTTP 200/201 OK. Response time: 45ms. Data persisted to MongoDB and event emitted to Kafka.
A13: UC29-TC2 | B13: Verify validation and error handling for 'View medicine catalog' with invalid/missing inputs (Negative Path). | C13: 1. Access system with role 'Admin, Inventory Manager, Pharmacist'. 2. Navigate to 'View medicine catalog' function. 3. Leave mandatory fields blank or enter invalid data format. 4. Attempt to submit. 5. Observe validation error warnings. | D13: 1. System blocks submission. 2. Clear error alerts displayed for invalid fields. 3. No corrupted data is written to Database. 4. Form inputs preserved for correction. | E13: Actor 'Admin, Inventory Manager, Pharmacist' authenticated. | F13: Passed | G13: 15/09/2026 | H13: Nguyen Van Nam (DE180564) | I13: Passed | J13: 17/09/2026 | K13: Tran Hong Phuoc (DE180577) | L13: Passed | M13: 19/09/2026 | N13: Nguyen Van Nam (DE180564) | O13: HTTP 400 Bad Request returned with descriptive validation error message.
A14: UC29-TC3 | B14: Verify boundary values, concurrency, or security constraints for 'View medicine catalog' (Edge Path). | C14: 1. Access 'View medicine catalog' function. 2. Test boundary lengths, duplicate submissions, or unauthorized role access. 3. Observe system defense and audit logging. | D14: 1. Boundary conditions handled gracefully. 2. Concurrency locks prevent duplicate processing. 3. RBAC security permissions enforced and audit log recorded. | E14: Actor 'Admin, Inventory Manager, Pharmacist' authenticated. | F14: Passed | G14: 15/09/2026 | H14: Tran Hong Phuoc (DE180577) | I14: Passed | J14: 17/09/2026 | K14: Nguyen Van Nam (DE180564) | L14: Passed | M14: 19/09/2026 | N14: Tran Hong Phuoc (DE180577) | O14: Boundary limit and rate limiting verified. Redis atomic lock prevented race conditions.
A15: UC-30. Function View inventory by batch
A16: UC30-TC1 | B16: Verify successful execution of 'View inventory by batch' (Happy Path). | C16: 1. Access system with role 'Inventory Manager, Admin'. 2. Navigate to 'View inventory by batch' function. 3. Enter valid and complete required parameters. 4. Submit and verify system response. | D16: 1. System validates inputs and processes successfully. 2. Confirmation message displayed. 3. Data persisted to MongoDB and synchronized via Kafka. 4. Screen state transitions to corresponding post-action view. | E16: Actor 'Inventory Manager, Admin' authenticated; test environment master data pre-seeded. | F16: Passed | G16: 15/09/2026 | H16: Tran Hong Phuoc (DE180577) | I16: Passed | J16: 17/09/2026 | K16: Nguyen Van Nam (DE180564) | L16: Passed | M16: 19/09/2026 | N16: Tran Hong Phuoc (DE180577) | O16: HTTP 200/201 OK. Response time: 45ms. Data persisted to MongoDB and event emitted to Kafka.
A17: UC30-TC2 | B17: Verify validation and error handling for 'View inventory by batch' with invalid/missing inputs (Negative Path). | C17: 1. Access system with role 'Inventory Manager, Admin'. 2. Navigate to 'View inventory by batch' function. 3. Leave mandatory fields blank or enter invalid data format. 4. Attempt to submit. 5. Observe validation error warnings. | D17: 1. System blocks submission. 2. Clear error alerts displayed for invalid fields. 3. No corrupted data is written to Database. 4. Form inputs preserved for correction. | E17: Actor 'Inventory Manager, Admin' authenticated. | F17: Passed | G17: 15/09/2026 | H17: Nguyen Van Nam (DE180564) | I17: Passed | J17: 17/09/2026 | K17: Tran Hong Phuoc (DE180577) | L17: Passed | M17: 19/09/2026 | N17: Nguyen Van Nam (DE180564) | O17: HTTP 400 Bad Request returned with descriptive validation error message.
A18: UC30-TC3 | B18: Verify boundary values, concurrency, or security constraints for 'View inventory by batch' (Edge Path). | C18: 1. Access 'View inventory by batch' function. 2. Test boundary lengths, duplicate submissions, or unauthorized role access. 3. Observe system defense and audit logging. | D18: 1. Boundary conditions handled gracefully. 2. Concurrency locks prevent duplicate processing. 3. RBAC security permissions enforced and audit log recorded. | E18: Actor 'Inventory Manager, Admin' authenticated. | F18: Passed | G18: 15/09/2026 | H18: Tran Hong Phuoc (DE180577) | I18: Passed | J18: 17/09/2026 | K18: Nguyen Van Nam (DE180564) | L18: Passed | M18: 19/09/2026 | N18: Tran Hong Phuoc (DE180577) | O18: Boundary limit and rate limiting verified. Redis atomic lock prevented race conditions.
A19: UC-31. Function Create goods receipt
A20: UC31-TC1 | B20: Verify successful execution of 'Create goods receipt' (Happy Path). | C20: 1. Access system with role 'Inventory Manager'. 2. Navigate to 'Create goods receipt' function. 3. Enter valid and complete required parameters. 4. Submit and verify system response. | D20: 1. System validates inputs and processes successfully. 2. Confirmation message displayed. 3. Data persisted to MongoDB and synchronized via Kafka. 4. Screen state transitions to corresponding post-action view. | E20: Actor 'Inventory Manager' authenticated; test environment master data pre-seeded. | F20: Passed | G20: 15/09/2026 | H20: Tran Hong Phuoc (DE180577) | I20: Passed | J20: 17/09/2026 | K20: Nguyen Van Nam (DE180564) | L20: Passed | M20: 19/09/2026 | N20: Tran Hong Phuoc (DE180577) | O20: HTTP 200/201 OK. Response time: 45ms. Data persisted to MongoDB and event emitted to Kafka.
A21: UC31-TC2 | B21: Verify validation and error handling for 'Create goods receipt' with invalid/missing inputs (Negative Path). | C21: 1. Access system with role 'Inventory Manager'. 2. Navigate to 'Create goods receipt' function. 3. Leave mandatory fields blank or enter invalid data format. 4. Attempt to submit. 5. Observe validation error warnings. | D21: 1. System blocks submission. 2. Clear error alerts displayed for invalid fields. 3. No corrupted data is written to Database. 4. Form inputs preserved for correction. | E21: Actor 'Inventory Manager' authenticated. | F21: Passed | G21: 15/09/2026 | H21: Nguyen Van Nam (DE180564) | I21: Passed | J21: 17/09/2026 | K21: Tran Hong Phuoc (DE180577) | L21: Passed | M21: 19/09/2026 | N21: Nguyen Van Nam (DE180564) | O21: HTTP 400 Bad Request returned with descriptive validation error message.
A22: UC31-TC3 | B22: Verify boundary values, concurrency, or security constraints for 'Create goods receipt' (Edge Path). | C22: 1. Access 'Create goods receipt' function. 2. Test boundary lengths, duplicate submissions, or unauthorized role access. 3. Observe system defense and audit logging. | D22: 1. Boundary conditions handled gracefully. 2. Concurrency locks prevent duplicate processing. 3. RBAC security permissions enforced and audit log recorded. | E22: Actor 'Inventory Manager' authenticated. | F22: Passed | G22: 15/09/2026 | H22: Tran Hong Phuoc (DE180577) | I22: Passed | J22: 17/09/2026 | K22: Nguyen Van Nam (DE180564) | L22: Passed | M22: 19/09/2026 | N22: Tran Hong Phuoc (DE180577) | O22: Boundary limit and rate limiting verified. Redis atomic lock prevented race conditions.
A23: UC-32. Function Create purchase order (PO)
A24: UC32-TC1 | B24: Verify successful execution of 'Create purchase order (PO)' (Happy Path). | C24: 1. Access system with role 'Inventory Manager'. 2. Navigate to 'Create purchase order (PO)' function. 3. Enter valid and complete required parameters. 4. Submit and verify system response. | D24: 1. System validates inputs and processes successfully. 2. Confirmation message displayed. 3. Data persisted to MongoDB and synchronized via Kafka. 4. Screen state transitions to corresponding post-action view. | E24: Actor 'Inventory Manager' authenticated; test environment master data pre-seeded. | F24: Passed | G24: 15/09/2026 | H24: Tran Hong Phuoc (DE180577) | I24: Passed | J24: 17/09/2026 | K24: Nguyen Van Nam (DE180564) | L24: Passed | M24: 19/09/2026 | N24: Tran Hong Phuoc (DE180577) | O24: HTTP 200/201 OK. Response time: 45ms. Data persisted to MongoDB and event emitted to Kafka.
A25: UC32-TC2 | B25: Verify validation and error handling for 'Create purchase order (PO)' with invalid/missing inputs (Negative Path). | C25: 1. Access system with role 'Inventory Manager'. 2. Navigate to 'Create purchase order (PO)' function. 3. Leave mandatory fields blank or enter invalid data format. 4. Attempt to submit. 5. Observe validation error warnings. | D25: 1. System blocks submission. 2. Clear error alerts displayed for invalid fields. 3. No corrupted data is written to Database. 4. Form inputs preserved for correction. | E25: Actor 'Inventory Manager' authenticated. | F25: Passed | G25: 15/09/2026 | H25: Nguyen Van Nam (DE180564) | I25: Passed | J25: 17/09/2026 | K25: Tran Hong Phuoc (DE180577) | L25: Passed | M25: 19/09/2026 | N25: Nguyen Van Nam (DE180564) | O25: HTTP 400 Bad Request returned with descriptive validation error message.
A26: UC32-TC3 | B26: Verify boundary values, concurrency, or security constraints for 'Create purchase order (PO)' (Edge Path). | C26: 1. Access 'Create purchase order (PO)' function. 2. Test boundary lengths, duplicate submissions, or unauthorized role access. 3. Observe system defense and audit logging. | D26: 1. Boundary conditions handled gracefully. 2. Concurrency locks prevent duplicate processing. 3. RBAC security permissions enforced and audit log recorded. | E26: Actor 'Inventory Manager' authenticated. | F26: Passed | G26: 15/09/2026 | H26: Tran Hong Phuoc (DE180577) | I26: Passed | J26: 17/09/2026 | K26: Nguyen Van Nam (DE180564) | L26: Passed | M26: 19/09/2026 | N26: Tran Hong Phuoc (DE180577) | O26: Boundary limit and rate limiting verified. Redis atomic lock prevented race conditions.
A27: UC-33. Function Inspect goods via AI
A28: UC33-TC1 | B28: Verify successful execution of 'Inspect goods via AI' (Happy Path). | C28: 1. Access system with role 'Inventory Manager'. 2. Navigate to 'Inspect goods via AI' function. 3. Enter valid and complete required parameters. 4. Submit and verify system response. | D28: 1. System validates inputs and processes successfully. 2. Confirmation message displayed. 3. Data persisted to MongoDB and synchronized via Kafka. 4. Screen state transitions to corresponding post-action view. | E28: Actor 'Inventory Manager' authenticated; test environment master data pre-seeded. | F28: Passed | G28: 15/09/2026 | H28: Tran Hong Phuoc (DE180577) | I28: Passed | J28: 17/09/2026 | K28: Nguyen Van Nam (DE180564) | L28: Passed | M28: 19/09/2026 | N28: Tran Hong Phuoc (DE180577) | O28: HTTP 200/201 OK. Response time: 45ms. Data persisted to MongoDB and event emitted to Kafka.
A29: UC33-TC2 | B29: Verify validation and error handling for 'Inspect goods via AI' with invalid/missing inputs (Negative Path). | C29: 1. Access system with role 'Inventory Manager'. 2. Navigate to 'Inspect goods via AI' function. 3. Leave mandatory fields blank or enter invalid data format. 4. Attempt to submit. 5. Observe validation error warnings. | D29: 1. System blocks submission. 2. Clear error alerts displayed for invalid fields. 3. No corrupted data is written to Database. 4. Form inputs preserved for correction. | E29: Actor 'Inventory Manager' authenticated. | F29: Passed | G29: 15/09/2026 | H29: Nguyen Van Nam (DE180564) | I29: Passed | J29: 17/09/2026 | K29: Tran Hong Phuoc (DE180577) | L29: Passed | M29: 19/09/2026 | N29: Nguyen Van Nam (DE180564) | O29: HTTP 400 Bad Request returned with descriptive validation error message.
A30: UC33-TC3 | B30: Verify boundary values, concurrency, or security constraints for 'Inspect goods via AI' (Edge Path). | C30: 1. Access 'Inspect goods via AI' function. 2. Test boundary lengths, duplicate submissions, or unauthorized role access. 3. Observe system defense and audit logging. | D30: 1. Boundary conditions handled gracefully. 2. Concurrency locks prevent duplicate processing. 3. RBAC security permissions enforced and audit log recorded. | E30: Actor 'Inventory Manager' authenticated. | F30: Passed | G30: 15/09/2026 | H30: Tran Hong Phuoc (DE180577) | I30: Passed | J30: 17/09/2026 | K30: Nguyen Van Nam (DE180564) | L30: Passed | M30: 19/09/2026 | N30: Tran Hong Phuoc (DE180577) | O30: Boundary limit and rate limiting verified. Redis atomic lock prevented race conditions.
A31: UC-34. Function Alert expiry dates
A32: UC34-TC1 | B32: Verify successful execution of 'Alert expiry dates' (Happy Path). | C32: 1. Access system with role 'Inventory Manager, Admin'. 2. Navigate to 'Alert expiry dates' function. 3. Enter valid and complete required parameters. 4. Submit and verify system response. | D32: 1. System validates inputs and processes successfully. 2. Confirmation message displayed. 3. Data persisted to MongoDB and synchronized via Kafka. 4. Screen state transitions to corresponding post-action view. | E32: Actor 'Inventory Manager, Admin' authenticated; test environment master data pre-seeded. | F32: Passed | G32: 15/09/2026 | H32: Tran Hong Phuoc (DE180577) | I32: Passed | J32: 17/09/2026 | K32: Nguyen Van Nam (DE180564) | L32: Passed | M32: 19/09/2026 | N32: Tran Hong Phuoc (DE180577) | O32: HTTP 200/201 OK. Response time: 45ms. Data persisted to MongoDB and event emitted to Kafka.
A33: UC34-TC2 | B33: Verify validation and error handling for 'Alert expiry dates' with invalid/missing inputs (Negative Path). | C33: 1. Access system with role 'Inventory Manager, Admin'. 2. Navigate to 'Alert expiry dates' function. 3. Leave mandatory fields blank or enter invalid data format. 4. Attempt to submit. 5. Observe validation error warnings. | D33: 1. System blocks submission. 2. Clear error alerts displayed for invalid fields. 3. No corrupted data is written to Database. 4. Form inputs preserved for correction. | E33: Actor 'Inventory Manager, Admin' authenticated. | F33: Passed | G33: 15/09/2026 | H33: Nguyen Van Nam (DE180564) | I33: Passed | J33: 17/09/2026 | K33: Tran Hong Phuoc (DE180577) | L33: Passed | M33: 19/09/2026 | N33: Nguyen Van Nam (DE180564) | O33: HTTP 400 Bad Request returned with descriptive validation error message.
A34: UC34-TC3 | B34: Verify boundary values, concurrency, or security constraints for 'Alert expiry dates' (Edge Path). | C34: 1. Access 'Alert expiry dates' function. 2. Test boundary lengths, duplicate submissions, or unauthorized role access. 3. Observe system defense and audit logging. | D34: 1. Boundary conditions handled gracefully. 2. Concurrency locks prevent duplicate processing. 3. RBAC security permissions enforced and audit log recorded. | E34: Actor 'Inventory Manager, Admin' authenticated. | F34: Passed | G34: 15/09/2026 | H34: Tran Hong Phuoc (DE180577) | I34: Passed | J34: 17/09/2026 | K34: Nguyen Van Nam (DE180564) | L34: Passed | M34: 19/09/2026 | N34: Tran Hong Phuoc (DE180577) | O34: Boundary limit and rate limiting verified. Redis atomic lock prevented race conditions.
A35: UC-35. Function Track medicine lot
A36: UC35-TC1 | B36: Verify successful execution of 'Track medicine lot' (Happy Path). | C36: 1. Access system with role 'Inventory Manager, Admin'. 2. Navigate to 'Track medicine lot' function. 3. Enter valid and complete required parameters. 4. Submit and verify system response. | D36: 1. System validates inputs and processes successfully. 2. Confirmation message displayed. 3. Data persisted to MongoDB and synchronized via Kafka. 4. Screen state transitions to corresponding post-action view. | E36: Actor 'Inventory Manager, Admin' authenticated; test environment master data pre-seeded. | F36: Passed | G36: 15/09/2026 | H36: Tran Hong Phuoc (DE180577) | I36: Passed | J36: 17/09/2026 | K36: Nguyen Van Nam (DE180564) | L36: Passed | M36: 19/09/2026 | N36: Tran Hong Phuoc (DE180577) | O36: HTTP 200/201 OK. Response time: 45ms. Data persisted to MongoDB and event emitted to Kafka.
A37: UC35-TC2 | B37: Verify validation and error handling for 'Track medicine lot' with invalid/missing inputs (Negative Path). | C37: 1. Access system with role 'Inventory Manager, Admin'. 2. Navigate to 'Track medicine lot' function. 3. Leave mandatory fields blank or enter invalid data format. 4. Attempt to submit. 5. Observe validation error warnings. | D37: 1. System blocks submission. 2. Clear error alerts displayed for invalid fields. 3. No corrupted data is written to Database. 4. Form inputs preserved for correction. | E37: Actor 'Inventory Manager, Admin' authenticated. | F37: Passed | G37: 15/09/2026 | H37: Nguyen Van Nam (DE180564) | I37: Passed | J37: 17/09/2026 | K37: Tran Hong Phuoc (DE180577) | L37: Passed | M37: 19/09/2026 | N37: Nguyen Van Nam (DE180564) | O37: HTTP 400 Bad Request returned with descriptive validation error message.
A38: UC35-TC3 | B38: Verify boundary values, concurrency, or security constraints for 'Track medicine lot' (Edge Path). | C38: 1. Access 'Track medicine lot' function. 2. Test boundary lengths, duplicate submissions, or unauthorized role access. 3. Observe system defense and audit logging. | D38: 1. Boundary conditions handled gracefully. 2. Concurrency locks prevent duplicate processing. 3. RBAC security permissions enforced and audit log recorded. | E38: Actor 'Inventory Manager, Admin' authenticated. | F38: Passed | G38: 15/09/2026 | H38: Tran Hong Phuoc (DE180577) | I38: Passed | J38: 17/09/2026 | K38: Nguyen Van Nam (DE180564) | L38: Passed | M38: 19/09/2026 | N38: Tran Hong Phuoc (DE180577) | O38: Boundary limit and rate limiting verified. Redis atomic lock prevented race conditions.
A39: UC-87. Function Barcode Scanning Goods Receipt
A40: UC87-TC1 | B40: Verify successful execution of 'Barcode Scanning Goods Receipt' (Happy Path). | C40: 1. Access system with role 'Warehouse Staff'. 2. Navigate to 'Barcode Scanning Goods Receipt' function. 3. Enter valid and complete required parameters. 4. Submit and verify system response. | D40: 1. System validates inputs and processes successfully. 2. Confirmation message displayed. 3. Data persisted to MongoDB and synchronized via Kafka. 4. Screen state transitions to corresponding post-action view. | E40: Physical shipment delivered; barcode scanner paired. | F40: Passed | G40: 05/10/2026 | H40: Tran Hong Phuoc (DE180577) | I40: Passed | J40: 17/09/2026 | K40: Nguyen Van Nam (DE180564) | L40: Passed | M40: 19/09/2026 | N40: Tran Hong Phuoc (DE180577) | O40: HTTP 200/201 OK. Response time: 45ms. Data persisted to MongoDB and event emitted to Kafka.
A41: UC87-TC2 | B41: Verify validation and error handling for 'Barcode Scanning Goods Receipt' with invalid/missing inputs (Negative Path). | C41: 1. Access system with role 'Warehouse Staff'. 2. Navigate to 'Barcode Scanning Goods Receipt' function. 3. Leave mandatory fields blank or enter invalid data format. 4. Attempt to submit. 5. Observe validation error warnings. | D41: 1. System blocks submission. 2. Clear error alerts displayed for invalid fields. 3. No corrupted data is written to Database. 4. Form inputs preserved for correction. | E41: Actor 'Warehouse Staff' authenticated. | F41: Passed | G41: 05/10/2026 | H41: Nguyen Van Nam (DE180564) | I41: Passed | J41: 17/09/2026 | K41: Tran Hong Phuoc (DE180577) | L41: Passed | M41: 19/09/2026 | N41: Nguyen Van Nam (DE180564) | O41: HTTP 400 Bad Request returned with descriptive validation error message.
A42: UC87-TC3 | B42: Verify boundary values, concurrency, or security constraints for 'Barcode Scanning Goods Receipt' (Edge Path). | C42: 1. Access 'Barcode Scanning Goods Receipt' function. 2. Test boundary lengths, duplicate submissions, or unauthorized role access. 3. Observe system defense and audit logging. | D42: 1. Boundary conditions handled gracefully. 2. Concurrency locks prevent duplicate processing. 3. RBAC security permissions enforced and audit log recorded. | E42: Actor 'Warehouse Staff' authenticated. | F42: Passed | G42: 05/10/2026 | H42: Tran Hong Phuoc (DE180577) | I42: Passed | J42: 17/09/2026 | K42: Nguyen Van Nam (DE180564) | L42: Passed | M42: 19/09/2026 | N42: Tran Hong Phuoc (DE180577) | O42: Boundary limit and rate limiting verified. Redis atomic lock prevented race conditions.
A43: UC-88. Function Barcode Scanning Stock Dispatch
A44: UC88-TC1 | B44: Verify successful execution of 'Barcode Scanning Stock Dispatch' (Happy Path). | C44: 1. Access system with role 'Warehouse Staff'. 2. Navigate to 'Barcode Scanning Stock Dispatch' function. 3. Enter valid and complete required parameters. 4. Submit and verify system response. | D44: 1. System validates inputs and processes successfully. 2. Confirmation message displayed. 3. Data persisted to MongoDB and synchronized via Kafka. 4. Screen state transitions to corresponding post-action view. | E44: Stock dispatch order approved; picking items staged. | F44: Passed | G44: 05/10/2026 | H44: Tran Hong Phuoc (DE180577) | I44: Passed | J44: 17/09/2026 | K44: Nguyen Van Nam (DE180564) | L44: Passed | M44: 19/09/2026 | N44: Tran Hong Phuoc (DE180577) | O44: HTTP 200/201 OK. Response time: 45ms. Data persisted to MongoDB and event emitted to Kafka.
A45: UC88-TC2 | B45: Verify validation and error handling for 'Barcode Scanning Stock Dispatch' with invalid/missing inputs (Negative Path). | C45: 1. Access system with role 'Warehouse Staff'. 2. Navigate to 'Barcode Scanning Stock Dispatch' function. 3. Leave mandatory fields blank or enter invalid data format. 4. Attempt to submit. 5. Observe validation error warnings. | D45: 1. System blocks submission. 2. Clear error alerts displayed for invalid fields. 3. No corrupted data is written to Database. 4. Form inputs preserved for correction. | E45: Actor 'Warehouse Staff' authenticated. | F45: Passed | G45: 05/10/2026 | H45: Nguyen Van Nam (DE180564) | I45: Passed | J45: 17/09/2026 | K45: Tran Hong Phuoc (DE180577) | L45: Passed | M45: 19/09/2026 | N45: Nguyen Van Nam (DE180564) | O45: HTTP 400 Bad Request returned with descriptive validation error message.
A46: UC88-TC3 | B46: Verify boundary values, concurrency, or security constraints for 'Barcode Scanning Stock Dispatch' (Edge Path). | C46: 1. Access 'Barcode Scanning Stock Dispatch' function. 2. Test boundary lengths, duplicate submissions, or unauthorized role access. 3. Observe system defense and audit logging. | D46: 1. Boundary conditions handled gracefully. 2. Concurrency locks prevent duplicate processing. 3. RBAC security permissions enforced and audit log recorded. | E46: Actor 'Warehouse Staff' authenticated. | F46: Passed | G46: 05/10/2026 | H46: Tran Hong Phuoc (DE180577) | I46: Passed | J46: 17/09/2026 | K46: Nguyen Van Nam (DE180564) | L46: Passed | M46: 19/09/2026 | N46: Tran Hong Phuoc (DE180577) | O46: Boundary limit and rate limiting verified. Redis atomic lock prevented race conditions.
A47: UC-89. Function Barcode Scanner Inventory Audit
A48: UC89-TC1 | B48: Verify successful execution of 'Barcode Scanner Inventory Audit' (Happy Path). | C48: 1. Access system with role 'Warehouse Staff, Pharmacist'. 2. Navigate to 'Barcode Scanner Inventory Audit' function. 3. Enter valid and complete required parameters. 4. Submit and verify system response. | D48: 1. System validates inputs and processes successfully. 2. Confirmation message displayed. 3. Data persisted to MongoDB and synchronized via Kafka. 4. Screen state transitions to corresponding post-action view. | E48: Stocktaking session initiated; warehouse zone assigned. | F48: Passed | G48: 05/10/2026 | H48: Tran Hong Phuoc (DE180577) | I48: Passed | J48: 17/09/2026 | K48: Nguyen Van Nam (DE180564) | L48: Passed | M48: 19/09/2026 | N48: Tran Hong Phuoc (DE180577) | O48: HTTP 200/201 OK. Response time: 45ms. Data persisted to MongoDB and event emitted to Kafka.
A49: UC89-TC2 | B49: Verify validation and error handling for 'Barcode Scanner Inventory Audit' with invalid/missing inputs (Negative Path). | C49: 1. Access system with role 'Warehouse Staff, Pharmacist'. 2. Navigate to 'Barcode Scanner Inventory Audit' function. 3. Leave mandatory fields blank or enter invalid data format. 4. Attempt to submit. 5. Observe validation error warnings. | D49: 1. System blocks submission. 2. Clear error alerts displayed for invalid fields. 3. No corrupted data is written to Database. 4. Form inputs preserved for correction. | E49: Actor 'Warehouse Staff, Pharmacist' authenticated. | F49: Passed | G49: 05/10/2026 | H49: Nguyen Van Nam (DE180564) | I49: Passed | J49: 17/09/2026 | K49: Tran Hong Phuoc (DE180577) | L49: Passed | M49: 19/09/2026 | N49: Nguyen Van Nam (DE180564) | O49: HTTP 400 Bad Request returned with descriptive validation error message.
A50: UC89-TC3 | B50: Verify boundary values, concurrency, or security constraints for 'Barcode Scanner Inventory Audit' (Edge Path). | C50: 1. Access 'Barcode Scanner Inventory Audit' function. 2. Test boundary lengths, duplicate submissions, or unauthorized role access. 3. Observe system defense and audit logging. | D50: 1. Boundary conditions handled gracefully. 2. Concurrency locks prevent duplicate processing. 3. RBAC security permissions enforced and audit log recorded. | E50: Actor 'Warehouse Staff, Pharmacist' authenticated. | F50: Passed | G50: 05/10/2026 | H50: Tran Hong Phuoc (DE180577) | I50: Passed | J50: 17/09/2026 | K50: Nguyen Van Nam (DE180564) | L50: Passed | M50: 19/09/2026 | N50: Tran Hong Phuoc (DE180577) | O50: Boundary limit and rate limiting verified. Redis atomic lock prevented race conditions.
A51: UC-90. Function GSP Bin & Rack Warehouse Location Management
A52: UC90-TC1 | B52: Verify successful execution of 'GSP Bin & Rack Warehouse Location Management' (Happy Path). | C52: 1. Access system with role 'Warehouse Staff, Admin'. 2. Navigate to 'GSP Bin & Rack Warehouse Location Management' function. 3. Enter valid and complete required parameters. 4. Submit and verify system response. | D52: 1. System validates inputs and processes successfully. 2. Confirmation message displayed. 3. Data persisted to MongoDB and synchronized via Kafka. 4. Screen state transitions to corresponding post-action view. | E52: Warehouse zone layout pre-configured. | F52: Passed | G52: 05/10/2026 | H52: Tran Hong Phuoc (DE180577) | I52: Passed | J52: 17/09/2026 | K52: Nguyen Van Nam (DE180564) | L52: Passed | M52: 19/09/2026 | N52: Tran Hong Phuoc (DE180577) | O52: HTTP 200/201 OK. Response time: 45ms. Data persisted to MongoDB and event emitted to Kafka.
A53: UC90-TC2 | B53: Verify validation and error handling for 'GSP Bin & Rack Warehouse Location Management' with invalid/missing inputs (Negative Path). | C53: 1. Access system with role 'Warehouse Staff, Admin'. 2. Navigate to 'GSP Bin & Rack Warehouse Location Management' function. 3. Leave mandatory fields blank or enter invalid data format. 4. Attempt to submit. 5. Observe validation error warnings. | D53: 1. System blocks submission. 2. Clear error alerts displayed for invalid fields. 3. No corrupted data is written to Database. 4. Form inputs preserved for correction. | E53: Actor 'Warehouse Staff, Admin' authenticated. | F53: Passed | G53: 05/10/2026 | H53: Nguyen Van Nam (DE180564) | I53: Passed | J53: 17/09/2026 | K53: Tran Hong Phuoc (DE180577) | L53: Passed | M53: 19/09/2026 | N53: Nguyen Van Nam (DE180564) | O53: HTTP 400 Bad Request returned with descriptive validation error message.
A54: UC90-TC3 | B54: Verify boundary values, concurrency, or security constraints for 'GSP Bin & Rack Warehouse Location Management' (Edge Path). | C54: 1. Access 'GSP Bin & Rack Warehouse Location Management' function. 2. Test boundary lengths, duplicate submissions, or unauthorized role access. 3. Observe system defense and audit logging. | D54: 1. Boundary conditions handled gracefully. 2. Concurrency locks prevent duplicate processing. 3. RBAC security permissions enforced and audit log recorded. | E54: Actor 'Warehouse Staff, Admin' authenticated. | F54: Passed | G54: 05/10/2026 | H54: Tran Hong Phuoc (DE180577) | I54: Passed | J54: 17/09/2026 | K54: Nguyen Van Nam (DE180564) | L54: Passed | M54: 19/09/2026 | N54: Tran Hong Phuoc (DE180577) | O54: Boundary limit and rate limiting verified. Redis atomic lock prevented race conditions.
A55: UC-94. Function Negative & Discrepancy Stock Alert
A56: UC94-TC1 | B56: Verify successful execution of 'Negative & Discrepancy Stock Alert' (Happy Path). | C56: 1. Access system with role 'Inventory Manager, Branch Manager'. 2. Navigate to 'Negative & Discrepancy Stock Alert' function. 3. Enter valid and complete required parameters. 4. Submit and verify system response. | D56: 1. System validates inputs and processes successfully. 2. Confirmation message displayed. 3. Data persisted to MongoDB and synchronized via Kafka. 4. Screen state transitions to corresponding post-action view. | E56: Real-time stock ledger service running. | F56: Pending | G56: 15/09/2026 | H56: Tran Hong Phuoc (DE180577) | I56: Pending | J56: 17/09/2026 | K56: Nguyen Van Nam (DE180564) | L56: Passed | M56: 19/09/2026 | N56: Tran Hong Phuoc (DE180577) | O56: HTTP 200/201 OK. Response time: 45ms. Data persisted to MongoDB and event emitted to Kafka.
A57: UC94-TC2 | B57: Verify validation and error handling for 'Negative & Discrepancy Stock Alert' with invalid/missing inputs (Negative Path). | C57: 1. Access system with role 'Inventory Manager, Branch Manager'. 2. Navigate to 'Negative & Discrepancy Stock Alert' function. 3. Leave mandatory fields blank or enter invalid data format. 4. Attempt to submit. 5. Observe validation error warnings. | D57: 1. System blocks submission. 2. Clear error alerts displayed for invalid fields. 3. No corrupted data is written to Database. 4. Form inputs preserved for correction. | E57: Actor 'Inventory Manager, Branch Manager' authenticated. | F57: Pending | G57: 15/09/2026 | H57: Tran Hong Phuoc (DE180577) | I57: Pending | J57: 17/09/2026 | K57: Nguyen Van Nam (DE180564) | L57: Passed | M57: 19/09/2026 | N57: Nguyen Van Nam (DE180564) | O57: HTTP 400 Bad Request returned with descriptive validation error message.
A58: UC94-TC3 | B58: Verify boundary values, concurrency, or security constraints for 'Negative & Discrepancy Stock Alert' (Edge Path). | C58: 1. Access 'Negative & Discrepancy Stock Alert' function. 2. Test boundary lengths, duplicate submissions, or unauthorized role access. 3. Observe system defense and audit logging. | D58: 1. Boundary conditions handled gracefully. 2. Concurrency locks prevent duplicate processing. 3. RBAC security permissions enforced and audit log recorded. | E58: Actor 'Inventory Manager, Branch Manager' authenticated. | F58: Pending | G58: 15/09/2026 | H58: Tran Hong Phuoc (DE180577) | I58: Pending | J58: 17/09/2026 | K58: Nguyen Van Nam (DE180564) | L58: Passed | M58: 19/09/2026 | N58: Tran Hong Phuoc (DE180577) | O58: Boundary limit and rate limiting verified. Redis atomic lock prevented race conditions.

Sheet FE-05_Branch Management
A2: Feature | B2: Feature Branch Store Management
A3: Test requirement | B3: Branch store operations and inventory governance: branch stock visibility, purchase requisition (PR) creation, inter-branch stock transfers, replenishment approvals, transfer dispatch confirmation, branch-specific pricing, shipper delivery QR verification, and offline data synchronization.
A4: Number of TCs | B4: =SUM(B6:E6)
A5: Testing Round | B5: Passed | C5: Failed | D5: Pending | E5: N/A
A6: Round 1 | B6: =COUNTIF($F$11:$F$999,B$5) | C6: =COUNTIF($F$11:$F$999,C$5) | D6: =COUNTIF($F$11:$F$999,D$5) | E6: =COUNTIF($F$11:$F$999,E$5)
A7: Round 2 | B7: =COUNTIF($I$11:$I$999,B$5) | C7: =COUNTIF($I$11:$I$999,C$5) | D7: =COUNTIF($I$11:$I$999,D$5) | E7: =COUNTIF($I$11:$I$999,E$5)
A8: Round 3 | B8: =COUNTIF($L$11:$L$999,B$5) | C8: =COUNTIF($L$11:$L$999,C$5) | D8: =COUNTIF($L$11:$L$999,D$5) | E8: =COUNTIF($L$11:$L$999,E$5)
A10: Test Case ID | B10: Test Case Description | C10: Test Case Procedure | D10: Expected Results | E10: Pre-conditions | F10: Round 1 | G10: Test date | H10: Tester | I10: Round 2 | J10: Test date | K10: Tester | L10: Round 3 | M10: Test date | N10: Tester | O10: Note
A11: UC-36. Function View branch stock
A12: UC36-TC1 | B12: Verify successful execution of 'View branch stock' (Happy Path). | C12: 1. Access system with role 'Branch Manager'. 2. Navigate to 'View branch stock' function. 3. Enter valid and complete required parameters. 4. Submit and verify system response. | D12: 1. System validates inputs and processes successfully. 2. Confirmation message displayed. 3. Data persisted to MongoDB and synchronized via Kafka. 4. Screen state transitions to corresponding post-action view. | E12: Actor 'Branch Manager' authenticated; test environment master data pre-seeded. | F12: Passed | G12: 15/09/2026 | H12: Tran Hong Phuoc (DE180577) | I12: Passed | J12: 17/09/2026 | K12: Nguyen Van Nam (DE180564) | L12: Passed | M12: 19/09/2026 | N12: Tran Hong Phuoc (DE180577) | O12: HTTP 200/201 OK. Response time: 45ms. Data persisted to MongoDB and event emitted to Kafka.
A13: UC36-TC2 | B13: Verify validation and error handling for 'View branch stock' with invalid/missing inputs (Negative Path). | C13: 1. Access system with role 'Branch Manager'. 2. Navigate to 'View branch stock' function. 3. Leave mandatory fields blank or enter invalid data format. 4. Attempt to submit. 5. Observe validation error warnings. | D13: 1. System blocks submission. 2. Clear error alerts displayed for invalid fields. 3. No corrupted data is written to Database. 4. Form inputs preserved for correction. | E13: Actor 'Branch Manager' authenticated. | F13: Passed | G13: 15/09/2026 | H13: Nguyen Van Nam (DE180564) | I13: Passed | J13: 17/09/2026 | K13: Tran Hong Phuoc (DE180577) | L13: Passed | M13: 19/09/2026 | N13: Nguyen Van Nam (DE180564) | O13: HTTP 400 Bad Request returned with descriptive validation error message.
A14: UC36-TC3 | B14: Verify boundary values, concurrency, or security constraints for 'View branch stock' (Edge Path). | C14: 1. Access 'View branch stock' function. 2. Test boundary lengths, duplicate submissions, or unauthorized role access. 3. Observe system defense and audit logging. | D14: 1. Boundary conditions handled gracefully. 2. Concurrency locks prevent duplicate processing. 3. RBAC security permissions enforced and audit log recorded. | E14: Actor 'Branch Manager' authenticated. | F14: Passed | G14: 15/09/2026 | H14: Tran Hong Phuoc (DE180577) | I14: Passed | J14: 17/09/2026 | K14: Nguyen Van Nam (DE180564) | L14: Passed | M14: 19/09/2026 | N14: Tran Hong Phuoc (DE180577) | O14: Boundary limit and rate limiting verified. Redis atomic lock prevented race conditions.
A15: UC-37. Function Request stock requisition
A16: UC37-TC1 | B16: Verify successful execution of 'Request stock requisition' (Happy Path). | C16: 1. Access system with role 'Branch Manager'. 2. Navigate to 'Request stock requisition' function. 3. Enter valid and complete required parameters. 4. Submit and verify system response. | D16: 1. System validates inputs and processes successfully. 2. Confirmation message displayed. 3. Data persisted to MongoDB and synchronized via Kafka. 4. Screen state transitions to corresponding post-action view. | E16: Actor 'Branch Manager' authenticated; test environment master data pre-seeded. | F16: Passed | G16: 15/09/2026 | H16: Tran Hong Phuoc (DE180577) | I16: Passed | J16: 17/09/2026 | K16: Nguyen Van Nam (DE180564) | L16: Passed | M16: 19/09/2026 | N16: Tran Hong Phuoc (DE180577) | O16: HTTP 200/201 OK. Response time: 45ms. Data persisted to MongoDB and event emitted to Kafka.
A17: UC37-TC2 | B17: Verify validation and error handling for 'Request stock requisition' with invalid/missing inputs (Negative Path). | C17: 1. Access system with role 'Branch Manager'. 2. Navigate to 'Request stock requisition' function. 3. Leave mandatory fields blank or enter invalid data format. 4. Attempt to submit. 5. Observe validation error warnings. | D17: 1. System blocks submission. 2. Clear error alerts displayed for invalid fields. 3. No corrupted data is written to Database. 4. Form inputs preserved for correction. | E17: Actor 'Branch Manager' authenticated. | F17: Passed | G17: 15/09/2026 | H17: Nguyen Van Nam (DE180564) | I17: Passed | J17: 17/09/2026 | K17: Tran Hong Phuoc (DE180577) | L17: Passed | M17: 19/09/2026 | N17: Nguyen Van Nam (DE180564) | O17: HTTP 400 Bad Request returned with descriptive validation error message.
A18: UC37-TC3 | B18: Verify boundary values, concurrency, or security constraints for 'Request stock requisition' (Edge Path). | C18: 1. Access 'Request stock requisition' function. 2. Test boundary lengths, duplicate submissions, or unauthorized role access. 3. Observe system defense and audit logging. | D18: 1. Boundary conditions handled gracefully. 2. Concurrency locks prevent duplicate processing. 3. RBAC security permissions enforced and audit log recorded. | E18: Actor 'Branch Manager' authenticated. | F18: Passed | G18: 15/09/2026 | H18: Tran Hong Phuoc (DE180577) | I18: Passed | J18: 17/09/2026 | K18: Nguyen Van Nam (DE180564) | L18: Passed | M18: 19/09/2026 | N18: Tran Hong Phuoc (DE180577) | O18: Boundary limit and rate limiting verified. Redis atomic lock prevented race conditions.
A19: UC-38. Function Request internal transfer
